Workbook
Name _ftn1: 'Summary (2.8 PEA)'!#REF!
Name _ftn2: 'Summary (2.8 PEA)'!#REF!
Name _ftn3: 'Summary (2.8 PEA)'!#REF!
Name _ftn4: 'Summary (2.8 PEA)'!$A$90
Name _ftn5: 'Summary (2.8 PEA)'!$A$92
Name _ftn6: 'Summary (2.8 PEA)'!$A$93
Name _ftn7: 'Summary (2.8 PEA)'!$A$63
Name _ftnref1: 'Summary (2.8 PEA)'!#REF!
Name _ftnref2: 'Summary (2.8 PEA)'!#REF!
Name _ftnref3: 'Summary (2.8 PEA)'!#REF!
Name _ftnref4: 'Summary (2.8 PEA)'!$K$78
Name _ftnref5: 'Summary (2.8 PEA)'!#REF!
Name _ftnref6: 'Summary (2.8 PEA)'!$L$78
Name _ftnref7: 'Summary (2.8 PEA)'!#REF!
Name BaitSuppBC: '[1]BCA BAIT SUPP'!$C$28
Name BaitSuppBEP: '[1]BCA BAIT SUPP'!#REF!
Name BaitSuppIRR: '[1]BCA BAIT SUPP'!#REF!
Name BaitSuppNPV: '[1]BCA BAIT SUPP'!$C$27
Name BaitSuppPBP: '[1]BCA BAIT SUPP'!#REF!
Name BaitSuppROE: '[1]BCA BAIT SUPP'!#REF!
Name BufferArea: '[1]Land use'!$BK$14
Name CostCurrent: #REF!
Name CostHoneyLoss: #REF!
Name CostHumanHealth: #REF!
Name CostSecondaryOutbreaks: #REF!
Name CountryName: '[1]Land use'!$BK$11
Name CurrentBC: '[1]BCA COVER SPRAY'!$C$28
Name CurrentControlMethod: '[1]Current control strategy'!$C$5
Name CurrentNPV: '[1]BCA COVER SPRAY'!$C$27
Name CurrentPerCentLoss: '[1]Production - Inputs'!$N$21
Name CurrentTonnesOfPostHarvestTreatment: #REF!
Name CurrentYield: '[1]Background data'!#REF!
Name DiscountRate: '[1]Background data'!$C$6
Name ExchangeRate: '[1]Background data'!$C$9
Name FactoryCost: '[1]Flies and Factory'!$C$13
Name FactoryYesNo: '[1]Flies and Factory'!$C$8
Name FlyNonFliersBought: '[1]Flies and Factory'!$C$18
Name FlyNonFliersOwnFactory: '[1]Flies and Factory'!$C$11
Name LossCurrent: '[1]Prod and Marketing - Output'!$T$3
Name MarketLoss: '[1]Prod and Marketing - Output'!$AC$3
Name No: '[1]Flies and Factory'!$R$4
Name OrchardArea: '[1]Land use'!$BK$13
Name OtherHostArea: '[1]Land use'!$BK$16
Name PotentialProduction000T: #REF!
Name ProjectDuration: '[1]Background data'!$C$5
Name ResidualLossBait: '[1]Background data'!$C$12
Name ResidualLossSIT: '[1]Background data'!$C$13
Name SITSuppBC: '[1]BCA SIT SUPP'!$C$29
Name SITSUPPNPV: '[1]BCA SIT SUPP'!$C$28
Name SprayPrice: '[1]Background data'!#REF!
Name TotalArea: '[1]Land use'!$BK$18
Name TotalCostConvControl: #REF!
Name TotalOrchardRatio: '[1]Land use'!$BK$19
Name TrapServiceCost: #REF!
Name UrbanArea: '[1]Land use'!$BK$15
Name Yes: '[1]Flies and Factory'!$R$3
Name Yield: '[1]Background data'!#REF!
Name ZoneName: '[1]Land use'!$BK$12

Sheet Main - PEA
B1: Pesticide Environmental Accounting - User Interface Page

Sheet Integration Inputs
B1: Input and integration page of Pretty et al. data with Kovach et al. EIQ system
B5: Pretty et al. 2001 UK, USA and Germany (adjusted to 1996 prices)
C6: UK | E6: USA | G6: Germany | Q6: UK | S6: USA | U6: Germany
B7: Active Ingredient (a.i.) consumption kg (late 1990s) | C7: 22500000 | E7: 425000000 | G7: 26500000 | Q7: 22500000 | S7: 425000000 | U7: 26500000
C9: UK | E9: USA | G9: Germany | Q9: UK | S9: USA | U9: Germany
B10: 1996 GBP | C10: Cost | D10: Cost per Kg ai | E10: Cost | F10: Cost per Kg ai | G10: Cost | H10: Cost per Kg ai | Q10: Cost | R10: Cost per Kg ai | S10: Cost | T10: Cost per Kg ai | U10: Cost | V10: Cost per Kg ai
B11: Pesticides in sources of drinking water | C11: 120000000 | D11: =C11/C$7 -> 5.3333333 | E11: 592000000 | F11: =E11/E$7 -> 1.3929412 | G11: 58000000 | H11: =G11/G$7 -> 2.1886792 | Q11: 120000000 | R11: =Q11/Q$7 -> 5.3333333 | S11: 592000000 | T11: =S11/S$7 -> 1.3929412 | U11: 58000000 | V11: =U11/U$7 -> 2.1886792
B12: Pollution incidents, fish deaths and monitoring costs | C12: =0.5*17000000 -> 8500000 | D12: =C12/C$7 -> 0.37777778 | E12: =0.5*170000000 -> 85000000 | F12: =E12/E$7 -> 0.2 | G12: =0.5*33000000 -> 16500000 | H12: =G12/G$7 -> 0.62264151 | Q12: =0.5*17000000 -> 8500000 | R12: =Q12/Q$7 -> 0.37777778 | S12: =0.5*170000000 -> 85000000 | T12: =S12/S$7 -> 0.2 | U12: =0.5*33000000 -> 16500000 | V12: =U12/U$7 -> 0.62264151
B13: Biodiversity/wildlife losses | C13: =0.5*25000000 -> 12500000 | D13: =C13/C$7 -> 0.55555556 | E13: =0.5*218000000 -> 109000000 | F13: =E13/E$7 -> 0.25647059 | G13: =0.5*4000000 -> 2000000 | H13: =G13/G$7 -> 0.075471698 | Q13: =0.5*25000000 -> 12500000 | R13: =Q13/Q$7 -> 0.55555556 | S13: =0.5*218000000 -> 109000000 | T13: =S13/S$7 -> 0.25647059 | U13: =0.5*4000000 -> 2000000 | V13: =U13/U$7 -> 0.075471698
B14: Cultural, landscape, toursim etc. (Hedgerow and dry stone walls) | C14: =0.5*99000000 -> 49500000 | D14: =C14/C$7 -> 2.2 | F14: =E14/E$7 -> 0 | H14: =G14/G$7 -> 0 | Q14: =0.5*99000000 -> 49500000 | R14: =Q14/Q$7 -> 2.2 | T14: =S14/S$7 -> 0 | V14: =U14/U$7 -> 0
B15: Bee colony losses | C15: =0.5*2000000 -> 1000000 | D15: =C15/C$7 -> 0.044444444 | E15: =0.5*152000000 -> 76000000 | F15: =E15/E$7 -> 0.17882353 | G15: =0.5*1000000 -> 500000 | H15: =G15/G$7 -> 0.018867925 | Q15: =0.5*2000000 -> 1000000 | R15: =Q15/Q$7 -> 0.044444444 | S15: =0.5*152000000 -> 76000000 | T15: =S15/S$7 -> 0.17882353 | U15: =0.5*1000000 -> 500000 | V15: =U15/U$7 -> 0.018867925
B16: Acute effects of pesticides to human health | C16: 1000000 | D16: =C16/C$7 -> 0.044444444 | E16: 88000000 | F16: =E16/E$7 -> 0.20705882 | G16: 9000000 | H16: =G16/G$7 -> 0.33962264 | Q16: 1000000 | R16: =Q16/Q$7 -> 0.044444444 | S16: 88000000 | T16: =S16/S$7 -> 0.20705882 | U16: 9000000 | V16: =U16/U$7 -> 0.33962264
B17: Total | C17: =SUM(C11:C16) -> 192500000 | D17: =C17/C$7 -> 8.5555556 | E17: =SUM(E11:E16) -> 950000000 | F17: =E17/E$7 -> 2.2352941 | G17: =SUM(G11:G16) -> 86000000 | H17: =G17/G$7 -> 3.245283
B27: Inflation and Euro conversion of £ data | Q27: ='UK Deflator'!B6 -> 1996-97
C29: UK | E29: USA | G29: Germany | Q29: ='UK Deflator'!B7 -> 1997-98
B30: =_xlfn.CONCAT("20",RIGHT(H39,2))&" Euros" -> 2024 Euros | C30: Cost | D30: Cost per Kg ai | E30: Cost | F30: Cost per Kg ai | G30: Cost | H30: Cost per Kg ai | Q30: ='UK Deflator'!B8 -> 1998-99
B31: Pesticides in sources of drinking water | C31: ='UK Deflator'!E36 -> 2.584344e+08 | D31: =C31/C$7 -> 11.485973 | E31: ='US Deflator'!E36 -> 1.5335229e+09 | F31: =E31/E$7 -> 3.6082891 | G31: ='German Deflator'!E36 -> 2.1967524e+08 | H31: =G31/G$7 -> 8.2896315 | Q31: ='UK Deflator'!B9 -> 1999-00
B32: Pollution incidents, fish deaths and monitoring costs | C32: ='UK Deflator'!F36 -> 18305770 | D32: =C32/C$7 -> 0.81358979 | E32: ='US Deflator'!F36 -> 2.2018487e+08 | F32: =E32/E$7 -> 0.51808205 | G32: ='German Deflator'!F36 -> 62493817 | H32: =G32/G$7 -> 2.3582572 | Q32: ='UK Deflator'!B10 -> 2000-01
B33: Biodiversity/wildlife losses | C33: ='UK Deflator'!G36 -> 26920250 | D33: =C33/C$7 -> 1.1964556 | E33: ='US Deflator'!G36 -> 2.8235471e+08 | F33: =E33/E$7 -> 0.66436403 | G33: ='German Deflator'!G36 -> 7575008.1 | H33: =G33/G$7 -> 0.28584936 | Q33: ='UK Deflator'!B11 -> 2001-02
B34: Cultural, landscape, toursim etc. (Hedgerow and dry stone walls) | C34: ='UK Deflator'!H36 -> 1.0660419e+08 | D34: =C34/C$7 -> 4.7379641 | E34: ='US Deflator'!H36 -> 0 | F34: =E34/E$7 -> 0 | G34: ='German Deflator'!H36 -> 0 | H34: =G34/G$7 -> 0 | Q34: ='UK Deflator'!B12 -> 2002-03
B35: Bee colony losses | C35: ='UK Deflator'!I36 -> 2153620 | D35: =C35/C$7 -> 0.095716446 | E35: ='US Deflator'!I36 -> 1.9687118e+08 | F35: =E35/E$7 -> 0.4632263 | G35: ='German Deflator'!I36 -> 1893752 | H35: =G35/G$7 -> 0.071462341 | Q35: ='UK Deflator'!B13 -> 2003-04
B36: Acute effects of pesticides to human health | C36: ='UK Deflator'!I36 -> 2153620 | D36: =C36/C$7 -> 0.095716446 | E36: ='US Deflator'!J36 -> 2.279561e+08 | F36: =E36/E$7 -> 0.53636729 | G36: ='German Deflator'!J36 -> 34087537 | H36: =G36/G$7 -> 1.2863221 | Q36: ='UK Deflator'!B14 -> 2004-05
B37: Total | C37: =SUM(C31:C36) -> 4.1457185e+08 | D37: =C37/C$7 -> 18.425416 | E37: =SUM(E31:E36) -> 2.4608897e+09 | F37: =E37/E$7 -> 5.7903287 | G37: =SUM(G31:G36) -> 3.2572535e+08 | H37: =G37/G$7 -> 12.291523 | Q37: ='UK Deflator'!B15 -> 2005-06
Q38: ='UK Deflator'!B16 -> 2006-07
G39: Inflate to Year: | H39: 2023-24 | Q39: ='UK Deflator'!B17 -> 2007-08
C40: Mean Cost per Kg ai | Q40: ='UK Deflator'!B18 -> 2008-09
B41: Pesticides in sources of drinking water | C41: =AVERAGE(D31,F31,H31) -> 7.7946314 | Q41: ='UK Deflator'!B19 -> 2009-10
B42: Pollution incidents, fish deaths and monitoring costs | C42: =AVERAGE(D32,F32,H32) -> 1.2299764 | Q42: ='UK Deflator'!B27 -> 2017-18
B43: Biodiversity/wildlife losses | C43: =AVERAGE(D33,F33,H33) -> 0.71555632 | Q43: ='UK Deflator'!B28 -> 2018-19
B44: Cultural, landscape, toursim etc. (Hedgerows, dry stone walls, perception of spraying) | C44: =AVERAGE(D34,F34,H34) -> 1.5793214 | Q44: ='UK Deflator'!B29 -> 2019-20
B45: Bee colony losses | C45: =AVERAGE(D35,F35,H35) -> 0.21013503 | Q45: ='UK Deflator'!B30 -> 2020-21
B46: Acute effects of pesticides to human health | C46: =AVERAGE(D36,F36,H36) -> 0.63946862 | Q46: ='UK Deflator'!B31 -> 2021-22
B47: Total | C47: =AVERAGE(D37,F37,H37) -> 12.169089 | Q47: ='UK Deflator'!B32 -> 2022-23
Q48: ='UK Deflator'!B33 -> 2023-24
B50: Distribution of Pretty et al. costs over Kovachs et al EIQ system | C50: Pesticides in sources of drinking water | D50: Pollution incidents, fish deaths and monitoring costs | E50: Biodiversity / wildlife losses | F50: Landscape / Cultural / tourism value | G50: Bee colony losses | H50: Acute effects of pesticides to human health
A51: human | B51: human | C51: 1 | H51: 1 | V51: 0.8
A52: env | B52: env | D52: 0.5 | F52: 1 | V52: 0.15
A53: ecoterr | B53: ecoterr | E53: 0.5 | G53: 1 | Q53: 1 | T53: 0.5 | V53: 0.05
A54: ecoaqu | B54: ecoaqu | D54: 0.5 | E54: 0.5 | R54: 0.5
R55: 0.5 | S55: 0.3
S56: 0.3 | T56: 0.2
S57: 0.1 | T57: 0.1 | U57: 1
S58: 0.3 | T58: 0.2
C59: =SUM(C51:C58) -> 1 | D59: =SUM(D51:D58) -> 1 | E59: =SUM(E51:E58) -> 1 | F59: =SUM(F51:F58) -> 1 | G59: =SUM(G51:G58) -> 1 | H59: =SUM(H51:H58) -> 1
B62: Cost application for moderate EIQ compound | C62: Pesticides in sources of drinking water | D62: Pollution incidents, fish deaths and monitoring costs | E62: Biodiversity / wildlife losses | F62: Landscape / Cultural / tourism value | G62: Bee colony losses | H62: Acute effects of pesticides to human health | I62: Total
A63: human | B63: human | C63: =$C$41*C51 -> 7.7946314 | D63: =$C$42*D51 -> 0 | E63: =$C$43*E51 -> 0 | F63: =$C$44*F51 -> 0 | G63: =$C$45*G51 -> 0 | H63: =$C$46*H51 -> 0.63946862 | I63: =SUM(C63:H63) -> 8.4341
A64: env | B64: env | C64: =$C$41*C52 -> 0 | D64: =$C$42*D52 -> 0.61498818 | E64: =$C$43*E52 -> 0 | F64: =$C$44*F52 -> 1.5793214 | G64: =$C$45*G52 -> 0 | H64: =$C$46*H52 -> 0 | I64: =SUM(C64:H64) -> 2.1943095
A65: ecoterr | B65: ecoterr | C65: =$C$41*C53 -> 0 | D65: =$C$42*D53 -> 0 | E65: =$C$43*E53 -> 0.35777816 | F65: =$C$44*F53 -> 0 | G65: =$C$45*G53 -> 0.21013503 | H65: =$C$46*H53 -> 0 | I65: =SUM(C65:H65) -> 0.56791319
A66: ecoaqu | B66: ecoaqu | C66: =$C$41*C54 -> 0 | D66: =$C$42*D54 -> 0.61498818 | E66: =$C$43*E54 -> 0.35777816 | F66: =$C$44*F54 -> 0 | G66: =$C$45*G54 -> 0 | H66: =$C$46*H54 -> 0 | I66: =SUM(C66:H66) -> 0.97276634
C67: =$C$41*C55 -> 0 | D67: =$C$42*D55 -> 0 | E67: =$C$43*E55 -> 0 | F67: =$C$44*F55 -> 0 | G67: =$C$45*G55 -> 0 | H67: =$C$46*H55 -> 0 | I67: =SUM(C67:H67) -> 0
C68: =$C$41*C56 -> 0 | D68: =$C$42*D56 -> 0 | E68: =$C$43*E56 -> 0 | F68: =$C$44*F56 -> 0 | G68: =$C$45*G56 -> 0 | H68: =$C$46*H56 -> 0 | I68: =SUM(C68:H68) -> 0
C69: =$C$41*C57 -> 0 | D69: =$C$42*D57 -> 0 | E69: =$C$43*E57 -> 0 | F69: =$C$44*F57 -> 0 | G69: =$C$45*G57 -> 0 | H69: =$C$46*H57 -> 0 | I69: =SUM(C69:H69) -> 0
C70: =$C$41*C58 -> 0 | D70: =$C$42*D58 -> 0 | E70: =$C$43*E58 -> 0 | F70: =$C$44*F58 -> 0 | G70: =$C$45*G58 -> 0 | H70: =$C$46*H58 -> 0 | I70: =SUM(C70:H70) -> 0
C71: =SUM(C63:C70) -> 7.7946314 | D71: =SUM(D63:D70) -> 1.2299764 | E71: =SUM(E63:E70) -> 0.71555632 | F71: =SUM(F63:F70) -> 1.5793214 | G71: =SUM(G63:G70) -> 0.21013503 | H71: =SUM(H63:H70) -> 0.63946862 | I71: =SUM(C71:H71) -> 12.169089
B75: EIQs | C75: Lowest possible | D75: Low max | E75: Middle | F75: Middle max | G75: Highest possible
B76: human | C76: 0 | D76: =(E76+C76)/2 -> 0.5 | E76: 1 | F76: =(G76+E76)/2 -> 1.25 | G76: 1.5
B77: env | C77: 0 | D77: =(E77+C77)/2 -> 0.5 | E77: 1 | F77: =(G77+E77)/2 -> 1.25 | G77: 1.5
B78: ecoterr | C78: 0 | D78: =(E78+C78)/2 -> 0.5 | E78: 1 | F78: =(G78+E78)/2 -> 1.25 | G78: 1.5
B79: ecoaqu | C79: 0 | D79: =(E79+C79)/2 -> 0.5 | E79: 1 | F79: =(G79+E79)/2 -> 1.25 | G79: 1.5
C80: 0 | D80: 0 | E80: 0 | F80: 0 | G80: 0
C81: 0 | D81: 0 | E81: 0 | F81: 0 | G81: 0
C82: 0 | D82: 0 | E82: 0 | F82: 0 | G82: 0
C83: 0 | D83: 0 | E83: 0 | F83: 0 | G83: 0
C84: 0 | D84: 0 | E84: 0 | F84: 0 | G84: 0
C85: 0 | D85: 0 | E85: 0 | F85: 0 | G85: 0
C86: 0 | D86: 0 | E86: 0 | F86: 0 | G86: 0
B87: EIQ = | C87: 6.7 | E87: 70 | G87: 210
C90: Low | D90: Middle | E90: High
B91: Cost multipliers for three levels of EIQ | C91: 0.5 | D91: 1 | E91: 1.5 | Q91: 0.5 | R91: 1 | S91: 2

Sheet UK Deflator
B2: Source: | C2: https://www.gov.uk/government/uploads/system/uploads/attachment_data/file/624527/GDP_Deflators_Qtrly_National_Accounts_June_2017_update.csv/preview
B4: GDP deflator at market prices
B5: Financial Year | D5: % change on previous year | E5: ='Integration Inputs'!B11 -> Pesticides in sources of drinking water | F5: ='Integration Inputs'!B12 -> Pollution incidents, fish deaths and monitoring costs | G5: ='Integration Inputs'!B13 -> Biodiversity/wildlife losses | H5: ='Integration Inputs'!B14 -> Cultural, landscape, toursim etc. (Hedgerow and dry stone walls) | I5: ='Integration Inputs'!B15 -> Bee colony losses | J5: ='Integration Inputs'!B16 -> Acute effects of pesticides to human health
B6: 1996-97 | C6: 52.6908 | D6: 3.3929402 | E6: ='Integration Inputs'!C11 -> 120000000 | F6: ='Integration Inputs'!C12 -> 8500000 | G6: ='Integration Inputs'!C13 -> 12500000 | H6: ='Integration Inputs'!C14 -> 49500000 | I6: ='Integration Inputs'!C15 -> 1000000 | J6: ='Integration Inputs'!C16 -> 1000000
B7: 1997-98 | C7: 52.6858 | D7: -0.0094893226 | E7: =E6*(1+($D7/100)) -> 1.1998861e+08 | F7: =F6*(1+($D7/100)) -> 8499193.4 | G7: =G6*(1+($D7/100)) -> 12498814 | H7: =H6*(1+($D7/100)) -> 49495303 | I7: =I6*(1+($D7/100)) -> 999905.11 | J7: =J6*(1+($D7/100)) -> 999905.11
B8: 1998-99 | C8: 53.4132 | D8: 1.3806377 | E8: =E7*(1+($D8/100)) -> 1.2164522e+08 | F8: =F7*(1+($D8/100)) -> 8616536.5 | G8: =G7*(1+($D8/100)) -> 12671377 | H8: =H7*(1+($D8/100)) -> 50178654 | I8: =I7*(1+($D8/100)) -> 1013710.2 | J8: =J7*(1+($D8/100)) -> 1013710.2
B9: 1999-00 | C9: 54.1182 | D9: 1.3198985 | E9: =E8*(1+($D9/100)) -> 1.2325081e+08 | F9: =F8*(1+($D9/100)) -> 8730266 | G9: =G8*(1+($D9/100)) -> 12838626 | H9: =H8*(1+($D9/100)) -> 50840961 | I9: =I8*(1+($D9/100)) -> 1027090.1 | J9: =J8*(1+($D9/100)) -> 1027090.1
B10: 2000-01 | C10: 54.6511 | D10: 0.98469646 | E10: =E9*(1+($D10/100)) -> 1.2446446e+08 | F10: =F9*(1+($D10/100)) -> 8816232.6 | G10: =G9*(1+($D10/100)) -> 12965048 | H10: =H9*(1+($D10/100)) -> 51341590 | I10: =I9*(1+($D10/100)) -> 1037203.8 | J10: =J9*(1+($D10/100)) -> 1037203.8
B11: 2001-02 | C11: 55.6035 | D11: 1.7426914 | E11: =E10*(1+($D11/100)) -> 1.2663349e+08 | F11: =F10*(1+($D11/100)) -> 8969872.3 | G11: =G10*(1+($D11/100)) -> 13190989 | H11: =H10*(1+($D11/100)) -> 52236315 | I11: =I10*(1+($D11/100)) -> 1055279.1 | J11: =J10*(1+($D11/100)) -> 1055279.1
B12: 2002-03 | C12: 56.8499 | D12: 2.2415855 | E12: =E11*(1+($D12/100)) -> 1.2947209e+08 | F12: =F11*(1+($D12/100)) -> 9170939.7 | G12: =G11*(1+($D12/100)) -> 13486676 | H12: =H11*(1+($D12/100)) -> 53407237 | I12: =I11*(1+($D12/100)) -> 1078934.1 | J12: =J11*(1+($D12/100)) -> 1078934.1
B13: 2003-04 | C13: 58.1359 | D13: 2.2620972 | E13: =E12*(1+($D13/100)) -> 1.3240087e+08 | F13: =F12*(1+($D13/100)) -> 9378395.3 | G13: =G12*(1+($D13/100)) -> 13791758 | H13: =H12*(1+($D13/100)) -> 54615361 | I13: =I12*(1+($D13/100)) -> 1103340.6 | J13: =J12*(1+($D13/100)) -> 1103340.6
B14: 2004-05 | C14: 59.8765 | D14: 2.9940192 | E14: =E13*(1+($D14/100)) -> 1.3636498e+08 | F14: =F13*(1+($D14/100)) -> 9659186.2 | G14: =G13*(1+($D14/100)) -> 14204686 | H14: =H13*(1+($D14/100)) -> 56250555 | I14: =I13*(1+($D14/100)) -> 1136374.9 | J14: =J13*(1+($D14/100)) -> 1136374.9
B15: 2005-06 | C15: 61.5117 | D15: 2.7309545 | E15: =E14*(1+($D15/100)) -> 1.4008905e+08 | F15: =F14*(1+($D15/100)) -> 9922974.2 | G15: =G14*(1+($D15/100)) -> 14592609 | H15: =H14*(1+($D15/100)) -> 57786732 | I15: =I14*(1+($D15/100)) -> 1167408.7 | J15: =J14*(1+($D15/100)) -> 1167408.7
B16: 2006-07 | C16: 63.1664 | D16: 2.6900573 | E16: =E15*(1+($D16/100)) -> 1.4385752e+08 | F16: =F15*(1+($D16/100)) -> 10189908 | G16: =G15*(1+($D16/100)) -> 14985159 | H16: =H15*(1+($D16/100)) -> 59341228 | I16: =I15*(1+($D16/100)) -> 1198812.7 | J16: =J15*(1+($D16/100)) -> 1198812.7
B17: 2007-08 | C17: 64.6979 | D17: 2.4245485 | E17: =E16*(1+($D17/100)) -> 1.4734542e+08 | F17: =F16*(1+($D17/100)) -> 10436967 | G17: =G16*(1+($D17/100)) -> 15348481 | H17: =H16*(1+($D17/100)) -> 60779985 | I17: =I16*(1+($D17/100)) -> 1227878.5 | J17: =J16*(1+($D17/100)) -> 1227878.5
B18: 2008-09 | C18: 67.0377 | D18: 3.6165007 | E18: =E17*(1+($D18/100)) -> 1.5267417e+08 | F18: =F17*(1+($D18/100)) -> 10814420 | G18: =G17*(1+($D18/100)) -> 15903559 | H18: =H17*(1+($D18/100)) -> 62978094 | I18: =I17*(1+($D18/100)) -> 1272284.7 | J18: =J17*(1+($D18/100)) -> 1272284.7
... B34: 2024-25 | C34: 100 | D34: 4.0685604 | E34: =E33*(1+($D34/100)) -> 2.2774374e+08 | F34: =F33*(1+($D34/100)) -> 16131848 | G34: =G33*(1+($D34/100)) -> 23723307 | H34: =H33*(1+($D34/100)) -> 93944294 | I34: =I33*(1+($D34/100)) -> 1897864.5 | J34: =J33*(1+($D34/100)) -> 1897864.5
C36: OUTPUT USED BY INTEGRATION PAGE: | D36: ='Integration Inputs'!H39 -> 2023-24 | E36: =VLOOKUP(D36,B6:J34,4)*VLOOKUP(D36,B43:D69,3) -> 2.584344e+08 | F36: =VLOOKUP(D36,B6:J34,5)*VLOOKUP(D36,B43:D69,3) -> 18305770 | G36: =VLOOKUP(D36,B6:J34,6)*VLOOKUP(D36,B43:D69,3) -> 26920250 | H36: =VLOOKUP(D36,B6:J34,7)*VLOOKUP(D36,B43:D69,3) -> 1.0660419e+08 | I36: =VLOOKUP(D36,B6:J34,8)*VLOOKUP(D36,B43:D69,3) -> 2153620 | J36: =VLOOKUP(D36,B6:J34,9)*VLOOKUP(D36,B43:D69,3) -> 2153620
C40: Source: | D40: https://www.ofx.com/en-gb/forex-news/historical-exchange-rates/ | H40: 45896
B43: 1998-99 | C43: £ to Euros 1999 | D43: 1.51912
B44: 1999-00 | C44: £ to Euros 2000 | D44: 1.64254
B45: 2000-01 | C45: £ to Euros 2001 | D45: 1.60905
B46: 2001-02 | C46: £ to Euros 2002 | D46: 1.59165
B47: 2002-03 | C47: £ to Euros 2003 | D47: 1.44615
B48: 2003-04 | C48: £ to Euros 2004 | D48: 1.47477
B49: 2004-05 | C49: £ to Euros 2005 | D49: 1.46081
B50: 2005-06 | C50: £ to Euros 2006 | D50: 1.466612
B51: 2006-07 | C51: £ to Euros 2007 | D51: 1.461786
B52: 2007-08 | C52: £ to Euros 2008 | D52: 1.259467
B53: 2008-09 | C53: £ to Euros 2009 | D53: 1.12246
B54: 2009-10 | C54: £ to Euros 2010 | D54: 1.165737
... B69: 2024-25 | C69: £ to Euros 2025 | D69: 1.178907

Sheet US Deflator
B2: Source: | C2: https://www.gpo.gov/fdsys/search/search.action?na=__publishdatehier&se=__2017false&sm=&flr=&ercode=&dateBrowse=&govAuthBrowse=&collection=&historical=false&st=GDP+deflators&psh=&sbh=&tfh=&originalSearch=GDP+deflators&fromState=&sb=re&ps=10&sb=re&ps=10
B4: GDP deflator at market prices
B5: Financial Year | C5: 2009=100 | D5: % change on previous year | E5: ='Integration Inputs'!B11 -> Pesticides in sources of drinking water | F5: ='Integration Inputs'!B12 -> Pollution incidents, fish deaths and monitoring costs | G5: ='Integration Inputs'!B13 -> Biodiversity/wildlife losses | H5: ='Integration Inputs'!B14 -> Cultural, landscape, toursim etc. (Hedgerow and dry stone walls) | I5: ='Integration Inputs'!B15 -> Bee colony losses | J5: ='Integration Inputs'!B16 -> Acute effects of pesticides to human health
B6: 1996-97 | C6: 68.164 | D6: 1.8300244 | E6: ='Integration Inputs'!E11*D39 -> 9.2492896e+08 | F6: ='Integration Inputs'!E12*D39 -> 1.328023e+08 | G6: ='Integration Inputs'!E13*D39 -> 170299420 | H6: ='Integration Inputs'!E14*D39 -> 0 | I6: ='Integration Inputs'!E15*D39 -> 1.1874088e+08 | J6: ='Integration Inputs'!E16*D39 -> 137489440
B7: 1997-98 | C7: 69.34 | D7: 1.7252509 | E7: =E6*(1+($D7/100)) -> 9.408863e+08 | F7: =F6*(1+($D7/100)) -> 1.3509347e+08 | G7: =G6*(1+($D7/100)) -> 1.7323751e+08 | H7: =H6*(1+($D7/100)) -> 0 | I7: =I6*(1+($D7/100)) -> 1.2078946e+08 | J7: =J6*(1+($D7/100)) -> 1.3986148e+08
B8: 1998-99 | C8: 70.119 | D8: 1.1234497 | E8: =E7*(1+($D8/100)) -> 9.5145669e+08 | F8: =F7*(1+($D8/100)) -> 1.3661118e+08 | G8: =G7*(1+($D8/100)) -> 1.7518375e+08 | H8: =H7*(1+($D8/100)) -> 0 | I8: =I7*(1+($D8/100)) -> 1.2214647e+08 | J8: =J7*(1+($D8/100)) -> 1.4143275e+08
B9: 1999-00 | C9: 71.111 | D9: 1.4147378 | E9: =E8*(1+($D9/100)) -> 9.6491731e+08 | F9: =F8*(1+($D9/100)) -> 1.3854387e+08 | G9: =G8*(1+($D9/100)) -> 1.7766214e+08 | H9: =H8*(1+($D9/100)) -> 0 | I9: =I8*(1+($D9/100)) -> 1.2387452e+08 | J9: =J8*(1+($D9/100)) -> 1.4343365e+08
B10: 2000-01 | C10: 72.722 | D10: 2.2654723 | E10: =E9*(1+($D10/100)) -> 9.8677724e+08 | F10: =F9*(1+($D10/100)) -> 1.4168254e+08 | G10: =G9*(1+($D10/100)) -> 1.8168703e+08 | H10: =H9*(1+($D10/100)) -> 0 | I10: =I9*(1+($D10/100)) -> 1.2668086e+08 | J10: =J9*(1+($D10/100)) -> 1.466831e+08
B11: 2001-02 | C11: 74.36 | D11: 2.2524133 | E11: =E10*(1+($D11/100)) -> 1.0090035e+09 | F11: =F10*(1+($D11/100)) -> 1.4487382e+08 | G11: =G10*(1+($D11/100)) -> 1.8577937e+08 | H11: =H10*(1+($D11/100)) -> 0 | I11: =I10*(1+($D11/100)) -> 1.2953424e+08 | J11: =J10*(1+($D11/100)) -> 1.4998701e+08
B12: 2002-03 | C12: 75.515 | D12: 1.5532544 | E12: =E11*(1+($D12/100)) -> 1.0246759e+09 | F12: =F11*(1+($D12/100)) -> 1.4712408e+08 | G12: =G11*(1+($D12/100)) -> 1.8866499e+08 | H12: =H11*(1+($D12/100)) -> 0 | I12: =I11*(1+($D12/100)) -> 1.3154623e+08 | J12: =J11*(1+($D12/100)) -> 1.5231669e+08
B13: 2003-04 | C13: 77.006 | D13: 1.9744422 | E13: =E12*(1+($D13/100)) -> 1.0449076e+09 | F13: =F12*(1+($D13/100)) -> 1.5002896e+08 | G13: =G12*(1+($D13/100)) -> 1.9239008e+08 | H13: =H12*(1+($D13/100)) -> 0 | I13: =I12*(1+($D13/100)) -> 1.3414354e+08 | J13: =J12*(1+($D13/100)) -> 1.553241e+08
B14: 2004-05 | C14: 79.077 | D14: 2.6894008 | E14: =E13*(1+($D14/100)) -> 1.0730093e+09 | F14: =F13*(1+($D14/100)) -> 1.5406384e+08 | G14: =G13*(1+($D14/100)) -> 1.9756422e+08 | H14: =H13*(1+($D14/100)) -> 0 | I14: =I13*(1+($D14/100)) -> 1.377512e+08 | J14: =J13*(1+($D14/100)) -> 1.5950139e+08
B15: 2005-06 | C15: 81.556 | D15: 3.1349191 | E15: =E14*(1+($D15/100)) -> 1.1066473e+09 | F15: =F14*(1+($D15/100)) -> 1.5889362e+08 | G15: =G14*(1+($D15/100)) -> 2.0375769e+08 | H15: =H14*(1+($D15/100)) -> 0 | I15: =I14*(1+($D15/100)) -> 1.4206959e+08 | J15: =J14*(1+($D15/100)) -> 1.6450163e+08
B16: 2006-07 | C16: 84.071 | D16: 3.0837707 | E16: =E15*(1+($D16/100)) -> 1.1407738e+09 | F16: =F15*(1+($D16/100)) -> 1.6379353e+08 | G16: =G15*(1+($D16/100)) -> 2.1004111e+08 | H16: =H15*(1+($D16/100)) -> 0 | I16: =I15*(1+($D16/100)) -> 1.4645069e+08 | J16: =J15*(1+($D16/100)) -> 1.6957448e+08
B17: 2007-08 | C17: 86.349 | D17: 2.7096145 | E17: =E16*(1+($D17/100)) -> 1.1716843e+09 | F17: =F16*(1+($D17/100)) -> 1.682317e+08 | G17: =G16*(1+($D17/100)) -> 2.1573242e+08 | H17: =H16*(1+($D17/100)) -> 0 | I17: =I16*(1+($D17/100)) -> 1.5041893e+08 | J17: =J16*(1+($D17/100)) -> 1.7416929e+08
B18: 2008-09 | C18: 88.013 | D18: 1.9270634 | E18: =E17*(1+($D18/100)) -> 1.1942634e+09 | F18: =F17*(1+($D18/100)) -> 1.7147363e+08 | G18: =G17*(1+($D18/100)) -> 2.1988972e+08 | H18: =H17*(1+($D18/100)) -> 0 | I18: =I17*(1+($D18/100)) -> 1.533176e+08 | J18: =J17*(1+($D18/100)) -> 1.7752565e+08
... B34: 2024-25 | C34: 125.23 | D34: 2.4183589 | E34: =E33*(1+($D34/100)) -> 1.6992673e+09 | F34: =F33*(1+($D34/100)) -> 2.4398263e+08 | G34: =G33*(1+($D34/100)) -> 3.1287184e+08 | H34: =H33*(1+($D34/100)) -> 0 | I34: =I33*(1+($D34/100)) -> 2.1814918e+08 | J34: =J33*(1+($D34/100)) -> 2.5259378e+08
C36: OUTPUT USED BY INTEGRATION PAGE: | D36: ='Integration Inputs'!H39 -> 2023-24 | E36: =VLOOKUP(D36,B6:J34,4)*VLOOKUP(D36,B41:D67,3) -> 1.5335229e+09 | F36: =VLOOKUP(D36,B6:J34,5)*VLOOKUP(D36,B41:D67,3) -> 2.2018487e+08 | G36: =VLOOKUP(D36,B6:J34,6)*VLOOKUP(D36,B41:D67,3) -> 2.8235471e+08 | H36: =VLOOKUP(D36,B6:J34,7)*VLOOKUP(D36,B41:D67,3) -> 0 | I36: =VLOOKUP(D36,B6:J34,8)*VLOOKUP(D36,B41:D67,3) -> 1.9687118e+08 | J36: =VLOOKUP(D36,B6:J34,9)*VLOOKUP(D36,B41:D67,3) -> 2.279561e+08
C38: Source: | D38: https://www.ofx.com/en-gb/forex-news/historical-exchange-rates/ | H38: 45894
C39: £ to USD Average 1996 | D39: 1.56238
B41: 1998-99 | C41: $ to Euro 1999 | D41: 0.939283
B42: 1999-00 | C42: $ to Euro 2000 | D42: 1.085947
B43: 2000-01 | C43: $ to Euro 2001 | D43: 1.117082
B44: 2001-02 | C44: $ to Euro 2002 | D44: 1.064385
B45: 2002-03 | C45: $ to Euro 2003 | D45: 0.883383
B46: 2003-04 | C46: $ to Euro 2004 | D46: 0.80471
B47: 2004-05 | C47: $ to Euro 2005 | D47: 0.803857
B48: 2005-06 | C48: $ to Euro 2006 | D48: 0.796727
B49: 2006-07 | C49: $ to Euro 2007 | D49: 0.730785
B50: 2007-08 | C50: $ to Euro 2008 | D50: 0.683075
B51: 2008-09 | C51: $ to Euro 2009 | D51: 0.719039
B52: 2009-10 | C52: $ to Euro 2010 | D52: 0.754908
... B67: 2024-25 | C67: $ to Euro 2025 | D67: 0.901311

Sheet German Deflator
B2: Source: | C2: http://data.worldbank.org/indicator/NY.GDP.DEFL.KD.ZG
B4: GDP deflator at market prices
B5: Financial Year | D5: % change on previous year | E5: ='Integration Inputs'!B11 -> Pesticides in sources of drinking water | F5: ='Integration Inputs'!B12 -> Pollution incidents, fish deaths and monitoring costs | G5: ='Integration Inputs'!B13 -> Biodiversity/wildlife losses | H5: ='Integration Inputs'!B14 -> Cultural, landscape, toursim etc. (Hedgerow and dry stone walls) | I5: ='Integration Inputs'!B15 -> Bee colony losses | J5: ='Integration Inputs'!B16 -> Acute effects of pesticides to human health
B6: 1996-97 | C6: 74.7 | D6: 0.1 | E6: ='Integration Inputs'!G11*D41 -> 136370180 | F6: ='Integration Inputs'!G12*D41 -> 38794965 | G6: ='Integration Inputs'!G13*D41 -> 4702420 | H6: ='Integration Inputs'!G14*D41 -> 0 | I6: ='Integration Inputs'!G15*D41 -> 1175605 | J6: ='Integration Inputs'!G16*D41 -> 21160890
B7: 1997-98 | C7: 75.2 | D7: 0.7 | E7: =E6*(1+($D7/100)) -> 1.3732477e+08 | F7: =F6*(1+($D7/100)) -> 39066530 | G7: =G6*(1+($D7/100)) -> 4735336.9 | H7: =H6*(1+($D7/100)) -> 0 | I7: =I6*(1+($D7/100)) -> 1183834.2 | J7: =J6*(1+($D7/100)) -> 21309016
B8: 1998-99 | C8: 75.6 | D8: 0.6 | E8: =E7*(1+($D8/100)) -> 1.3814872e+08 | F8: =F7*(1+($D8/100)) -> 39300929 | G8: =G7*(1+($D8/100)) -> 4763749 | H8: =H7*(1+($D8/100)) -> 0 | I8: =I7*(1+($D8/100)) -> 1190937.2 | J8: =J7*(1+($D8/100)) -> 21436870
B9: 1999-00 | C9: 75.3 | D9: -0.3 | E9: =E8*(1+($D9/100)) -> 1.3773427e+08 | F9: =F8*(1+($D9/100)) -> 39183026 | G9: =G8*(1+($D9/100)) -> 4749457.7 | H9: =H8*(1+($D9/100)) -> 0 | I9: =I8*(1+($D9/100)) -> 1187364.4 | J9: =J8*(1+($D9/100)) -> 21372560
B10: 2000-01 | C10: 76.4 | D10: 1.4 | E10: =E9*(1+($D10/100)) -> 1.3966255e+08 | F10: =F9*(1+($D10/100)) -> 39731589 | G10: =G9*(1+($D10/100)) -> 4815950.1 | H10: =H9*(1+($D10/100)) -> 0 | I10: =I9*(1+($D10/100)) -> 1203987.5 | J10: =J9*(1+($D10/100)) -> 21671776
B11: 2001-02 | C11: 77.6 | D11: 1.5 | E11: =E10*(1+($D11/100)) -> 1.4175749e+08 | F11: =F10*(1+($D11/100)) -> 40327562 | G11: =G10*(1+($D11/100)) -> 4888189.4 | H11: =H10*(1+($D11/100)) -> 0 | I11: =I10*(1+($D11/100)) -> 1222047.3 | J11: =J10*(1+($D11/100)) -> 21996852
B12: 2002-03 | C12: 78.6 | D12: 1.3 | E12: =E11*(1+($D12/100)) -> 1.4360034e+08 | F12: =F11*(1+($D12/100)) -> 40851821 | G12: =G11*(1+($D12/100)) -> 4951735.8 | H12: =H11*(1+($D12/100)) -> 0 | I12: =I11*(1+($D12/100)) -> 1237934 | J12: =J11*(1+($D12/100)) -> 22282811
B13: 2003-04 | C13: 79.5 | D13: 1.2 | E13: =E12*(1+($D13/100)) -> 1.4532354e+08 | F13: =F12*(1+($D13/100)) -> 41342042 | G13: =G12*(1+($D13/100)) -> 5011156.7 | H13: =H12*(1+($D13/100)) -> 0 | I13: =I12*(1+($D13/100)) -> 1252789.2 | J13: =J12*(1+($D13/100)) -> 22550205
B14: 2004-05 | C14: 79.9 | D14: 0.5 | E14: =E13*(1+($D14/100)) -> 1.4605016e+08 | F14: =F13*(1+($D14/100)) -> 41548753 | G14: =G13*(1+($D14/100)) -> 5036212.4 | H14: =H13*(1+($D14/100)) -> 0 | I14: =I13*(1+($D14/100)) -> 1259053.1 | J14: =J13*(1+($D14/100)) -> 22662956
B15: 2005-06 | C15: 80.3 | D15: 0.4 | E15: =E14*(1+($D15/100)) -> 1.4663436e+08 | F15: =F14*(1+($D15/100)) -> 41714948 | G15: =G14*(1+($D15/100)) -> 5056357.3 | H15: =H14*(1+($D15/100)) -> 0 | I15: =I14*(1+($D15/100)) -> 1264089.3 | J15: =J14*(1+($D15/100)) -> 22753608
B16: 2006-07 | C16: 81.8 | D16: 1.8 | E16: =E15*(1+($D16/100)) -> 1.4927378e+08 | F16: =F15*(1+($D16/100)) -> 42465817 | G16: =G15*(1+($D16/100)) -> 5147371.7 | H16: =H15*(1+($D16/100)) -> 0 | I16: =I15*(1+($D16/100)) -> 1286842.9 | J16: =J15*(1+($D16/100)) -> 23163173
B17: 2007-08 | C17: 82.5 | D17: 1 | E17: =E16*(1+($D17/100)) -> 1.5076652e+08 | F17: =F16*(1+($D17/100)) -> 42890475 | G17: =G16*(1+($D17/100)) -> 5198845.4 | H17: =H16*(1+($D17/100)) -> 0 | I17: =I16*(1+($D17/100)) -> 1299711.4 | J17: =J16*(1+($D17/100)) -> 23394805
B18: 2008-09 | C18: 84.2 | D18: 2 | E18: =E17*(1+($D18/100)) -> 1.5378185e+08 | F18: =F17*(1+($D18/100)) -> 43748284 | G18: =G17*(1+($D18/100)) -> 5302822.4 | H18: =H17*(1+($D18/100)) -> 0 | I18: =I17*(1+($D18/100)) -> 1325705.6 | J18: =J17*(1+($D18/100)) -> 23862701
... B33: 2023-24 | C33: 120.2 | D33: 3.1 | E33: =E32*(1+($D33/100)) -> 2.1967524e+08 | F33: =F32*(1+($D33/100)) -> 62493817 | G33: =G32*(1+($D33/100)) -> 7575008.1 | H33: =H32*(1+($D33/100)) -> 0 | I33: =I32*(1+($D33/100)) -> 1893752 | J33: =J32*(1+($D33/100)) -> 34087537
C36: OUTPUT USED BY INTEGRATION PAGE: | D36: ='Integration Inputs'!H39 -> 2023-24 | E36: =VLOOKUP(D36,B6:J33,4)*VLOOKUP(D36,B43:D61,3) -> 2.1967524e+08 | F36: =VLOOKUP(D36,B6:J33,5)*VLOOKUP(D36,B43:D61,3) -> 62493817 | G36: =VLOOKUP(D36,B6:J33,6)*VLOOKUP(D36,B43:D61,3) -> 7575008.1 | H36: =VLOOKUP(D36,B6:J33,7)*VLOOKUP(D36,B43:D61,3) -> 0 | I36: =VLOOKUP(D36,B6:J33,8)*VLOOKUP(D36,B43:D61,3) -> 1893752 | J36: =VLOOKUP(D36,B6:J33,9)*VLOOKUP(D36,B43:D61,3) -> 34087537
C40: Source: | D40: http://www.oanda.com/convert/fxhistory
C41: £ to DM Average 1996 | D41: 2.35121
B43: =B8 -> 1998-99 | C43: DM to Euro 1999 | D43: 0.51131
B44: =B9 -> 1999-00 | C44: DM to Euro 2000 | D44: 0.51131
B45: =B10 -> 2000-01 | C45: DM to Euro 2001 | D45: 0.51131
B46: =B11 -> 2001-02 | C46: Euro 2002 | D46: 1
B47: =B12 -> 2002-03 | C47: Euro 2003 | D47: 1
B48: =B13 -> 2003-04 | C48: Euro 2004 | D48: 1
B49: =B14 -> 2004-05 | C49: Euro 2005 | D49: 1
B50: =B15 -> 2005-06 | C50: Euro 2006 | D50: 1
B51: =B16 -> 2006-07 | C51: Euro 2007 | D51: 1
B52: =B17 -> 2007-08 | C52: Euro 2008 | D52: 1
B53: =B18 -> 2008-09 | C53: Euro 2009 | D53: 1
B54: =B26 -> 2016-17 | C54: Euro 2010 | D54: 1
B55: =B27 -> 2017-18 | C55: Euro 2011 | D55: 1
B56: =B28 -> 2018-19 | C56: Euro 2012 | D56: 1
B57: =B29 -> 2019-20 | C57: Euro 2013 | D57: 1
B58: =B30 -> 2020-21 | C58: Euro 2014 | D58: 1
B59: =B31 -> 2021-22 | C59: Euro 2015 | D59: 1
B60: =B32 -> 2022-23 | C60: Euro 2016 | D60: 1
B61: =B33 -> 2023-24 | C61: Euro 2017 | D61: 1

Sheet Chemical EIQ and Costs
B1: Environmental Impact Quotient - EIQ with Adjusted Integrated Costs from Pretty et al. 2001
B2: Kovach, J., Petzoldt, C., Degnil, J. and Tette, J. (1992) New York's Food and Life Sci. Bull. 139:1-8
B4: Most of the data to EIQ assessment is available at: | D4: http://sitem.herts.ac.uk/aeru/footprint/en/index.htm
B7: 1). | I7: Mode of action | L7: Toxicity to fish - 96hr LC50
C8: http://sitem.herts.ac.uk/aeru/footprint/en/index.htm | I8: Non systemic | J8: 1 | L8: >100 ppm | M8: 1
C9: Enter name of pesticde for EIQ evaluation | D9: Meptyldinocap | I9: All herbicides | J9: 1 | L9: 0.1-100 ppm | M9: 3
C10: SY = systemicity = | D10: Non systemic | E10: =IF(D10=$I$8,$J$8,IF(D10=$I$9,$J$9,IF(D10=$I$10,$J$10,0))) -> 1 | I10: Systemic | J10: 3 | L10: <0.1 ppm | M10: 5
C11: DT = dermal toxicity = | D11: >2000 | E11: =IF(D11=$I$13,$J$13,IF(D11=$I$14,$J$14,IF(D11=$I$15,$J$15,0))) -> 1
C12: CT = chronic toxicity = Reproductive | D12: Little or none | E12: =IF(D12=$I$18,$J$18,IF(D12=$I$19,$J$19,IF(D12=$I$20,$J$20,0))) -> 1 | I12: Acute dermal - LD50 for Rabbits/Rats (mg/kg) | L12: Toxicity to birds - 8 day LC50
C13: CT = chronic toxicity = Teratogenic | D13: Little or none | E13: =IF(D13=$I$18,$J$18,IF(D13=$I$19,$J$19,IF(D13=$I$20,$J$20,0))) -> 1 | I13: >2000 | J13: 1 | L13: >2000 ppm | M13: 1
C14: CT = chronic toxicity = Mutagenic | D14: Possible | E14: =IF(D14=$I$18,$J$18,IF(D14=$I$19,$J$19,IF(D14=$I$20,$J$20,0))) -> 3 | I14: 100-2000 | J14: 3 | L14: 100-2000 ppm | M14: 3
C15: CT = chronic toxicity = Oncogenic | D15: Little or none | E15: =IF(D15=$I$18,$J$18,IF(D15=$I$19,$J$19,IF(D15=$I$20,$J$20,0))) -> 1 | I15: 0-100 | J15: 5 | L15: <100 ppm | M15: 5
C16: SHL = soil half-life = | D16: <30 days | E16: =IF(D16=$I$30,$J$30,IF(D16=$I$31,$J$31,IF(D16=$I$32,$J$32,0))) -> 1
C17: SLP = surface loss potential = | D17: small | E17: =IF(D17=$L$30,$M$30,IF(D17=$L$31,$M$31,IF(D17=$L$32,$M$32,0))) -> 1 | I17: Long-term Health Effects | L17: Toxicity to Bees
C18: LP = leaching potential = | D18: small | E18: =IF(D18=$L$30,$M$30,IF(D18=$L$31,$M$31,IF(D18=$L$32,$M$32,0))) -> 1 | I18: Little or none | J18: 1 | L18: > 100 ug/bee | M18: 1
C19: PSHL = plant surface half-life = | D19: 1-2 weeks | E19: =IF(D19=$I$23,$J$23,IF(D19=$I$24,$J$24,IF(D19=$I$25,$J$25,IF(D19=$I$26,$J$26,IF(D19=$I$27,$J$27,0))))) -> 1 | I19: Possible | J19: 3 | L19: 1-100 ug/bee | M19: 3
C20: BT = bird toxicity = | D20: >2000 ppm | E20: =IF(D20=$L$13,$M$13,IF(D20=$L$14,$M$14,IF(D20=$L$15,$M$15,0))) -> 1 | I20: Definite | J20: 5 | L20: <1 ug/bee | M20: 5
C21: FT = fish toxicity = | D21: <0.1 ppm | E21: =IF(D21=$L$8,$M$8,IF(D21=$L$9,$M$9,IF(D21=$L$10,$M$10,0))) -> 5
C22: ZT = bee toxicity = | D22: 1-100 ug/bee | E22: =IF(D22=$L$18,$M$18,IF(D22=$L$19,$M$19,IF(D22=$L$20,$M$20,0))) -> 3 | I22: Plant surface residues - Half life | L22: Toxicity to Beneficials
C23: BAT = beneficIal arthropod toxicity = | D23: Moderate impact | E23: =IF(D23=$L$23,$M$23,IF(D23=$L$24,$M$24,IF(D23=$L$25,$M$25,0))) -> 3 | F23: No calculable data, used bee tox | I23: 1-2 weeks | J23: 1 | L23: Low impact | M23: 1
I24: 2-4 weeks | J24: 3 | L24: Moderate impact | M24: 3
I25: >4 weeks | J25: 5 | L25: Severe impact | M25: 5
E26: Costs (€ per Kg ai) | F26: Costs per Hectare | I26: Pre-emergent herbicides | J26: 1
C27: Applicator effects | D27: =IF(AND(E11=0,E12=0,E13=0,E14=0,E15=0),0,E11*5*(AVERAGE(E12:E15))) -> 7.5 | E27: =IF(D27=0,0,IF(D27<'Integration Inputs'!$D$76,'Integration Inputs'!$C$91*SUM('Integration Inputs'!$C$63:$H$63),IF(D27<'Integration Inputs'!$F$76,'Integration Inputs'!$D$91*SUM('Integration Inputs'!$C$63:$H$63),'Integration Inputs'!$E$91*SUM('Integration Inputs'!C$63:H$63)))) -> 12.65115 | F27: =E27*D40*D41 -> 0 | I27: Post emergent herbicides | J27: 3
C28: Picker effects | D28: =IF(AND(E11=0,E12=0,E19=0),0,E11*E19*(AVERAGE(E12:E15))) -> 1.5 | E28: =IF(D28=0,0,IF(D28<'Integration Inputs'!$D$77,'Integration Inputs'!$C$91*SUM('Integration Inputs'!$C$64:$H$64),IF(D28<'Integration Inputs'!$F$77,'Integration Inputs'!$D$91*SUM('Integration Inputs'!$C$64:$H$64),'Integration Inputs'!$E$91*SUM('Integration Inputs'!$C$64:$H$64)))) -> 3.2914643 | F28: =E28*D40*D41 -> 0
C29: Consumer effects | D29: =IF(AND(E10=0,E12=0,E13=0,E14=0,E15=0,E16=0,,E19=0),0,(AVERAGE(E12:E15)*((E16+E19)/2)*E10)) -> 1.5 | E29: =IF(D29=0,0,IF(D29<'Integration Inputs'!$D$78,'Integration Inputs'!$C$91*SUM('Integration Inputs'!$C$65:$H$65),IF(D29<'Integration Inputs'!$F$78,'Integration Inputs'!$D$91*SUM('Integration Inputs'!$C$65:$H$65),'Integration Inputs'!$E$91*SUM('Integration Inputs'!$C$65:$H$65)))) -> 0.85186978 | F29: =E29*D40*D41 -> 0 | I29: Soil residue half-life | L29: Groundwater and Runoff Potential
C30: Ground water leaching | D30: =IF(E18=0,0,E18) -> 1 | E30: =IF(D30=0,0,IF(D30<'Integration Inputs'!$D$79,'Integration Inputs'!$C$91*SUM('Integration Inputs'!$C$66:$H$66),IF(D30<'Integration Inputs'!$F$79,'Integration Inputs'!$D$91*SUM('Integration Inputs'!$C$66:$H$66),'Integration Inputs'!$E$91*SUM('Integration Inputs'!$C$66:$H$66)))) -> 0.97276634 | F30: =E30*D40*D41 -> 0 | I30: <30 days | J30: 1 | L30: small | M30: 1
C31: Aquatic effects | D31: =IF(AND(E21=0,E17=0),0,E21*E17) -> 5 | E31: =IF(D31=0,0,IF(D31<'Integration Inputs'!$D$80,'Integration Inputs'!$C$91*SUM('Integration Inputs'!$C$67:$H$67),IF(D31<'Integration Inputs'!$F$80,'Integration Inputs'!$D$91*SUM('Integration Inputs'!$C$67:$H$67),'Integration Inputs'!$E$91*SUM('Integration Inputs'!$C$67:$H$67)))) -> 0 | F31: =E31*D40*D41 -> 0 | I31: 30-100 days | J31: 3 | L31: medium | M31: 3
C32: Bird effects | D32: =IF(AND(E16=0,E19=0,E20=0),0,E20*((E16+E19)/2)*3) -> 3 | E32: =IF(D32=0,0,IF(D32<'Integration Inputs'!$D$81,'Integration Inputs'!$C$91*SUM('Integration Inputs'!$C$68:$H$68),IF(D32<'Integration Inputs'!$F$81,'Integration Inputs'!$D$91*SUM('Integration Inputs'!$C$68:$H$68),'Integration Inputs'!$E$91*SUM('Integration Inputs'!$C$68:$H$68)))) -> 0 | F32: =E32*D40*D41 -> 0 | I32: >100 days | J32: 5 | L32: large | M32: 5
C33: Bee effects | D33: =IF(AND(E19=0,E22=0),0,E22*E19*3) -> 9 | E33: =IF(D33=0,0,IF(D33<'Integration Inputs'!$D$82,'Integration Inputs'!$C$91*SUM('Integration Inputs'!$C$69:$H$69),IF(D33<'Integration Inputs'!$F$82,'Integration Inputs'!$D$91*SUM('Integration Inputs'!$C$69:$H$69),'Integration Inputs'!$E$91*SUM('Integration Inputs'!$C$69:$H$69)))) -> 0 | F33: =E33*D40*D41 -> 0
C34: Beneficials effects | D34: =IF(AND(E19=0,E23=0),0,(E23*E19*5)) -> 15 | E34: =IF(D34=0,0,IF(D34<'Integration Inputs'!$D$83,'Integration Inputs'!$C$91*SUM('Integration Inputs'!$C$70:$H$70),IF(D34<'Integration Inputs'!$F$83,'Integration Inputs'!$D$91*SUM('Integration Inputs'!$C$70:$H$70),'Integration Inputs'!$E$91*SUM('Integration Inputs'!$C$70:$H$70)))) -> 0 | F34: =E34*D40*D41 -> 0
C35: Farmworker component | D35: =SUM(D27:D28) -> 9 | E35: =SUM(E27:E28) -> 15.942614 | F35: =SUM(F27:F28) -> 0
C36: Consumer component | D36: =SUM(D29:D30) -> 2.5 | E36: =SUM(E29:E30) -> 1.8246361 | F36: =SUM(F29:F30) -> 0
C37: Ecological component | D37: =SUM(D31:D34) -> 32 | E37: =SUM(E31:E34) -> 0 | F37: =SUM(F31:F34) -> 0
E38: =SUM(E27:E34) -> 17.76725 | F38: =SUM(F27:F34) -> 0
C39: EIQ = | D39: =(AVERAGE(E12:E15)*((E11*5)+(E11*E19))+((AVERAGE(E12:E15)*((E16+E19)/2)*E10)+(E18))+((E21*E17)+(E20*((E16+E19)/2)*3)+(E22*E19*3)+(E23*E19*5)))/3 -> 14.5
C40: % active ingredient
C41: Rate (Kg of formulation per hectare)
C42: EIQ Field Use Rating = | D42: =D39*D40*D41 -> 0 | E42: =SUM(F27:F34) -> 0 | F42: of secondary damage per hectare
B44: =LEFT(B7,1)+1&")." -> 2).
C45: http://sitem.herts.ac.uk/aeru/footprint/en/index.htm
C46: Enter name of pesticde for EIQ evaluation | D46: Metrafenone
C47: SY = systemicity = | D47: Non systemic | E47: =IF(D47=$I$8,$J$8,IF(D47=$I$9,$J$9,IF(D47=$I$10,$J$10,0))) -> 1
C48: DT = dermal toxicity = | D48: >2000 | E48: =IF(D48=$I$13,$J$13,IF(D48=$I$14,$J$14,IF(D48=$I$15,$J$15,0))) -> 1
C49: CT = chronic toxicity = Reproductive | D49: Little or none | E49: =IF(D49=$I$18,$J$18,IF(D49=$I$19,$J$19,IF(D49=$I$20,$J$20,0))) -> 1
C50: CT = chronic toxicity = Teratogenic | D50: Little or none | E50: =IF(D50=$I$18,$J$18,IF(D50=$I$19,$J$19,IF(D50=$I$20,$J$20,0))) -> 1
C51: CT = chronic toxicity = Mutagenic | D51: Possible | E51: =IF(D51=$I$18,$J$18,IF(D51=$I$19,$J$19,IF(D51=$I$20,$J$20,0))) -> 3
C52: CT = chronic toxicity = Oncogenic | D52: Possible | E52: =IF(D52=$I$18,$J$18,IF(D52=$I$19,$J$19,IF(D52=$I$20,$J$20,0))) -> 3
C53: SHL = soil half-life = | D53: >100 days | E53: =IF(D53=$I$30,$J$30,IF(D53=$I$31,$J$31,IF(D53=$I$32,$J$32,0))) -> 5
C54: SLP = surface loss potential = | D54: small | E54: =IF(D54=$L$30,$M$30,IF(D54=$L$31,$M$31,IF(D54=$L$32,$M$32,0))) -> 1
C55: LP = leaching potential = | D55: small | E55: =IF(D55=$L$30,$M$30,IF(D55=$L$31,$M$31,IF(D55=$L$32,$M$32,0))) -> 1
C56: PSHL = plant surface half-life = | D56: >4 weeks | E56: =IF(D56=$I$23,$J$23,IF(D56=$I$24,$J$24,IF(D56=$I$25,$J$25,IF(D56=$I$26,$J$26,IF(D56=$I$27,$J$27,0))))) -> 5
C57: BT = bird toxicity = | D57: >2000 ppm | E57: =IF(D57=$L$13,$M$13,IF(D57=$L$14,$M$14,IF(D57=$L$15,$M$15,0))) -> 1
C58: FT = fish toxicity = | D58: 0.1-100 ppm | E58: =IF(D58=$L$8,$M$8,IF(D58=$L$9,$M$9,IF(D58=$L$10,$M$10,0))) -> 3
C59: ZT = bee toxicity = | D59: > 100 ug/bee | E59: =IF(D59=$L$18,$M$18,IF(D59=$L$19,$M$19,IF(D59=$L$20,$M$20,0))) -> 1
C60: BAT = beneficial arthropod toxicity = | D60: Moderate impact | E60: =IF(D60=$L$23,$M$23,IF(D60=$L$24,$M$24,IF(D60=$L$25,$M$25,0))) -> 3 | F60: No calculable data, used bee tox
E63: Costs (€ per Kg ai) | F63: Costs per Hectare
C64: Applicator effects | D64: =IF(AND(E48=0,E49=0,E50=0,E51=0,E52=0),0,E48*5*(AVERAGE(E49:E52))) -> 10 | E64: =IF(D64=0,0,IF(D64<'Integration Inputs'!$D$76,'Integration Inputs'!$C$91*SUM('Integration Inputs'!$C$63:$H$63),IF(D64<'Integration Inputs'!$F$76,'Integration Inputs'!$D$91*SUM('Integration Inputs'!$C$63:$H$63),'Integration Inputs'!$E$91*SUM('Integration Inputs'!C$63:H$63)))) -> 12.65115 | F64: =E64*D77*D78 -> 0
C65: Picker effects | D65: =IF(AND(E48=0,E49=0,E56=0),0,E48*E56*(AVERAGE(E49:E52))) -> 10 | E65: =IF(D65=0,0,IF(D65<'Integration Inputs'!$D$77,'Integration Inputs'!$C$91*SUM('Integration Inputs'!$C$64:$H$64),IF(D65<'Integration Inputs'!$F$77,'Integration Inputs'!$D$91*SUM('Integration Inputs'!$C$64:$H$64),'Integration Inputs'!$E$91*SUM('Integration Inputs'!$C$64:$H$64)))) -> 3.2914643 | F65: =E65*D77*D78 -> 0
C66: Consumer effects | D66: =IF(AND(E47=0,E49=0,E50=0,E51=0,E52=0,E53=0,,E56=0),0,(AVERAGE(E49:E52)*((E53+E56)/2)*E47)) -> 10 | E66: =IF(D66=0,0,IF(D66<'Integration Inputs'!$D$78,'Integration Inputs'!$C$91*SUM('Integration Inputs'!$C$65:$H$65),IF(D66<'Integration Inputs'!$F$78,'Integration Inputs'!$D$91*SUM('Integration Inputs'!$C$65:$H$65),'Integration Inputs'!$E$91*SUM('Integration Inputs'!$C$65:$H$65)))) -> 0.85186978 | F66: =E66*D77*D78 -> 0
C67: Ground water | D67: =IF(E55=0,0,E55) -> 1 | E67: =IF(D67=0,0,IF(D67<'Integration Inputs'!$D$79,'Integration Inputs'!$C$91*SUM('Integration Inputs'!$C$66:$H$66),IF(D67<'Integration Inputs'!$F$79,'Integration Inputs'!$D$91*SUM('Integration Inputs'!$C$66:$H$66),'Integration Inputs'!$E$91*SUM('Integration Inputs'!$C$66:$H$66)))) -> 0.97276634 | F67: =E67*D77*D78 -> 0
C68: Aquatic effects | D68: =IF(AND(E58=0,E54=0),0,E58*E54) -> 3 | E68: =IF(D68=0,0,IF(D68<'Integration Inputs'!$D$80,'Integration Inputs'!$C$91*SUM('Integration Inputs'!$C$67:$H$67),IF(D68<'Integration Inputs'!$F$80,'Integration Inputs'!$D$91*SUM('Integration Inputs'!$C$67:$H$67),'Integration Inputs'!$E$91*SUM('Integration Inputs'!$C$67:$H$67)))) -> 0 | F68: =E68*D77*D78 -> 0
C69: Bird effects | D69: =IF(AND(E53=0,E56=0,E57=0),0,E57*((E53+E56)/2)*3) -> 15 | E69: =IF(D69=0,0,IF(D69<'Integration Inputs'!$D$81,'Integration Inputs'!$C$91*SUM('Integration Inputs'!$C$68:$H$68),IF(D69<'Integration Inputs'!$F$81,'Integration Inputs'!$D$91*SUM('Integration Inputs'!$C$68:$H$68),'Integration Inputs'!$E$91*SUM('Integration Inputs'!$C$68:$H$68)))) -> 0 | F69: =E69*D77*D78 -> 0
C70: Bee effects | D70: =IF(AND(E56=0,E59=0),0,E59*E56*3) -> 15 | E70: =IF(D70=0,0,IF(D70<'Integration Inputs'!$D$82,'Integration Inputs'!$C$91*SUM('Integration Inputs'!$C$69:$H$69),IF(D70<'Integration Inputs'!$F$82,'Integration Inputs'!$D$91*SUM('Integration Inputs'!$C$69:$H$69),'Integration Inputs'!$E$91*SUM('Integration Inputs'!$C$69:$H$69)))) -> 0 | F70: =E70*D77*D78 -> 0
C71: Beneficials effects | D71: =IF(AND(E56=0,E60=0),0,(E60*E56*5)) -> 75 | E71: =IF(D71=0,0,IF(D71<'Integration Inputs'!$D$83,'Integration Inputs'!$C$91*SUM('Integration Inputs'!$C$70:$H$70),IF(D71<'Integration Inputs'!$F$83,'Integration Inputs'!$D$91*SUM('Integration Inputs'!$C$70:$H$70),'Integration Inputs'!$E$91*SUM('Integration Inputs'!$C$70:$H$70)))) -> 0 | F71: =E71*D77*D78 -> 0
C72: Farmworker component | D72: =SUM(D64:D65) -> 20 | E72: =SUM(E64:E65) -> 15.942614 | F72: =SUM(F64:F65) -> 0
C73: Consumer component | D73: =SUM(D66:D67) -> 11 | E73: =SUM(E66:E67) -> 1.8246361 | F73: =SUM(F66:F67) -> 0
C74: Ecological component | D74: =SUM(D68:D71) -> 108 | E74: =SUM(E68:E71) -> 0 | F74: =SUM(F68:F71) -> 0
E75: =SUM(E64:E71) -> 17.76725 | F75: =SUM(F64:F71) -> 0
C76: EIQ = | D76: =(AVERAGE(E49:E52)*((E48*5)+(E48*E56))+((AVERAGE(E49:E52)*((E53+E56)/2)*E47)+(E55))+((E58*E54)+(E57*((E53+E56)/2)*3)+(E59*E56*3)+(E60*E56*5)))/3 -> 46.333333
C77: % active ingredient
C78: Rate (Kg of formulation per hectare)
C79: EIQ Field Use Rating = | D79: =D76*D77*D78 -> 0 | E79: =SUM(F64:F71) -> 0 | F79: of secondary damage per hectare
B81: =LEFT(B44,1)+1&")." -> 3).
C82: http://sitem.herts.ac.uk/aeru/footprint/en/index.htm
C83: Enter name of pesticde for EIQ evaluation | D83: Propiconazole
C84: SY = systemicity = | D84: Systemic | E84: =IF(D84=$I$8,$J$8,IF(D84=$I$9,$J$9,IF(D84=$I$10,$J$10,0))) -> 3
C85: DT = dermal toxicity = | D85: >2000 | E85: =IF(D85=$I$13,$J$13,IF(D85=$I$14,$J$14,IF(D85=$I$15,$J$15,0))) -> 1
C86: CT = chronic toxicity = Reproductive | D86: Possible | E86: =IF(D86=$I$18,$J$18,IF(D86=$I$19,$J$19,IF(D86=$I$20,$J$20,0))) -> 3
C87: CT = chronic toxicity = Teratogenic | D87: Possible | E87: =IF(D87=$I$18,$J$18,IF(D87=$I$19,$J$19,IF(D87=$I$20,$J$20,0))) -> 3
C88: CT = chronic toxicity = Mutagenic | D88: Little or none | E88: =IF(D88=$I$18,$J$18,IF(D88=$I$19,$J$19,IF(D88=$I$20,$J$20,0))) -> 1
C89: CT = chronic toxicity = Oncogenic | D89: Possible | E89: =IF(D89=$I$18,$J$18,IF(D89=$I$19,$J$19,IF(D89=$I$20,$J$20,0))) -> 3
C90: SHL = soil half-life = | D90: 30-100 days | E90: =IF(D90=$I$30,$J$30,IF(D90=$I$31,$J$31,IF(D90=$I$32,$J$32,0))) -> 3
C91: SLP = surface loss potential = | D91: small | E91: =IF(D91=$L$30,$M$30,IF(D91=$L$31,$M$31,IF(D91=$L$32,$M$32,0))) -> 1
C92: LP = leaching potential = | D92: medium | E92: =IF(D92=$L$30,$M$30,IF(D92=$L$31,$M$31,IF(D92=$L$32,$M$32,0))) -> 3
C93: PSHL = plant surface half-life = | D93: 1-2 weeks | E93: =IF(D93=$I$23,$J$23,IF(D93=$I$24,$J$24,IF(D93=$I$25,$J$25,IF(D93=$I$26,$J$26,IF(D93=$I$27,$J$27,0))))) -> 1
C94: BT = bird toxicity = | D94: >2000 ppm | E94: =IF(D94=$L$13,$M$13,IF(D94=$L$14,$M$14,IF(D94=$L$15,$M$15,0))) -> 1
C95: FT = fish toxicity = | D95: 0.1-100 ppm | E95: =IF(D95=$L$8,$M$8,IF(D95=$L$9,$M$9,IF(D95=$L$10,$M$10,0))) -> 3
C96: ZT = bee toxicity = | D96: > 100 ug/bee | E96: =IF(D96=$L$18,$M$18,IF(D96=$L$19,$M$19,IF(D96=$L$20,$M$20,0))) -> 1
C97: BAT = beneficial arthropod toxicity = | D97: Low impact | E97: =IF(D97=$L$23,$M$23,IF(D97=$L$24,$M$24,IF(D97=$L$25,$M$25,0))) -> 1 | F97: No calculable data, used bee tox
E100: Costs (€ per Kg ai) | F100: Costs per Hectare
C101: Applicator effects | D101: =IF(AND(E85=0,E86=0,E87=0,E88=0,E89=0),0,E85*5*(AVERAGE(E86:E89))) -> 12.5 | E101: =IF(D101=0,0,IF(D101<'Integration Inputs'!$D$76,'Integration Inputs'!$C$91*SUM('Integration Inputs'!$C$63:$H$63),IF(D101<'Integration Inputs'!$F$76,'Integration Inputs'!$D$91*SUM('Integration Inputs'!$C$63:$H$63),'Integration Inputs'!$E$91*SUM('Integration Inputs'!C$63:H$63)))) -> 12.65115 | F101: =E101*D114*D115 -> 0
C102: Picker effects | D102: =IF(AND(E85=0,E86=0,E93=0),0,E85*E93*(AVERAGE(E86:E89))) -> 2.5 | E102: =IF(D102=0,0,IF(D102<'Integration Inputs'!$D$77,'Integration Inputs'!$C$91*SUM('Integration Inputs'!$C$64:$H$64),IF(D102<'Integration Inputs'!$F$77,'Integration Inputs'!$D$91*SUM('Integration Inputs'!$C$64:$H$64),'Integration Inputs'!$E$91*SUM('Integration Inputs'!$C$64:$H$64)))) -> 3.2914643 | F102: =E102*D114*D115 -> 0
C103: Consumer effects | D103: =IF(AND(E84=0,E86=0,E87=0,E88=0,E89=0,E90=0,,E93=0),0,(AVERAGE(E86:E89)*((E90+E93)/2)*E84)) -> 15 | E103: =IF(D103=0,0,IF(D103<'Integration Inputs'!$D$78,'Integration Inputs'!$C$91*SUM('Integration Inputs'!$C$65:$H$65),IF(D103<'Integration Inputs'!$F$78,'Integration Inputs'!$D$91*SUM('Integration Inputs'!$C$65:$H$65),'Integration Inputs'!$E$91*SUM('Integration Inputs'!$C$65:$H$65)))) -> 0.85186978 | F103: =E103*D114*D115 -> 0
C104: Ground water | D104: =IF(E92=0,0,E92) -> 3 | E104: =IF(D104=0,0,IF(D104<'Integration Inputs'!$D$79,'Integration Inputs'!$C$91*SUM('Integration Inputs'!$C$66:$H$66),IF(D104<'Integration Inputs'!$F$79,'Integration Inputs'!$D$91*SUM('Integration Inputs'!$C$66:$H$66),'Integration Inputs'!$E$91*SUM('Integration Inputs'!$C$66:$H$66)))) -> 1.4591495 | F104: =E104*D114*D115 -> 0
C105: Aquatic effects | D105: =IF(AND(E95=0,E91=0),0,E95*E91) -> 3 | E105: =IF(D105=0,0,IF(D105<'Integration Inputs'!$D$80,'Integration Inputs'!$C$91*SUM('Integration Inputs'!$C$67:$H$67),IF(D105<'Integration Inputs'!$F$80,'Integration Inputs'!$D$91*SUM('Integration Inputs'!$C$67:$H$67),'Integration Inputs'!$E$91*SUM('Integration Inputs'!$C$67:$H$67)))) -> 0 | F105: =E105*D114*D115 -> 0
C106: Bird effects | D106: =IF(AND(E90=0,E93=0,E94=0),0,E94*((E90+E93)/2)*3) -> 6 | E106: =IF(D106=0,0,IF(D106<'Integration Inputs'!$D$81,'Integration Inputs'!$C$91*SUM('Integration Inputs'!$C$68:$H$68),IF(D106<'Integration Inputs'!$F$81,'Integration Inputs'!$D$91*SUM('Integration Inputs'!$C$68:$H$68),'Integration Inputs'!$E$91*SUM('Integration Inputs'!$C$68:$H$68)))) -> 0 | F106: =E106*D114*D115 -> 0
C107: Bee effects | D107: =IF(AND(E93=0,E96=0),0,E96*E93*3) -> 3 | E107: =IF(D107=0,0,IF(D107<'Integration Inputs'!$D$82,'Integration Inputs'!$C$91*SUM('Integration Inputs'!$C$69:$H$69),IF(D107<'Integration Inputs'!$F$82,'Integration Inputs'!$D$91*SUM('Integration Inputs'!$C$69:$H$69),'Integration Inputs'!$E$91*SUM('Integration Inputs'!$C$69:$H$69)))) -> 0 | F107: =E107*D114*D115 -> 0
C108: Beneficials effects | D108: =IF(AND(E93=0,E97=0),0,(E97*E93*5)) -> 5 | E108: =IF(D108=0,0,IF(D108<'Integration Inputs'!$D$83,'Integration Inputs'!$C$91*SUM('Integration Inputs'!$C$70:$H$70),IF(D108<'Integration Inputs'!$F$83,'Integration Inputs'!$D$91*SUM('Integration Inputs'!$C$70:$H$70),'Integration Inputs'!$E$91*SUM('Integration Inputs'!$C$70:$H$70)))) -> 0 | F108: =E108*D114*D115 -> 0
C109: Farmworker component | D109: =SUM(D101:D102) -> 15 | E109: =SUM(E101:E102) -> 15.942614 | F109: =SUM(F101:F102) -> 0
...

Sheet GDP Pop Data
B1: GDP and Population Data
B2: http://en.wikipedia.org/wiki/List_of_countries_by_GDP_%28PPP%29
B5: Country | C5: GDP millions (USD) | D5: Population | E5: % GDP from Agriculture | F5: % Labour force in agricuture | G5: GDP per capita (USD) | H5: % of Weighted UK, US & German GDP per capita | I5: Multiple of weighted UK, US and Germany % GDP from Agriculture | K5: Multiple of weighted UK, US and Germany % Labour force in Agriculture
B6: Absolute costs | H6: =G228/G228 -> 1 | I6: =G229/G229 -> 1 | K6: =F41/F$41 -> #DIV/0!
B7: Afghanistan | C7: 82007.333 | D7: 42650000 | E7: 0.347 | G7: =C7/D7*1000000 -> 1922.798 | H7: =G7/G$228 -> 0.024700448 | I7: =IFERROR(E7/G$229,"-") -> 40.687934
B8: Albania | C8: 59400.333 | D8: 2790000 | E8: 0.155 | G8: =C8/D8*1000000 -> 21290.442 | H8: =G8/G$228 -> 0.27349907 | I8: =IFERROR(E8/G$229,"-") -> 18.174726
B9: Algeria | C9: 806655.67 | D9: 46810000 | E9: 0.131 | G9: =C9/D9*1000000 -> 17232.55 | H9: =G9/G$228 -> 0.221371 | I9: =IFERROR(E9/G$229,"-") -> 15.360575
B10: Andorra | C10: 5988.3333 | D10: 80000 | E10: 0.005 | G10: =C10/D10*1000000 -> 74854.167 | H10: =G10/G$228 -> 0.96158383 | I10: =IFERROR(E10/G$229,"-") -> 0.58628147
B11: Angola | C11: 332221 | D11: 37890000 | E11: 0.164 | G11: =C11/D11*1000000 -> 8768.0391 | H11: =G11/G$228 -> 0.11263507 | I11: =IFERROR(E11/G$229,"-") -> 19.230032
B12: Antigua and Barbuda | C12: 3085.3333 | D12: 90000 | E12: 0.019 | G12: =C12/D12*1000000 -> 34281.481 | H12: =G12/G$228 -> 0.44038321 | I12: =IFERROR(E12/G$229,"-") -> 2.2278696
B13: Argentina | C13: 1361776.3 | D13: 45700000 | E13: 0.06 | G13: =C13/D13*1000000 -> 29798.169 | H13: =G13/G$228 -> 0.38279015 | I13: =IFERROR(E13/G$229,"-") -> 7.0353776
B14: Armenia | C14: 68145.667 | D14: 2970000 | E14: 0.079 | G14: =C14/D14*1000000 -> 22944.669 | H14: =G14/G$228 -> 0.29474942 | I14: =IFERROR(E14/G$229,"-") -> 9.2632472
B15: Aruba | C15: 4900.6667 | D15: 110000 | E15: 0 | G15: =C15/D15*1000000 -> 44551.515 | H15: =G15/G$228 -> 0.57231305 | I15: =IFERROR(E15/G$229,"-") -> 0
B16: Australia | C16: 1850606.7 | D16: 26710000 | E16: 0.022 | G16: =C16/D16*1000000 -> 69285.162 | H16: =G16/G$228 -> 0.89004385 | I16: =IFERROR(E16/G$229,"-") -> 2.5796385
B17: Austria | C17: 640445.33 | D17: 9120000 | E17: 0.012 | G17: =C17/D17*1000000 -> 70224.269 | H17: =G17/G$228 -> 0.90210772 | I17: =IFERROR(E17/G$229,"-") -> 1.4070755
B18: Azerbaijan | C18: 251092.33 | D18: 10340000 | E18: 0.057 | G18: =C18/D18*1000000 -> 24283.591 | H18: =G18/G$228 -> 0.31194935 | I18: =IFERROR(E18/G$229,"-") -> 6.6836088
... B72: France | C72: 4145781 | D72: 66550000 | E72: 0.014 | G72: =C72/D72*1000000 -> 62295.733 | H72: =G72/G$228 -> 0.80025697 | I72: =IFERROR(E72/G$229,"-") -> 1.6415881
B73: French Guiana | D73: 310000 | G73: =C73/D73*1000000 -> 0 | H73: =G73/G$228 -> 0 | I73: =IFERROR(E73/G$229,"-") -> 0
B74: French Polynesia | D74: 280000 | E74: 0.022 | G74: =C74/D74*1000000 -> 0 | H74: =G74/G$228 -> 0 | I74: =IFERROR(E74/G$229,"-") -> 2.5796385
B75: Gabon | C75: 53367.333 | D75: 2540000 | E75: 0.062 | G75: =C75/D75*1000000 -> 21010.761 | H75: =G75/G$228 -> 0.26990626 | I75: =IFERROR(E75/G$229,"-") -> 7.2698902
B76: Gambia | C76: 9406.3333 | D76: 2760000 | E76: 0.241 | G76: =C76/D76*1000000 -> 3408.0918 | H76: =G76/G$228 -> 0.043780675 | I76: =IFERROR(E76/G$229,"-") -> 28.258767
B77: Georgia | C77: 103278.33 | D77: 3810000 | E77: 0.054 | G77: =C77/D77*1000000 -> 27107.174 | H77: =G77/G$228 -> 0.34822137 | I77: =IFERROR(E77/G$229,"-") -> 6.3318399
B78: Germany | C78: 5815284.7 | D78: 84550000 | E78: 0.008 | G78: =C78/D78*1000000 -> 68779.239 | H78: =G78/G$228 -> 0.88354472 | I78: =IFERROR(E78/G$229,"-") -> 0.93805035
B79: Ghana | C79: 271532.33 | D79: 34430000 | E79: 0.207 | G79: =C79/D79*1000000 -> 7886.504 | H79: =G79/G$228 -> 0.10131079 | I79: =IFERROR(E79/G$229,"-") -> 24.272053
B80: Greece | C80: 439224.67 | D80: 10050000 | E80: 0.033 | G80: =C80/D80*1000000 -> 43703.947 | H80: =G80/G$228 -> 0.56142511 | I80: =IFERROR(E80/G$229,"-") -> 3.8694577
B81: Greenland | C81: 4261.5 | D81: 60000 | E81: 0.166 | G81: =C81/D81*1000000 -> 71025 | H81: =G81/G$228 -> 0.91239398 | I81: =IFERROR(E81/G$229,"-") -> 19.464545
B82: Grenada | C82: 2321.3333 | D82: 120000 | E82: 0.027 | G82: =C82/D82*1000000 -> 19344.444 | H82: =G82/G$228 -> 0.24850059 | I82: =IFERROR(E82/G$229,"-") -> 3.1659199
B83: Guadeloupe | D83: 380000 | G83: =C83/D83*1000000 -> 0 | H83: =G83/G$228 -> 0 | I83: =IFERROR(E83/G$229,"-") -> 0
B84: Guam | D84: 170000 | G84: =C84/D84*1000000 -> 0 | H84: =G84/G$228 -> 0 | I84: =IFERROR(E84/G$229,"-") -> 0
B85: Guatemala | C85: 259993.67 | D85: 18410000 | E85: 0.098 | G85: =C85/D85*1000000 -> 14122.415 | H85: =G85/G$228 -> 0.18141791 | I85: =IFERROR(E85/G$229,"-") -> 11.491117
B86: Guinea | C86: 67351.667 | D86: 14750000 | E86: 0.296 | G86: =C86/D86*1000000 -> 4566.2147 | H86: =G86/G$228 -> 0.058658033 | I86: =IFERROR(E86/G$229,"-") -> 34.707863
B87: Guinea-Bissau | C87: 6417.3333 | D87: 2200000 | E87: 0.368 | G87: =C87/D87*1000000 -> 2916.9697 | H87: =G87/G$228 -> 0.037471673 | I87: =IFERROR(E87/G$229,"-") -> 43.150316
B88: Guyana | C88: 66708.667 | D88: 830000 | E88: 0.08 | G88: =C88/D88*1000000 -> 80371.888 | H88: =G88/G$228 -> 1.032465 | I88: =IFERROR(E88/G$229,"-") -> 9.3805035
B89: Haiti | C89: 36215.333 | D89: 11770000 | E89: 0.159 | G89: =C89/D89*1000000 -> 3076.9187 | H89: =G89/G$228 -> 0.039526394 | I89: =IFERROR(E89/G$229,"-") -> 18.643751
B90: Honduras | C90: 79440.667 | D90: 10830000 | E90: 0.112 | G90: =C90/D90*1000000 -> 7335.2416 | H90: =G90/G$228 -> 0.09422922 | I90: =IFERROR(E90/G$229,"-") -> 13.132705
B91: Hong Kong | C91: 551205.67 | D91: 7410000 | E91: 0 | G91: =C91/D91*1000000 -> 74386.73 | H91: =G91/G$228 -> 0.95557909 | I91: =IFERROR(E91/G$229,"-") -> 0
B92: Hungary | C92: 436378.33 | D92: 9680000 | E92: 0.024 | G92: =C92/D92*1000000 -> 45080.406 | H92: =G92/G$228 -> 0.57910724 | I92: =IFERROR(E92/G$229,"-") -> 2.8141511
B93: Iceland | C93: 29996 | D93: 390000 | E93: 0.04 | G93: =C93/D93*1000000 -> 76912.821 | H93: =G93/G$228 -> 0.98802949 | I93: =IFERROR(E93/G$229,"-") -> 4.6902518
B94: India | C94: 16027290 | D94: 1450940000 | E94: 0.164 | G94: =C94/D94*1000000 -> 11046.143 | H94: =G94/G$228 -> 0.14189981 | I94: =IFERROR(E94/G$229,"-") -> 19.230032
B95: Indonesia | C95: 4591457 | D95: 283490000 | E95: 0.126 | G95: =C95/D95*1000000 -> 16196.187 | H95: =G95/G$228 -> 0.20805777 | I95: =IFERROR(E95/G$229,"-") -> 14.774293
B96: Iran | C96: 1640307 | D96: 91570000 | E96: 0.13 | G96: =C96/D96*1000000 -> 17913.148 | H96: =G96/G$228 -> 0.23011403 | I96: =IFERROR(E96/G$229,"-") -> 15.243318
... B119: Luxembourg | C119: 97958 | D119: 670000 | E119: 0.002 | G119: =C119/D119*1000000 -> 146205.97 | H119: =G119/G$228 -> 1.878176 | I119: =IFERROR(E119/G$229,"-") -> 0.23451259
B120: Macau | C120: 86452 | D120: 720000 | G120: =C120/D120*1000000 -> 120072.22 | H120: =G120/G$228 -> 1.5424593 | I120: =IFERROR(E120/G$229,"-") -> -
B121: Madagascar | C121: 59139 | D121: 31970000 | E121: 0.225 | G121: =C121/D121*1000000 -> 1849.828 | H121: =G121/G$228 -> 0.023763068 | I121: =IFERROR(E121/G$229,"-") -> 26.382666
B122: Malawi | C122: 39488 | D122: 21660000 | E122: 0.324 | G122: =C122/D122*1000000 -> 1823.084 | H122: =G122/G$228 -> 0.023419513 | I122: =IFERROR(E122/G$229,"-") -> 37.991039
B123: Malaysia | C123: 1353588.7 | D123: 35560000 | E123: 0.082 | G123: =C123/D123*1000000 -> 38064.923 | H123: =G123/G$228 -> 0.48898567 | I123: =IFERROR(E123/G$229,"-") -> 9.6150161
B124: Maldives | C124: 13788 | D124: 530000 | E124: 0.03 | G124: =C124/D124*1000000 -> 26015.094 | H124: =G124/G$228 -> 0.3341924 | I124: =IFERROR(E124/G$229,"-") -> 3.5176888
B125: Mali | C125: 74994.333 | D125: 24480000 | E125: 0.334 | G125: =C125/D125*1000000 -> 3063.494 | H125: =G125/G$228 -> 0.039353939 | I125: =IFERROR(E125/G$229,"-") -> 39.163602
B126: Malta | C126: 38869.667 | D126: 540000 | E126: 0.002 | G126: =C126/D126*1000000 -> 71980.864 | H126: =G126/G$228 -> 0.92467311 | I126: =IFERROR(E126/G$229,"-") -> 0.23451259
B127: Marshall Islands | C127: 286.66667 | D127: 40000 | E127: 0.195 | G127: =C127/D127*1000000 -> 7166.6667 | H127: =G127/G$228 -> 0.09206369 | I127: =IFERROR(E127/G$229,"-") -> 22.864977
B128: Martinique | D128: 340000 | G128: =C128/D128*1000000 -> 0 | H128: =G128/G$228 -> 0 | I128: =IFERROR(E128/G$229,"-") -> 0
B129: Mauritania | C129: 36905.667 | D129: 5170000 | E129: 0.186 | G129: =C129/D129*1000000 -> 7138.4268 | H129: =G129/G$228 -> 0.091700918 | I129: =IFERROR(E129/G$229,"-") -> 21.809671
B130: Mauritius | C130: 38289 | D130: 1270000 | E130: 0.043 | G130: =C130/D130*1000000 -> 30148.819 | H130: =G130/G$228 -> 0.38729463 | I130: =IFERROR(E130/G$229,"-") -> 5.0420206
B131: Mexico | C131: 3213495.3 | D131: 1.3086e+08 | E131: 0.038 | G131: =C131/D131*1000000 -> 24556.743 | H131: =G131/G$228 -> 0.31545828 | I131: =IFERROR(E131/G$229,"-") -> 4.4557392
B132: Micronesia | C132: 458.66667 | D132: 110000 | E132: 0.233 | G132: =C132/D132*1000000 -> 4169.697 | H132: =G132/G$228 -> 0.053564328 | I132: =IFERROR(E132/G$229,"-") -> 27.320716
B133: Moldova | C133: 43475.333 | D133: 3040000 | E133: 0.071 | G133: =C133/D133*1000000 -> 14301.096 | H133: =G133/G$228 -> 0.18371326 | I133: =IFERROR(E133/G$229,"-") -> 8.3251969
B134: Mongolia | C134: 66605 | D134: 3480000 | E134: 0.074 | G134: =C134/D134*1000000 -> 19139.368 | H134: =G134/G$228 -> 0.24586616 | I134: =IFERROR(E134/G$229,"-") -> 8.6769658
B135: Monaco | C135: 8924 | D135: 40000 | E135: 0 | G135: =C135/D135*1000000 -> 223100 | H135: =G135/G$228 -> 2.8659641 | I135: =IFERROR(E135/G$229,"-") -> 0
B136: Montenegro | C136: 19835.667 | D136: 640000 | E136: 0.052 | G136: =C136/D136*1000000 -> 30993.229 | H136: =G136/G$228 -> 0.398142 | I136: =IFERROR(E136/G$229,"-") -> 6.0973273
B137: Morocco | C137: 391326.33 | D137: 38080000 | E137: 0.101 | G137: =C137/D137*1000000 -> 10276.427 | H137: =G137/G$228 -> 0.13201197 | I137: =IFERROR(E137/G$229,"-") -> 11.842886
B138: Mozambique | C138: 57534.333 | D138: 34630000 | E138: 0.263 | G138: =C138/D138*1000000 -> 1661.4015 | H138: =G138/G$228 -> 0.021342523 | I138: =IFERROR(E138/G$229,"-") -> 30.838405
B139: Myanmar | C139: 313771.67 | D139: 54500000 | E139: 0.208 | G139: =C139/D139*1000000 -> 5757.2783 | H139: =G139/G$228 -> 0.073958551 | I139: =IFERROR(E139/G$229,"-") -> 24.389309
B140: Namibia | C140: 34764.667 | D140: 3030000 | E140: 0.073 | G140: =C140/D140*1000000 -> 11473.487 | H140: =G140/G$228 -> 0.14738952 | I140: =IFERROR(E140/G$229,"-") -> 8.5597095
B141: Nauru | C141: 156.66667 | D141: 10000 | G141: =C141/D141*1000000 -> 15666.667 | H141: =G141/G$228 -> 0.20125551 | I141: =IFERROR(E141/G$229,"-") -> -
B142: Nepal | C142: 166793.33 | D142: 29650000 | E142: 0.219 | G142: =C142/D142*1000000 -> 5625.4075 | H142: =G142/G$228 -> 0.072264526 | I142: =IFERROR(E142/G$229,"-") -> 25.679128
B143: Netherlands | C143: 1439228.7 | D143: 18230000 | E143: 0.017 | G143: =C143/D143*1000000 -> 78948.364 | H143: =G143/G$228 -> 1.0141783 | I143: =IFERROR(E143/G$229,"-") -> 1.993357
B144: New Zealand | C144: 283389.33 | D144: 5210000 | E144: 0.046 | G144: =C144/D144*1000000 -> 54393.346 | H144: =G144/G$228 -> 0.69874216 | I144: =IFERROR(E144/G$229,"-") -> 5.3937895
B145: Nicaragua | C145: 59010 | D145: 6920000 | E145: 0.144 | G145: =C145/D145*1000000 -> 8527.4566 | H145: =G145/G$228 -> 0.10954453 | I145: =IFERROR(E145/G$229,"-") -> 16.884906
B146: Niger | C146: 54475.667 | D146: 27030000 | E146: 0.338 | G146: =C146/D146*1000000 -> 2015.378 | H146: =G146/G$228 -> 0.025889739 | I146: =IFERROR(E146/G$229,"-") -> 39.632627
B147: Nigeria | C147: 1467123.3 | D147: 232680000 | E147: 0.204 | G147: =C147/D147*1000000 -> 6305.3263 | H147: =G147/G$228 -> 0.080998829 | I147: =IFERROR(E147/G$229,"-") -> 23.920284
B148: North Korea | C148: 15416 | D148: 26500000 | G148: =C148/D148*1000000 -> 581.73585 | H148: =G148/G$228 -> 0.0074730347 | I148: =IFERROR(E148/G$229,"-") -> -
B149: North Macedonia | C149: 48279.333 | D149: 1820000 | E149: 0.06 | G149: =C149/D149*1000000 -> 26527.106 | H149: =G149/G$228 -> 0.34076976 | I149: =IFERROR(E149/G$229,"-") -> 7.0353776
B150: Norway | C150: 559081.67 | D150: 5580000 | E150: 0.02 | G150: =C150/D150*1000000 -> 100193.85 | H150: =G150/G$228 -> 1.2870998 | I150: =IFERROR(E150/G$229,"-") -> 2.3451259
B151: Oman | C151: 214934 | D151: 5280000 | E151: 0.026 | G151: =C151/D151*1000000 -> 40707.197 | H151: =G151/G$228 -> 0.52292857 | I151: =IFERROR(E151/G$229,"-") -> 3.0486636
B152: Pakistan | C152: 1547197.3 | D152: 251270000 | E152: 0.235 | G152: =C152/D152*1000000 -> 6157.5092 | H152: =G152/G$228 -> 0.079099955 | I152: =IFERROR(E152/G$229,"-") -> 27.555229
B153: Palau | C153: 304.33333 | D153: 20000 | E153: 0.03 | G153: =C153/D153*1000000 -> 15216.667 | H153: =G153/G$228 -> 0.19547476 | I153: =IFERROR(E153/G$229,"-") -> 3.5176888
B154: Palestine | C154: 27976.667 | D154: 5500000 | E154: 0.057 | G154: =C154/D154*1000000 -> 5086.6667 | H154: =G154/G$228 -> 0.065343809 | I154: =IFERROR(E154/G$229,"-") -> 6.6836088
B155: Panama | C155: 183866.67 | D155: 4520000 | E155: 0.026 | G155: =C155/D155*1000000 -> 40678.466 | H155: =G155/G$228 -> 0.52255949 | I155: =IFERROR(E155/G$229,"-") -> 3.0486636
B156: Papua New Guinea | C156: 48431 | D156: 10580000 | E156: 0.172 | G156: =C156/D156*1000000 -> 4577.5992 | H156: =G156/G$228 -> 0.05880428 | I156: =IFERROR(E156/G$229,"-") -> 20.168083
B157: Paraguay | C157: 125904.67 | D157: 6930000 | E157: 0.107 | G157: =C157/D157*1000000 -> 18168.062 | H157: =G157/G$228 -> 0.23338867 | I157: =IFERROR(E157/G$229,"-") -> 12.546423
B158: Peru | C158: 596041 | D158: 34220000 | E158: 0.061 | G158: =C158/D158*1000000 -> 17417.914 | H158: =G158/G$228 -> 0.22375219 | I158: =IFERROR(E158/G$229,"-") -> 7.1526339
B159: Philippines | C159: 1349219 | D159: 115840000 | E159: 0.091 | G159: =C159/D159*1000000 -> 11647.263 | H159: =G159/G$228 -> 0.14962187 | I159: =IFERROR(E159/G$229,"-") -> 10.670323
B160: Poland | C160: 1836022.7 | D160: 38540000 | E160: 0.026 | G160: =C160/D160*1000000 -> 47639.405 | H160: =G160/G$228 -> 0.61198038 | I160: =IFERROR(E160/G$229,"-") -> 3.0486636
... B216: Vietnam | C216: 1632312.3 | D216: 100990000 | E216: 0.119 | G216: =C216/D216*1000000 -> 16163.109 | H216: =G216/G$228 -> 0.20763285 | I216: =IFERROR(E216/G$229,"-") -> 13.953499
B217: Western Sahara | D217: 590000 | G217: =C217/D217*1000000 -> 0 | H217: =G217/G$228 -> 0 | I217: =IFERROR(E217/G$229,"-") -> 0
B218: World | C218: 1.9248976e+08 | D218: 8161970000 | E218: 0.064 | G218: =C218/D218*1000000 -> 23583.738 | H218: =G218/G$228 -> 0.30295897 | I218: =IFERROR(E218/G$229,"-") -> 7.5044028
B219: Yemen | C219: 44339.5 | D219: 40580000 | E219: 0.287 | G219: =C219/D219*1000000 -> 1092.6442 | H219: =G219/G$228 -> 0.014036212 | I219: =IFERROR(E219/G$229,"-") -> 33.652556
B220: Zambia | C220: 89131.667 | D220: 21320000 | E220: 0.018 | G220: =C220/D220*1000000 -> 4180.6598 | H220: =G220/G$228 -> 0.053705158 | I220: =IFERROR(E220/G$229,"-") -> 2.1106133
B221: Zimbabwe | C221: 72165.667 | D221: 16630000 | E221: 0.054 | G221: =C221/D221*1000000 -> 4339.4869 | H221: =G221/G$228 -> 0.055745466 | I221: =IFERROR(E221/G$229,"-") -> 6.3318399
B224: Original study countries | C224: =C5 -> GDP millions (USD) | D224: =D5 -> Population | E224: =E5 -> % GDP from Agriculture | G224: =G5 -> GDP per capita (USD) | H224: =H5 -> % of Weighted UK, US & German GDP per capita | I224: % Labour force in agriculture
B225: Germany | C225: =VLOOKUP($B225,$B$7:$E$221,2,0) -> 5815284.7 | D225: =VLOOKUP($B225,$B$7:$E$221,3,0) -> 84550000 | E225: =VLOOKUP($B225,$B$7:$E$212,4,0) -> 0.008 | G225: =C225/D225*1000000 -> 68779.239 | H225: =G225/G$228 -> 0.88354472 | I225: 0.01
B226: United Kingdom | C226: =VLOOKUP($B226,$B$7:$E$221,2,0) -> 4093449 | D226: =VLOOKUP($B226,$B$7:$E$221,3,0) -> 69140000 | E226: =VLOOKUP($B226,$B$7:$E$212,4,0) -> 0.006 | G226: =C226/D226*1000000 -> 59205.221 | H226: =G226/G$228 -> 0.76055597 | I226: 0.01
B227: United States | C227: =VLOOKUP($B227,$B$7:$E$221,2,0) -> 28456036 | D227: =VLOOKUP($B227,$B$7:$E$221,3,0) -> 345430000 | E227: =VLOOKUP($B227,$B$7:$E$212,4,0) -> 0.009 | G227: =C227/D227*1000000 -> 82378.588 | H227: =G227/G$228 -> 1.0582433 | I227: 0.02
E228: Average GDP per capita of Germany, UK and US weighted by GDP | G228: =((C225*G225)+(C226*G226)+(C227*G227))/SUM(C225:C227) -> 77844.661
E229: Average % GDP from Agriculture of Germany, US and US weighted by GDP | G229: =((C225*E225)+(C226*E226)+(C227*E227))/SUM(C225:C227) -> 0.0085283268
E230: Average % Labour force in Agriculture of Germany, US and US weighted by GDP | G230: =((C225*I225)+(C226*I226)+(C227*I227))/SUM(C225:C227) -> 0.017417231

Sheet Table Dev GDP, POP, AG
B1: TABLE DEVELOPMENT SHEET
B2: Cleaned-up and harmonised
B3: SEE BELOW THESE THREE TABLES FOR THE FINAL TABLE FOR USE IN THE 'GDP pop Data' WORKSHEET
B5: https://en.wikipedia.org/wiki/List_of_countries_by_GDP_(PPP) | J5: https://en.wikipedia.org/wiki/List_of_countries_and_dependencies_by_population | O5: https://en.wikipedia.org/wiki/List_of_countries_by_GDP_sector_composition
B6: GDP (PPP) | P6: 2017
B7: Country or territory | C7: IMF | D7: World Bank | E7: CIA | F7: GDP millions (USD) | H7: Country checker | J7: Location | K7: Population | M7: Country checker | O7: Country/Economy | P7: % GDP from Agriculture
B8: Afghanistan | C8: 72512 | D8: 91272 | E8: 82238 | F8: =AVERAGE(C8:E8) -> 82007.333 | H8: =IF(B8<>J8,"DOH!","OK") -> OK | J8: Afghanistan | K8: 43844000 | M8: =IF(J8<>O8,"DOH!","OK") -> OK | O8: Afghanistan | P8: 0.23
B9: Albania | C9: 63080 | D9: 63761 | E9: 51360 | F9: =AVERAGE(C9:E9) -> 59400.333 | H9: =IF(B9<>J9,"DOH!","OK") -> OK | J9: Albania | K9: 2363314 | M9: =IF(J9<>O9,"DOH!","OK") -> OK | O9: Albania | P9: 0.217
B10: Algeria | C10: 875334 | D10: 821721 | E10: 722912 | F10: =AVERAGE(C10:E10) -> 806655.67 | H10: =IF(B10<>J10,"DOH!","OK") -> OK | J10: Algeria | K10: 47400000 | M10: =IF(J10<>O10,"DOH!","OK") -> OK | O10: Algeria | P10: 0.133
B11: Andorra | C11: 6423 | D11: 6140 | E11: 5402 | F11: =AVERAGE(C11:E11) -> 5988.3333 | H11: =IF(B11<>J11,"DOH!","OK") -> OK | J11: Andorra | K11: 88306 | M11: =IF(J11<>O11,"DOH!","OK") -> OK | O11: Andorra | P11: 0.119
B12: Angola | C12: 402155 | D12: 316269 | E12: 278239 | F12: =AVERAGE(C12:E12) -> 332221 | H12: =IF(B12<>J12,"DOH!","OK") -> OK | J12: Angola | K12: 36170961 | M12: =IF(J12<>O12,"DOH!","OK") -> OK | O12: Angola | P12: 0.102
B13: Antigua and Barbuda | C13: 3333 | D13: 3151 | E13: 2772 | F13: =AVERAGE(C13:E13) -> 3085.3333 | H13: =IF(B13<>J13,"DOH!","OK") -> OK | J13: Antigua and Barbuda | K13: 103603 | M13: =IF(J13<>O13,"DOH!","OK") -> OK | O13: Antigua and Barbuda | P13: 0.018
B14: Argentina | C14: 1493423 | D14: 1378906 | E14: 1213000 | F14: =AVERAGE(C14:E14) -> 1361776.3 | H14: =IF(B14<>J14,"DOH!","OK") -> OK | J14: Argentina | K14: 46735004 | M14: =IF(J14<>O14,"DOH!","OK") -> OK | O14: Argentina | P14: 0.108
B15: Armenia | C15: 74294 | D15: 69234 | E15: 60909 | F15: =AVERAGE(C15:E15) -> 68145.667 | H15: =IF(B15<>J15,"DOH!","OK") -> OK | J15: Armenia | K15: 3081100 | M15: =IF(J15<>O15,"DOH!","OK") -> OK | O15: Armenia | P15: 0.167
B16: Aruba | C16: 5524 | D16: 4828 | E16: 4350 | F16: =AVERAGE(C16:E16) -> 4900.6667 | H16: =IF(B16<>J16,"DOH!","OK") -> OK | J16: Aruba | K16: 107566 | M16: =IF(J16<>O16,"DOH!","OK") -> OK | O16: Aruba | P16: 0.004
B17: Australia | C17: 1980022 | D17: 1936798 | E17: 1635000 | F17: =AVERAGE(C17:E17) -> 1850606.7 | H17: =IF(B17<>J17,"DOH!","OK") -> OK | J17: Australia | K17: 27536874 | M17: =IF(J17<>O17,"DOH!","OK") -> OK | O17: Australia | P17: 0.036
B18: Austria | C18: 682861 | D18: 657344 | E18: 581131 | F18: =AVERAGE(C18:E18) -> 640445.33 | H18: =IF(B18<>J18,"DOH!","OK") -> OK | J18: Austria | K18: 9200931 | M18: =IF(J18<>O18,"DOH!","OK") -> OK | O18: Austria | P18: 0.013
B19: Azerbaijan | C19: 272100 | D19: 255979 | E19: 225198 | F19: =AVERAGE(C19:E19) -> 251092.33 | H19: =IF(B19<>J19,"DOH!","OK") -> OK | J19: Azerbaijan | K19: 10241722 | M19: =IF(J19<>O19,"DOH!","OK") -> OK | O19: Azerbaijan | P19: 0.061
... B27: Benin | C27: 69509 | D27: 64136 | E27: 56424 | F27: =AVERAGE(C27:E27) -> 63356.333 | H27: =IF(B27<>J27,"DOH!","OK") -> OK | J27: Benin | K27: 13224860 | M27: =IF(J27<>O27,"DOH!","OK") -> OK | O27: Benin | P27: 0.261
B28: Bermuda | C28: — | D28: 7738 | E28: 6808 | F28: =AVERAGE(C28:E28) -> 7273 | H28: =IF(B28<>J28,"DOH!","OK") -> OK | J28: Bermuda | K28: 64055 | M28: =IF(J28<>O28,"DOH!","OK") -> OK | O28: Bermuda | P28: 0.009
B29: Bhutan | C29: 14106 | D29: 12782 | E29: 11517 | F29: =AVERAGE(C29:E29) -> 12801.667 | H29: =IF(B29<>J29,"DOH!","OK") -> OK | J29: Bhutan | K29: 784043 | M29: =IF(J29<>O29,"DOH!","OK") -> OK | O29: Bhutan | P29: 0.162
B30: Bolivia | C30: 144098 | D30: 138903 | E30: 122200 | F30: =AVERAGE(C30:E30) -> 135067 | H30: =IF(B30<>J30,"DOH!","OK") -> OK | J30: Bolivia | K30: 11365333 | M30: =IF(J30<>O30,"DOH!","OK") -> OK | O30: Bolivia | P30: 0.138
B31: Bosnia and Herzegovina | C31: 78655 | D31: 69522 | E31: 64641 | F31: =AVERAGE(C31:E31) -> 70939.333 | H31: =IF(B31<>J31,"DOH!","OK") -> OK | J31: Bosnia and Herzegovina | K31: 3422000 | M31: =IF(J31<>O31,"DOH!","OK") -> OK | O31: Bosnia and Herzegovina | P31: 0.068
B32: Botswana | C32: 52961 | D32: 51779 | E32: 45553 | F32: =AVERAGE(C32:E32) -> 50097.667 | H32: =IF(B32<>J32,"DOH!","OK") -> OK | J32: Botswana | K32: 2359609 | M32: =IF(J32<>O32,"DOH!","OK") -> OK | O32: Botswana | P32: 0.018
B33: Brazil | C33: 4958122 | D33: 4734651 | E33: 4165000 | F33: =AVERAGE(C33:E33) -> 4619257.7 | H33: =IF(B33<>J33,"DOH!","OK") -> OK | J33: Brazil | K33: 213421037 | M33: =IF(J33<>O33,"DOH!","OK") -> OK | O33: Brazil | P33: 0.066
B34: Brunei | C34: 43833 | D34: 41648 | E34: 36640 | F34: =AVERAGE(C34:E34) -> 40707 | H34: =IF(B34<>J34,"DOH!","OK") -> OK | J34: Brunei | K34: 455500 | M34: =IF(J34<>O34,"DOH!","OK") -> OK | O34: Brunei | P34: 0.012
B35: Bulgaria | C35: 264699 | D35: 264774 | E35: 219645 | F35: =AVERAGE(C35:E35) -> 249706 | H35: =IF(B35<>J35,"DOH!","OK") -> OK | J35: Bulgaria | K35: 6437360 | M35: =IF(J35<>O35,"DOH!","OK") -> OK | O35: Bulgaria | P35: 0.043
B36: Burkina Faso | C36: 72820 | D36: 68202 | E36: 60001 | F36: =AVERAGE(C36:E36) -> 67007.667 | H36: =IF(B36<>J36,"DOH!","OK") -> OK | J36: Burkina Faso | K36: 24070553 | M36: =IF(J36<>O36,"DOH!","OK") -> OK | O36: Burkina Faso | P36: 0.31
B37: Burundi | C37: 13975 | D37: 13343 | E37: 11739 | F37: =AVERAGE(C37:E37) -> 13019 | H37: =IF(B37<>J37,"DOH!","OK") -> OK | J37: Burundi | K37: 12332788 | M37: =IF(J37<>O37,"DOH!","OK") -> OK | O37: Burundi | P37: 0.395
B38: Cambodia | C38: 150047 | D38: 140580 | E38: 123676 | F38: =AVERAGE(C38:E38) -> 138101 | H38: =IF(B38<>J38,"DOH!","OK") -> OK | J38: Cambodia | K38: 17577760 | M38: =IF(J38<>O38,"DOH!","OK") -> OK | O38: Cambodia | P38: 0.253
B39: Cameroon | C39: 172974 | D39: 162845 | E39: 143264 | F39: =AVERAGE(C39:E39) -> 159694.33 | H39: =IF(B39<>J39,"DOH!","OK") -> OK | J39: Cameroon | K39: 29442327 | M39: =IF(J39<>O39,"DOH!","OK") -> OK | O39: Cameroon | P39: 0.167
B40: Canada | C40: 2730110 | D40: 2702880 | E40: 2341000 | F40: =AVERAGE(C40:E40) -> 2591330 | H40: =IF(B40<>J40,"DOH!","OK") -> OK | J40: Canada | K40: 41651653 | M40: =IF(J40<>O40,"DOH!","OK") -> OK | O40: Canada | P40: 0.016
B41: Cape Verde | C41: 6299 | D41: 5911 | E41: 5200 | F41: =AVERAGE(C41:E41) -> 5803.3333 | H41: =IF(B41<>J41,"DOH!","OK") -> OK | J41: Cape Verde | K41: 491233 | M41: =IF(J41<>O41,"DOH!","OK") -> OK | O41: Cape Verde | P41: 0.089
B42: Cayman Islands | C42: — | D42: 6332 | E42: 5705 | F42: =AVERAGE(C42:E42) -> 6018.5 | H42: =IF(B42<>J42,"DOH!","OK") -> OK | J42: Cayman Islands | K42: 84738 | M42: =IF(J42<>O42,"DOH!","OK") -> OK | O42: Cayman Islands | P42: 0.003
B43: Central African Republic | C43: 7332 | D43: 6736 | E43: 5926 | F43: =AVERAGE(C43:E43) -> 6664.6667 | H43: =IF(B43<>J43,"DOH!","OK") -> OK | J43: Central African Republic | K43: 6470307 | M43: =IF(J43<>O43,"DOH!","OK") -> OK | O43: Central African Republic | P43: 0.432
B44: Chad | C44: 56653 | D44: 60125 | E44: 52895 | F44: =AVERAGE(C44:E44) -> 56557.667 | H44: =IF(B44<>J44,"DOH!","OK") -> OK | J44: Chad | K44: 19340757 | M44: =IF(J44<>O44,"DOH!","OK") -> OK | O44: Chad | P44: 0.523
B45: Chile | C45: 710195 | D45: 684595 | E45: 596556 | F45: =AVERAGE(C45:E45) -> 663782 | H45: =IF(B45<>J45,"DOH!","OK") -> OK | J45: Chile | K45: 20206953 | M45: =IF(J45<>O45,"DOH!","OK") -> OK | O45: Chile | P45: 0.042
B46: China | C46: 40716448 | D46: 38190085 | E46: 33598000 | F46: =AVERAGE(C46:E46) -> 37501511 | H46: =IF(B46<>J46,"DOH!","OK") -> OK | J46: China | K46: 1408280000 | M46: =IF(J46<>O46,"DOH!","OK") -> OK | O46: China | P46: 0.079
B47: Colombia | C47: 1190795 | D47: 1136771 | E47: 978592 | F47: =AVERAGE(C47:E47) -> 1102052.7 | H47: =IF(B47<>J47,"DOH!","OK") -> OK | J47: Colombia | K47: 53057212 | M47: =IF(J47<>O47,"DOH!","OK") -> OK | O47: Colombia | P47: 0.072
B48: Comoros | C48: 3655 | D48: 3514 | E48: 3092 | F48: =AVERAGE(C48:E48) -> 3420.3333 | H48: =IF(B48<>J48,"DOH!","OK") -> OK | J48: Comoros | K48: 870038 | M48: =IF(J48<>O48,"DOH!","OK") -> OK | O48: Comoros | P48: 0.477
B49: Congo | C49: 42763 | D49: 44719 | E49: 19030 | F49: =AVERAGE(C49:E49) -> 35504 | H49: =IF(B49<>J49,"DOH!","OK") -> OK | J49: Congo | K49: 6142180 | M49: =IF(J49<>O49,"DOH!","OK") -> OK | O49: Congo | P49: 0.093
B50: Costa Rica | C50: 169034 | D50: 154220 | E50: 138371 | F50: =AVERAGE(C50:E50) -> 153875 | H50: =IF(B50<>J50,"DOH!","OK") -> OK | J50: Costa Rica | K50: 5309625 | M50: =IF(J50<>O50,"DOH!","OK") -> OK | O50: Costa Rica | P50: 0.055
B51: Croatia | C51: 198268 | D51: 187806 | E51: 164825 | F51: =AVERAGE(C51:E51) -> 183633 | H51: =IF(B51<>J51,"DOH!","OK") -> OK | J51: Croatia | K51: 3866233 | M51: =IF(J51<>O51,"DOH!","OK") -> OK | O51: Croatia | P51: 0.037
B52: Cuba | C52: — | D52: — | E52: 81165 | F52: =AVERAGE(C52:E52) -> 81165 | H52: =IF(B52<>J52,"DOH!","OK") -> OK | J52: Cuba | K52: 9748007 | M52: =IF(J52<>O52,"DOH!","OK") -> OK | O52: Cuba | P52: 0.04
B53: Curaçao | C53: — | D53: 4785 | E53: 4312 | F53: =AVERAGE(C53:E53) -> 4548.5 | H53: =IF(B53<>J53,"DOH!","OK") -> OK | J53: Curaçao | K53: 156115 | M53: =IF(J53<>O53,"DOH!","OK") -> OK | O53: Curaçao | P53: 0.007
B54: Cyprus | C54: 61298 | D54: 57562 | E54: 50055 | F54: =AVERAGE(C54:E54) -> 56305 | H54: =IF(B54<>J54,"DOH!","OK") -> OK | J54: Cyprus | K54: 966400 | M54: =IF(J54<>O54,"DOH!","OK") -> OK | O54: Cyprus | P54: 0.02
B55: Czech Republic | C55: 647322 | D55: 618168 | E55: 521928 | F55: =AVERAGE(C55:E55) -> 595806 | H55: =IF(B55<>J55,"DOH!","OK") -> OK | J55: Czech Republic | K55: 10882341 | M55: =IF(J55<>O55,"DOH!","OK") -> OK | O55: Czech Republic | P55: 0.023
B56: Denmark | C56: 533752 | D56: 475256 | E56: 440558 | F56: =AVERAGE(C56:E56) -> 483188.67 | H56: =IF(B56<>J56,"DOH!","OK") -> OK | J56: Denmark | K56: 6004342 | M56: =IF(J56<>O56,"DOH!","OK") -> OK | O56: Denmark | P56: 0.013
B57: Djibouti | C57: 9942 | D57: 8187 | E57: 7995 | F57: =AVERAGE(C57:E57) -> 8708 | H57: =IF(B57<>J57,"DOH!","OK") -> OK | J57: Djibouti | K57: 1066809 | M57: =IF(J57<>O57,"DOH!","OK") -> OK | O57: Djibouti | P57: 0.024
B58: Dominica | C58: 1473 | D58: 1410 | E58: 1241 | F58: =AVERAGE(C58:E58) -> 1374.6667 | H58: =IF(B58<>J58,"DOH!","OK") -> OK | J58: Dominica | K58: 67408 | M58: =IF(J58<>O58,"DOH!","OK") -> OK | O58: Dominica | P58: 0.223
B59: Dominican Republic | C59: 336082 | D59: 314728 | E59: 276884 | F59: =AVERAGE(C59:E59) -> 309231.33 | H59: =IF(B59<>J59,"DOH!","OK") -> OK | J59: Dominican Republic | K59: 10771504 | M59: =IF(J59<>O59,"DOH!","OK") -> OK | O59: Dominican Republic | P59: 0.056
B60: DR Congo | C60: 200760 | D60: 186833 | E60: 164367 | F60: =AVERAGE(C60:E60) -> 183986.67 | H60: =IF(B60<>J60,"DOH!","OK") -> OK | J60: DR Congo | K60: 112832000 | M60: =IF(J60<>O60,"DOH!","OK") -> OK | O60: DR Congo | P60: 0.197
B61: Ecuador | C61: 300122 | D61: 287271 | E61: 252728 | F61: =AVERAGE(C61:E61) -> 280040.33 | H61: =IF(B61<>J61,"DOH!","OK") -> OK | J61: Ecuador | K61: 18103660 | M61: =IF(J61<>O61,"DOH!","OK") -> OK | O61: Ecuador | P61: 0.067
B62: Egypt | C62: 2371530 | D62: 2225198 | E62: 1958000 | F62: =AVERAGE(C62:E62) -> 2184909.3 | H62: =IF(B62<>J62,"DOH!","OK") -> OK | J62: Egypt | K62: 107271260 | M62: =IF(J62<>O62,"DOH!","OK") -> OK | O62: Egypt | P62: 0.117
B63: El Salvador | C63: 88282 | D63: 84070 | E63: 73961 | F63: =AVERAGE(C63:E63) -> 82104.333 | H63: =IF(B63<>J63,"DOH!","OK") -> OK | J63: El Salvador | K63: 6029976 | M63: =IF(J63<>O63,"DOH!","OK") -> OK | O63: El Salvador | P63: 0.12
B64: Equatorial Guinea | C64: 33003 | D64: 33245 | E64: 29248 | F64: =AVERAGE(C64:E64) -> 31832 | H64: =IF(B64<>J64,"DOH!","OK") -> OK | J64: Equatorial Guinea | K64: 1668768 | M64: =IF(J64<>O64,"DOH!","OK") -> OK | O64: Equatorial Guinea | P64: 0.025
B65: Eritrea | C65: 6405 | D65: — | E65: 2534 | F65: =AVERAGE(C65:E65) -> 4469.5 | H65: =IF(B65<>J65,"DOH!","OK") -> OK | J65: Eritrea | K65: 3607000 | M65: =IF(J65<>O65,"DOH!","OK") -> OK | O65: Eritrea | P65: 0.117
B66: Estonia | C66: 68235 | D66: 67685 | E66: 57001 | F66: =AVERAGE(C66:E66) -> 64307 | H66: =IF(B66<>J66,"DOH!","OK") -> OK | J66: Estonia | K66: 1369995 | M66: =IF(J66<>O66,"DOH!","OK") -> OK | O66: Estonia | P66: 0.028
B67: Eswatini | C67: 16322 | D67: 14646 | E67: 12885 | F67: =AVERAGE(C67:E67) -> 14617.667 | H67: =IF(B67<>J67,"DOH!","OK") -> OK | J67: Eswatini | K67: 1235549 | M67: =IF(J67<>O67,"DOH!","OK") -> OK | O67: Eswatini | P67: 0.065
B68: Ethiopia | C68: 484408 | D68: 432957 | E68: 380895 | F68: =AVERAGE(C68:E68) -> 432753.33 | H68: =IF(B68<>J68,"DOH!","OK") -> OK | J68: Ethiopia | K68: 111652998 | M68: =IF(J68<>O68,"DOH!","OK") -> OK | O68: Ethiopia | P68: 0.348
B69: Faroe Islands | C69: — | D69: 4255 | E69: 3834 | F69: =AVERAGE(C69:E69) -> 4044.5 | H69: =IF(B69<>J69,"DOH!","OK") -> OK | J69: Faroe Islands | K69: 55146 | M69: =IF(J69<>O69,"DOH!","OK") -> OK | O69: Faroe Islands | P69: 0.18
B70: Fiji | C70: 15657 | D70: 14891 | E70: 13100 | F70: =AVERAGE(C70:E70) -> 14549.333 | H70: =IF(B70<>J70,"DOH!","OK") -> OK | J70: Fiji | K70: 900869 | M70: =IF(J70<>O70,"DOH!","OK") -> OK | O70: Fiji | P70: 0.135
B71: Finland | C71: 373156 | D71: 361296 | E71: 313591 | F71: =AVERAGE(C71:E71) -> 349347.67 | H71: =IF(B71<>J71,"DOH!","OK") -> OK | J71: Finland | K71: 5650325 | M71: =IF(J71<>O71,"DOH!","OK") -> OK | O71: Finland | P71: 0.027
B72: France | C72: 4503783 | D72: 4201560 | E72: 3732000 | F72: =AVERAGE(C72:E72) -> 4145781 | H72: =IF(B72<>J72,"DOH!","OK") -> OK | J72: France | K72: 68688000 | M72: =IF(J72<>O72,"DOH!","OK") -> OK | O72: France | P72: 0.007
B73: Gabon | C73: 57445 | D73: 54612 | E73: 48045 | F73: =AVERAGE(C73:E73) -> 53367.333 | H73: =IF(B73<>J73,"DOH!","OK") -> OK | J73: Gabon | K73: 2469296 | M73: =IF(J73<>O73,"DOH!","OK") -> OK | O73: Gabon | P73: 0.05
B74: Gambia | C74: 10345 | D74: 9509 | E74: 8365 | F74: =AVERAGE(C74:E74) -> 9406.3333 | H74: =IF(B74<>J74,"DOH!","OK") -> OK | J74: Gambia | K74: 2422712 | M74: =IF(J74<>O74,"DOH!","OK") -> OK | O74: Gambia | P74: 0.204
B75: Georgia | C75: 113583 | D75: 104403 | E75: 91849 | F75: =AVERAGE(C75:E75) -> 103278.33 | H75: =IF(B75<>J75,"DOH!","OK") -> OK | J75: Georgia | K75: 3704500 | M75: =IF(J75<>O75,"DOH!","OK") -> OK | O75: Georgia | P75: 0.082
B76: Germany | C76: 6161002 | D76: 6037852 | E76: 5247000 | F76: =AVERAGE(C76:E76) -> 5815284.7 | H76: =IF(B76<>J76,"DOH!","OK") -> OK | J76: Germany | K76: 83517030 | M76: =IF(J76<>O76,"DOH!","OK") -> OK | O76: Germany | P76: 0.007
B77: Ghana | C77: 295118 | D77: 276355 | E77: 243124 | F77: =AVERAGE(C77:E77) -> 271532.33 | H77: =IF(B77<>J77,"DOH!","OK") -> OK | J77: Ghana | K77: 33742380 | M77: =IF(J77<>O77,"DOH!","OK") -> OK | O77: Ghana | P77: 0.183
B78: Greece | C78: 467590 | D78: 457879 | E78: 392205 | F78: =AVERAGE(C78:E78) -> 439224.67 | H78: =IF(B78<>J78,"DOH!","OK") -> OK | J78: Greece | K78: 10400720 | M78: =IF(J78<>O78,"DOH!","OK") -> OK | O78: Greece | P78: 0.041
B79: Greenland | C79: — | D79: 4483 | E79: 4040 | F79: =AVERAGE(C79:E79) -> 4261.5 | H79: =IF(B79<>J79,"DOH!","OK") -> OK | J79: Greenland | K79: 56542 | M79: =IF(J79<>O79,"DOH!","OK") -> OK | O79: Greenland | P79: 0.159
B80: Grenada | C80: 2520 | D80: 2364 | E80: 2080 | F80: =AVERAGE(C80:E80) -> 2321.3333 | H80: =IF(B80<>J80,"DOH!","OK") -> OK | J80: Grenada | K80: 109021 | M80: =IF(J80<>O80,"DOH!","OK") -> OK | O80: Grenada | P80: 0.068
B81: Guatemala | C81: 282833 | D81: 264475 | E81: 232673 | F81: =AVERAGE(C81:E81) -> 259993.67 | H81: =IF(B81<>J81,"DOH!","OK") -> OK | J81: Guatemala | K81: 18079810 | M81: =IF(J81<>O81,"DOH!","OK") -> OK | O81: Guatemala | P81: 0.133
B82: Guinea | C82: 75052 | D82: 67564 | E82: 59439 | F82: =AVERAGE(C82:E82) -> 67351.667 | H82: =IF(B82<>J82,"DOH!","OK") -> OK | J82: Guinea | K82: 14363931 | M82: =IF(J82<>O82,"DOH!","OK") -> OK | O82: Guinea | P82: 0.198
B83: Guinea-Bissau | C83: 6620 | D83: 6720 | E83: 5912 | F83: =AVERAGE(C83:E83) -> 6417.3333 | H83: =IF(B83<>J83,"DOH!","OK") -> OK | J83: Guinea-Bissau | K83: 1781308 | M83: =IF(J83<>O83,"DOH!","OK") -> OK | O83: Guinea-Bissau | P83: 0.5
B84: Guyana | C84: 75294 | D84: 66409 | E84: 58423 | F84: =AVERAGE(C84:E84) -> 66708.667 | H84: =IF(B84<>J84,"DOH!","OK") -> OK | J84: Guyana | K84: 772975 | M84: =IF(J84<>O84,"DOH!","OK") -> OK | O84: Guyana | P84: 0.154
B85: Haiti | C85: 38198 | D85: 37477 | E85: 32971 | F85: =AVERAGE(C85:E85) -> 36215.333 | H85: =IF(B85<>J85,"DOH!","OK") -> OK | J85: Haiti | K85: 11867032 | M85: =IF(J85<>O85,"DOH!","OK") -> OK | O85: Haiti | P85: 0.221
B86: Honduras | C86: 85984 | D86: 81041 | E86: 71297 | F86: =AVERAGE(C86:E86) -> 79440.667 | H86: =IF(B86<>J86,"DOH!","OK") -> OK | J86: Honduras | K86: 9892632 | M86: =IF(J86<>O86,"DOH!","OK") -> OK | O86: Honduras | P86: 0.142
B87: Hong Kong | C87: 589806 | D87: 565931 | E87: 497880 | F87: =AVERAGE(C87:E87) -> 551205.67 | H87: =IF(B87<>J87,"DOH!","OK") -> OK | J87: Hong Kong | K87: 7527500 | M87: =IF(J87<>O87,"DOH!","OK") -> OK | O87: Hong Kong | P87: 0.001
B88: Hungary | C88: 464419 | D88: 455509 | E88: 389207 | F88: =AVERAGE(C88:E88) -> 436378.33 | H88: =IF(B88<>J88,"DOH!","OK") -> OK | J88: Hungary | K88: 9539502 | M88: =IF(J88<>O88,"DOH!","OK") -> OK | O88: Hungary | P88: 0.039
B89: Iceland | C89: 31763 | D89: 31664 | E89: 26561 | F89: =AVERAGE(C89:E89) -> 29996 | H89: =IF(B89<>J89,"DOH!","OK") -> OK | J89: Iceland | K89: 391810 | M89: =IF(J89<>O89,"DOH!","OK") -> OK | O89: Iceland | P89: 0.058
B90: India | C90: 17647050 | D90: 16190820 | E90: 14244000 | F90: =AVERAGE(C90:E90) -> 16027290 | H90: =IF(B90<>J90,"DOH!","OK") -> OK | J90: India | K90: 1417492000 | M90: =IF(J90<>O90,"DOH!","OK") -> OK | O90: India | P90: 0.154
B91: Indonesia | C91: 5009483 | D91: 4662888 | E91: 4102000 | F91: =AVERAGE(C91:E91) -> 4591457 | H91: =IF(B91<>J91,"DOH!","OK") -> OK | J91: Indonesia | K91: 284438782 | M91: =IF(J91<>O91,"DOH!","OK") -> OK | O91: Indonesia | P91: 0.137
... B112: Libya | C112: 123987 | D112: 102993 | E112: 90609 | F112: =AVERAGE(C112:E112) -> 105863 | H112: =IF(B112<>J112,"DOH!","OK") -> OK | J112: Libya | K112: 7459000 | M112: =IF(J112<>O112,"DOH!","OK") -> OK | O112: Libya | P112: 0.013
B113: Liechtenstein | C113: — | D113: — | E113: 7172 | F113: =AVERAGE(C113:E113) -> 7172 | H113: =IF(B113<>J113,"DOH!","OK") -> OK | J113: Liechtenstein | K113: 40900 | M113: =IF(J113<>O113,"DOH!","OK") -> OK | O113: Liechtenstein | P113: 0.07
B114: Lithuania | C114: 165442 | D114: 157150 | E114: 136227 | F114: =AVERAGE(C114:E114) -> 152939.67 | H114: =IF(B114<>J114,"DOH!","OK") -> OK | J114: Lithuania | K114: 2894548 | M114: =IF(J114<>O114,"DOH!","OK") -> OK | O114: Lithuania | P114: 0.035
B115: Luxembourg | C115: 104822 | D115: 102181 | E115: 86871 | F115: =AVERAGE(C115:E115) -> 97958 | H115: =IF(B115<>J115,"DOH!","OK") -> OK | J115: Luxembourg | K115: 681973 | M115: =IF(J115<>O115,"DOH!","OK") -> OK | O115: Luxembourg | P115: 0.003
B116: Macau | C116: 93712 | D116: 88120 | E116: 77524 | F116: =AVERAGE(C116:E116) -> 86452 | H116: =IF(B116<>J116,"DOH!","OK") -> OK | J116: Macau | K116: 685900 | M116: =IF(J116<>O116,"DOH!","OK") -> OK | O116: Macau | P116: 0
B117: Madagascar | C117: 64242 | D117: 60207 | E117: 52968 | F117: =AVERAGE(C117:E117) -> 59139 | H117: =IF(B117<>J117,"DOH!","OK") -> OK | J117: Madagascar | K117: 31727042 | M117: =IF(J117<>O117,"DOH!","OK") -> OK | O117: Madagascar | P117: 0.24
B118: Malawi | C118: 42772 | D118: 40267 | E118: 35425 | F118: =AVERAGE(C118:E118) -> 39488 | H118: =IF(B118<>J118,"DOH!","OK") -> OK | J118: Malawi | K118: 20734262 | M118: =IF(J118<>O118,"DOH!","OK") -> OK | O118: Malawi | P118: 0.286
B119: Malaysia | C119: 1471655 | D119: 1377111 | E119: 1212000 | F119: =AVERAGE(C119:E119) -> 1353588.7 | H119: =IF(B119<>J119,"DOH!","OK") -> OK | J119: Malaysia | K119: 34231700 | M119: =IF(J119<>O119,"DOH!","OK") -> OK | O119: Malaysia | P119: 0.088
B120: Maldives | C120: 15030 | D120: 14009 | E120: 12325 | F120: =AVERAGE(C120:E120) -> 13788 | H120: =IF(B120<>J120,"DOH!","OK") -> OK | J120: Maldives | K120: 515132 | M120: =IF(J120<>O120,"DOH!","OK") -> OK | O120: Maldives | P120: 0.03
B121: Mali | C121: 72738 | D121: 80992 | E121: 71253 | F121: =AVERAGE(C121:E121) -> 74994.333 | H121: =IF(B121<>J121,"DOH!","OK") -> OK | J121: Mali | K121: 22395489 | M121: =IF(J121<>O121,"DOH!","OK") -> OK | O121: Mali | P121: 0.418
B122: Malta | C122: 43188 | D122: 38690 | E122: 34731 | F122: =AVERAGE(C122:E122) -> 38869.667 | H122: =IF(B122<>J122,"DOH!","OK") -> OK | J122: Malta | K122: 574250 | M122: =IF(J122<>O122,"DOH!","OK") -> OK | O122: Malta | P122: 0.011
B123: Marshall Islands | C123: 281 | D123: 308 | E123: 271 | F123: =AVERAGE(C123:E123) -> 286.66667 | H123: =IF(B123<>J123,"DOH!","OK") -> OK | J123: Marshall Islands | K123: 42418 | M123: =IF(J123<>O123,"DOH!","OK") -> OK | O123: Marshall Islands | P123: 0.044
B124: Mauritania | C124: 40060 | D124: 37588 | E124: 33069 | F124: =AVERAGE(C124:E124) -> 36905.667 | H124: =IF(B124<>J124,"DOH!","OK") -> OK | J124: Mauritania | K124: 4927532 | M124: =IF(J124<>O124,"DOH!","OK") -> OK | O124: Mauritania | P124: 0.278
B125: Mauritius | C125: 41352 | D125: 39109 | E125: 34406 | F125: =AVERAGE(C125:E125) -> 38289 | H125: =IF(B125<>J125,"DOH!","OK") -> OK | J125: Mauritius | K125: 1243741 | M125: =IF(J125<>O125,"DOH!","OK") -> OK | O125: Mauritius | P125: 0.04
... B128: Moldova | C128: 46365 | D128: 44719 | E128: 39342 | F128: =AVERAGE(C128:E128) -> 43475.333 | H128: =IF(B128<>J128,"DOH!","OK") -> OK | J128: Moldova | K128: 2381300 | M128: =IF(J128<>O128,"DOH!","OK") -> OK | O128: Moldova | P128: 0.177
B129: Monaco | C129: — | D129: — | E129: 8924 | F129: =AVERAGE(C129:E129) -> 8924 | H129: =IF(B129<>J129,"DOH!","OK") -> OK | J129: Monaco | K129: 38423 | M129: =IF(J129<>O129,"DOH!","OK") -> OK | O129: Monaco | P129: 0
B130: Mongolia | C130: 73279 | D130: 67315 | E130: 59221 | F130: =AVERAGE(C130:E130) -> 66605 | H130: =IF(B130<>J130,"DOH!","OK") -> OK | J130: Mongolia | K130: 3544835 | M130: =IF(J130<>O130,"DOH!","OK") -> OK | O130: Mongolia | P130: 0.121
...

Sheet Table of Hazards (AI only)
B1: Summary Table of EIQ and PEA for ACTIVE INGREDIENTS (HAZARD)
B2: This is NOT field level risk as the concentration and application rate are not included
I4: EIQ | M4: PEA
B5: Active Ingredient | C5: EIQ Farmworker | D5: EIQ Consumer | E5: EIQ Environmental | F5: PEA Farmworker | G5: PEA Consumer | H5: PEA Environmental | I5: Farmworker | J5: Consumer | K5: Environmental | L5: Average | M5: Farmworker | N5: Consumer | O5: Environmental | P5: Sum
B6: Abamectin | C6: 90 | D6: 4 | E6: 44 | F6: 0.60749519 | G6: 4.6156268 | H6: 1.8452632 | I6: =C6 -> 90 | J6: =D6 -> 4 | K6: =E6 -> 44 | L6: =AVERAGE(C6:E6) -> 46 | M6: =F6 -> 0.60749519 | N6: =G6 -> 4.6156268 | O6: =H6 -> 1.8452632 | P6: =SUM(F6:H6) -> 7.0683852
B7: Acequinocyl | C7: 15 | D7: 3.5 | E7: 18 | F7: 0.3037476 | G7: 4.6156268 | H7: 1.1651701 | I7: =SUM(C7,D7) -> 18.5 | J7: =D7 -> 3.5 | K7: =E7 -> 18 | L7: =AVERAGE(C7:E7) -> 12.166667 | M7: =F7 -> 0.3037476 | N7: =G7 -> 4.6156268 | O7: =H7 -> 1.1651701 | P7: =SUM(F7:H7) -> 6.0845445
B8: Acetamiprid | C8: 6 | D8: 4 | E8: 42 | F8: 0.3037476 | G8: 4.6156268 | H8: 1.4304357 | I8: =SUM(C8,D8) -> 10 | J8: =D8 -> 4 | K8: =E8 -> 42 | L8: =AVERAGE(C8:E8) -> 17.333333 | M8: =F8 -> 0.3037476 | N8: =G8 -> 4.6156268 | O8: =H8 -> 1.4304357 | P8: =SUM(F8:H8) -> 6.3498101
B9: Acibenzolar-S-methyl | C9: 21 | D9: 11.5 | E9: 14 | F9: 0.3037476 | G9: 4.6156268 | H9: 1.1651701 | I9: =SUM(C9,D9) -> 32.5 | J9: =D9 -> 11.5 | K9: =E9 -> 14 | L9: =AVERAGE(C9:E9) -> 15.5 | M9: =F9 -> 0.3037476 | N9: =G9 -> 4.6156268 | O9: =H9 -> 1.1651701 | P9: =SUM(F9:H9) -> 6.0845445
B10: Acrinathrin | C10: 15 | D10: 6 | E10: 51 | F10: 0.3037476 | G10: 4.6156268 | H10: 2.0650746 | I10: =SUM(C10,D10) -> 21 | J10: =D10 -> 6 | K10: =E10 -> 51 | L10: =AVERAGE(C10:E10) -> 24 | M10: =F10 -> 0.3037476 | N10: =G10 -> 4.6156268 | O10: =H10 -> 2.0650746 | P10: =SUM(F10:H10) -> 6.984449
B11: Alpha-cypermethrin | C11: 18 | D11: 7 | E11: 41 | F11: 0.3037476 | G11: 4.6156268 | H11: 1.799809 | I11: =SUM(C11,D11) -> 25 | J11: =D11 -> 7 | K11: =E11 -> 41 | L11: =AVERAGE(C11:E11) -> 22 | M11: =F11 -> 0.3037476 | N11: =G11 -> 4.6156268 | O11: =H11 -> 1.799809 | P11: =SUM(F11:H11) -> 6.7191835
B12: Ametoctradin | C12: 12 | D12: 3 | E12: 26 | F12: 0.3037476 | G12: 4.6156268 | H12: 1.5799976 | I12: =SUM(C12,D12) -> 15 | J12: =D12 -> 3 | K12: =E12 -> 26 | L12: =AVERAGE(C12:E12) -> 13.666667 | M12: =F12 -> 0.3037476 | N12: =G12 -> 4.6156268 | O12: =H12 -> 1.5799976 | P12: =SUM(F12:H12) -> 6.4993721
B13: Amisulbrom | C13: 21 | D13: 4.5 | E13: 16 | F13: 0.3037476 | G13: 4.6156268 | H13: 1.5799976 | I13: =SUM(C13,D13) -> 25.5 | J13: =D13 -> 4.5 | K13: =E13 -> 16 | L13: =AVERAGE(C13:E13) -> 13.833333 | M13: =F13 -> 0.3037476 | N13: =G13 -> 4.6156268 | O13: =H13 -> 1.5799976 | P13: =SUM(F13:H13) -> 6.4993721
B14: Azadirachtin | C14: 6 | D14: 6 | E14: 42 | F14: 0.3037476 | G14: 5.230615 | H14: 1.5799976 | I14: =SUM(C14,D14) -> 12 | J14: =D14 -> 6 | K14: =E14 -> 42 | L14: =AVERAGE(C14:E14) -> 18 | M14: =F14 -> 0.3037476 | N14: =G14 -> 5.230615 | O14: =H14 -> 1.5799976 | P14: =SUM(F14:H14) -> 7.1143602
B15: Azoxystrobin | C15: 15 | D15: 25.5 | E15: 26 | F15: 0.3037476 | G15: 9.2312536 | H15: 1.5799976 | I15: =SUM(C15,D15) -> 40.5 | J15: =D15 -> 25.5 | K15: =E15 -> 26 | L15: =AVERAGE(C15:E15) -> 22.166667 | M15: =F15 -> 0.3037476 | N15: =G15 -> 9.2312536 | O15: =H15 -> 1.5799976 | P15: =SUM(F15:H15) -> 11.114999
B16: Bacillus thuringiensis Berliner subsp. Kurstaki | C16: 6 | D16: 2 | E16: 12 | F16: 0.3037476 | G16: 4.6156268 | H16: 1.1651701 | I16: =SUM(C16,D16) -> 8 | J16: =D16 -> 2 | K16: =E16 -> 12 | L16: =AVERAGE(C16:E16) -> 6.6666667 | M16: =F16 -> 0.3037476 | N16: =G16 -> 4.6156268 | O16: =H16 -> 1.1651701 | P16: =SUM(F16:H16) -> 6.0845445
B17: Beauveria bassiana ATCC 74040 | C17: 6 | D17: 2 | E17: 12 | F17: 0.3037476 | G17: 4.6156268 | H17: 1.1651701 | I17: =SUM(C17,D17) -> 8 | J17: =D17 -> 2 | K17: =E17 -> 12 | L17: =AVERAGE(C17:E17) -> 6.6666667 | M17: =F17 -> 0.3037476 | N17: =G17 -> 4.6156268 | O17: =H17 -> 1.1651701 | P17: =SUM(F17:H17) -> 6.0845445
B18: Benalaxyl | C18: 12 | D18: 15 | E18: 17 | F18: 0.3037476 | G18: 4.9231209 | H18: 1.1651701 | I18: =SUM(C18,D18) -> 27 | J18: =D18 -> 15 | K18: =E18 -> 17 | L18: =AVERAGE(C18:E18) -> 14.666667 | M18: =F18 -> 0.3037476 | N18: =G18 -> 4.9231209 | O18: =H18 -> 1.1651701 | P18: =SUM(F18:H18) -> 6.3920386
... B129: Zoxamide | C129: 6 | D129: 4 | E129: 14 | F129: 0.3037476 | G129: 4.6156268 | H129: 1.1651701 | I129: =SUM(C129,D129) -> 10 | J129: =D129 -> 4 | K129: =E129 -> 14 | L129: =AVERAGE(C129:E129) -> 8 | M129: =F129 -> 0.3037476 | N129: =G129 -> 4.6156268 | O129: =H129 -> 1.1651701 | P129: =SUM(F129:H129) -> 6.0845445
D149: PEA (€ per 1 kg of ai)
D150: Farmworker | E150: Consumer | F150: Environmental | G150: Sum
C151: Abamectin | D151: =VLOOKUP($C151,$B$6:$P$129,12,0) -> 0.60749519 | E151: =VLOOKUP($C151,$B$6:$P$129,13,0) -> 4.6156268 | F151: =VLOOKUP($C151,$B$6:$P$129,14,0) -> 1.8452632 | G151: =VLOOKUP($C151,$B$6:$P$129,15,0) -> 7.0683852
C152: Acetamiprid | D152: =VLOOKUP($C152,$B$6:$P$129,12,0) -> 0.3037476 | E152: =VLOOKUP($C152,$B$6:$P$129,13,0) -> 4.6156268 | F152: =VLOOKUP($C152,$B$6:$P$129,14,0) -> 1.4304357 | G152: =VLOOKUP($C152,$B$6:$P$129,15,0) -> 6.3498101
C153: Alpha-cypermethrin | D153: =VLOOKUP($C153,$B$6:$P$129,12,0) -> 0.3037476 | E153: =VLOOKUP($C153,$B$6:$P$129,13,0) -> 4.6156268 | F153: =VLOOKUP($C153,$B$6:$P$129,14,0) -> 1.799809 | G153: =VLOOKUP($C153,$B$6:$P$129,15,0) -> 6.7191835
C154: Azadirachtin | D154: =VLOOKUP($C154,$B$6:$P$129,12,0) -> 0.3037476 | E154: =VLOOKUP($C154,$B$6:$P$129,13,0) -> 5.230615 | F154: =VLOOKUP($C154,$B$6:$P$129,14,0) -> 1.5799976 | G154: =VLOOKUP($C154,$B$6:$P$129,15,0) -> 7.1143602
C155: Chlorantraniliprole | D155: =VLOOKUP($C155,$B$6:$P$129,12,0) -> 0.3037476 | E155: =VLOOKUP($C155,$B$6:$P$129,13,0) -> 5.230615 | F155: =VLOOKUP($C155,$B$6:$P$129,14,0) -> 1.5799976 | G155: =VLOOKUP($C155,$B$6:$P$129,15,0) -> 7.1143602
C156: Chlorpyrifos-methyl | D156: =VLOOKUP($C156,$B$6:$P$129,12,0) -> 0.3037476 | E156: =VLOOKUP($C156,$B$6:$P$129,13,0) -> 4.6156268 | F156: =VLOOKUP($C156,$B$6:$P$129,14,0) -> 1.3849815 | G156: =VLOOKUP($C156,$B$6:$P$129,15,0) -> 6.3043559
C157: Deltamethrin | D157: =VLOOKUP($C157,$B$6:$P$129,12,0) -> 0.3037476 | E157: =VLOOKUP($C157,$B$6:$P$129,13,0) -> 4.6156268 | F157: =VLOOKUP($C157,$B$6:$P$129,14,0) -> 2.0650746 | G157: =VLOOKUP($C157,$B$6:$P$129,15,0) -> 6.984449
C158: Etofenprox | D158: =VLOOKUP($C158,$B$6:$P$129,12,0) -> 0.3037476 | E158: =VLOOKUP($C158,$B$6:$P$129,13,0) -> 4.6156268 | F158: =VLOOKUP($C158,$B$6:$P$129,14,0) -> 2.0650746 | G158: =VLOOKUP($C158,$B$6:$P$129,15,0) -> 6.984449
C159: Imidacloprid | D159: =VLOOKUP($C159,$B$6:$P$129,12,0) -> 0.3037476 | E159: =VLOOKUP($C159,$B$6:$P$129,13,0) -> 9.5387477 | F159: =VLOOKUP($C159,$B$6:$P$129,14,0) -> 2.3303402 | G159: =VLOOKUP($C159,$B$6:$P$129,15,0) -> 12.172836
C160: Lambda-cyhalothrin | D160: =VLOOKUP($C160,$B$6:$P$129,12,0) -> 0.55953505 | E160: =VLOOKUP($C160,$B$6:$P$129,13,0) -> 4.6156268 | F160: =VLOOKUP($C160,$B$6:$P$129,14,0) -> 2.0650746 | G160: =VLOOKUP($C160,$B$6:$P$129,15,0) -> 7.2402365
C161: Malathion | D161: =VLOOKUP($C161,$B$6:$P$129,12,0) -> 0.3037476 | E161: =VLOOKUP($C161,$B$6:$P$129,13,0) -> 4.6156268 | F161: =VLOOKUP($C161,$B$6:$P$129,14,0) -> 2.0650746 | G161: =VLOOKUP($C161,$B$6:$P$129,15,0) -> 6.984449
C162: Phosmet | D162: =VLOOKUP($C162,$B$6:$P$129,12,0) -> 0.55953505 | E162: =VLOOKUP($C162,$B$6:$P$129,13,0) -> 4.6156268 | F162: =VLOOKUP($C162,$B$6:$P$129,14,0) -> 1.9155127 | G162: =VLOOKUP($C162,$B$6:$P$129,15,0) -> 7.0906745
... C165: Spirotetramat | D165: =VLOOKUP($C165,$B$6:$P$129,12,0) -> 0.3037476 | E165: =VLOOKUP($C165,$B$6:$P$129,13,0) -> 4.6156268 | F165: =VLOOKUP($C165,$B$6:$P$129,14,0) -> 1.5799976 | G165: =VLOOKUP($C165,$B$6:$P$129,15,0) -> 6.4993721
C167: THESE CELLS ARE LINKED TO TABLE ABOVE CUT AND PASTE THESE AS VALUES TO THE ECONOMIC MODEL '2.8 PEA' WORKSHEET
D168: Pyrethroids | I168: Neonicitinoids | K168: Keto-enols | M168: Organophosphates | P168: IGRs | Q168: Diamides | R168: Avermectins
D169: Deltamethrin | E169: Lambda-cyhalothrin | F169: Alpha-cypermethrin | G169: Etofenprox | H169: Pyrethrins | I169: Imidacloprid | J169: Acetamiprid | K169: Spirotetramat | L169: Spinosad | M169: Chlorpyrifos-methyl | N169: Phosmet | O169: Malathion | P169: Azadirachtin | Q169: Chlorantraniliprole | R169: Abamectin
B170: PEA (€/ha per 1 kg of ai) | C170: Farmworker | D170: =D157 -> 0.3037476 | E170: =D160 -> 0.55953505 | F170: =D153 -> 0.3037476 | G170: =D158 -> 0.3037476 | H170: =D163 -> 0.3037476 | I170: =D159 -> 0.3037476 | J170: =D152 -> 0.3037476 | K170: =D165 -> 0.3037476 | L170: =D164 -> 0.3037476 | M170: =D156 -> 0.3037476 | N170: =D162 -> 0.55953505 | O170: =D161 -> 0.3037476 | P170: =D154 -> 0.3037476 | Q170: =D155 -> 0.3037476 | R170: =D151 -> 0.60749519
C171: Consumer | D171: =E157 -> 4.6156268 | E171: =E160 -> 4.6156268 | F171: =E153 -> 4.6156268 | G171: =E158 -> 4.6156268 | H171: =E163 -> 4.6156268 | I171: =E159 -> 9.5387477 | J171: =E152 -> 4.6156268 | K171: =E165 -> 4.6156268 | L171: =E164 -> 4.9231209 | M171: =E156 -> 4.6156268 | N171: =E162 -> 4.6156268 | O171: =E161 -> 4.6156268 | P171: =E154 -> 5.230615 | Q171: =E155 -> 5.230615 | R171: =E151 -> 4.6156268
C172: Environmental | D172: =F157 -> 2.0650746 | E172: =F160 -> 2.0650746 | F172: =F153 -> 1.799809 | G172: =F158 -> 2.0650746 | H172: =F163 -> 1.799809 | I172: =F159 -> 2.3303402 | J172: =F152 -> 1.4304357 | K172: =F165 -> 1.5799976 | L172: =F164 -> 1.3849815 | M172: =F156 -> 1.3849815 | N172: =F162 -> 1.9155127 | O172: =F161 -> 2.0650746 | P172: =F154 -> 1.5799976 | Q172: =F155 -> 1.5799976 | R172: =F151 -> 1.8452632
C173: Sum | D173: =G157 -> 6.984449 | E173: =G160 -> 7.2402365 | F173: =G153 -> 6.7191835 | G173: =G158 -> 6.984449 | H173: =G163 -> 6.7191835 | I173: =G159 -> 12.172836 | J173: =G152 -> 6.3498101 | K173: =G165 -> 6.4993721 | L173: =G164 -> 6.61185 | M173: =G156 -> 6.3043559 | N173: =G162 -> 7.0906745 | O173: =G161 -> 6.984449 | P173: =G154 -> 7.1143602 | Q173: =G155 -> 7.1143602 | R173: =G151 -> 7.0683852

Sheet Table of Risks (Field)
B1: Summary Table of EIQ and PEA for ACTIVE INGREDIENTS (FIELD) | AQ1: Max EIQ H&S | AR1: =LARGE(V6:V508,15) -> 41.643
B2: Field level risk takes into account the AI concentration and field application rate | AQ2: Max EIQ Ecol | AR2: =LARGE(X6:X509,30) -> 10.734375
AQ3: Max PEA H&S | AR3: =LARGE(Y6:Y509,15) -> 35.333333
V4: EIQ | Y4: PEA (€/ha) | AQ4: Max PEA Ecol | AR4: =LARGE(AA6:AA509,20) -> 0.56798674
B5: Crop | C5: Type of insecticide | D5: Active ingredients (AI) | E5: Active Ingredient 1 | F5: AI-1 conc (kg/l) | G5: Active Ingredient 2 | H5: AI-2 conc (kg/l) | I5: Formulation application rate (l/ha kg/ha) | J5: EIQ Farm worker HAZ - AI1 | K5: EIQ Consumer HAZ - AI1 | L5: EIQ Environmental HAZ - AI1 | M5: PEA Farm worker HAZ - AI1 | N5: PEA Consumer HAZ - AI1 | O5: PEA Environmental HAZ - AI1 | P5: EIQ Farm worker HAZ - AI2 | Q5: EIQ Consumer HAZ - AI2 | R5: EIQ Environmental HAZ - AI2 | S5: PEA Farm worker HAZ - AI2 | T5: PEA Consumer HAZ - AI2 | U5: PEA Environmental HAZ - AI2 | V5: Farm worker Field | W5: Consumer Field | X5: Environmental Field | Y5: Farm worker Field | Z5: Consumer Field | AA5: Environmental Field | AB5: Total (€/ha) | AC5: Trade name
B6: Grapes | C6: Black rot | D6: Difenoconazole | E6: Difenoconazole | F6: 0.25 | I6: 0.2 | J6: =IF(ISBLANK($E6),0,VLOOKUP($E6,'Table of Hazards (AI only)'!$B$6:$P$129,8,)) -> 37 | L6: =IF(ISBLANK($E6),0,VLOOKUP($E6,'Table of Hazards (AI only)'!$B$6:$P$129,9,)) -> 19 | M6: =IF(ISBLANK($E6),0,VLOOKUP($E6,'Table of Hazards (AI only)'!$B$6:$P$129,11,)) -> 18 | O6: =IF(ISBLANK($E6),0,VLOOKUP($E6,'Table of Hazards (AI only)'!$B$6:$P$129,12,)) -> 0.3037476 | P6: =IF(ISBLANK($G6),0,VLOOKUP($G6,'Table of Hazards (AI only)'!$B$6:$P$129,8,)) -> 0 | R6: =IF(ISBLANK($G6),0,VLOOKUP($G6,'Table of Hazards (AI only)'!$B$6:$P$129,9,)) -> 0 | S6: =IF(ISBLANK($G6),0,VLOOKUP($G6,'Table of Hazards (AI only)'!$B$6:$P$129,11,)) -> 0 | U6: =IF(ISBLANK($G6),0,VLOOKUP($G6,'Table of Hazards (AI only)'!$B$6:$P$129,12,)) -> 0 | V6: =(($F6*J6)+($H6*P6))*$I6 -> 1.85 | X6: =(($F6*L6)+($H6*R6))*$I6 -> 0.95 | Y6: =(($F6*M6)+($H6*S6))*$I6 -> 0.9 | AA6: =(($F6*O6)+($H6*U6))*$I6 -> 0.01518738 | AC6: SCORE 25 EC
B7: Grapes | C7: Black rot | D7: Mancozeb | E7: Mancozeb | F7: 0.8 | I7: 2 | J7: =IF(ISBLANK($E7),0,VLOOKUP($E7,'Table of Hazards (AI only)'!$B$6:$P$129,8,)) -> 29 | L7: =IF(ISBLANK($E7),0,VLOOKUP($E7,'Table of Hazards (AI only)'!$B$6:$P$129,9,)) -> 5 | M7: =IF(ISBLANK($E7),0,VLOOKUP($E7,'Table of Hazards (AI only)'!$B$6:$P$129,11,)) -> 15 | O7: =IF(ISBLANK($E7),0,VLOOKUP($E7,'Table of Hazards (AI only)'!$B$6:$P$129,12,)) -> 0.3037476 | P7: =IF(ISBLANK($G7),0,VLOOKUP($G7,'Table of Hazards (AI only)'!$B$6:$P$129,8,)) -> 0 | R7: =IF(ISBLANK($G7),0,VLOOKUP($G7,'Table of Hazards (AI only)'!$B$6:$P$129,9,)) -> 0 | S7: =IF(ISBLANK($G7),0,VLOOKUP($G7,'Table of Hazards (AI only)'!$B$6:$P$129,11,)) -> 0 | U7: =IF(ISBLANK($G7),0,VLOOKUP($G7,'Table of Hazards (AI only)'!$B$6:$P$129,12,)) -> 0 | V7: =(($F7*J7)+($H7*P7))*$I7 -> 46.4 | X7: =(($F7*L7)+($H7*R7))*$I7 -> 8 | Y7: =(($F7*M7)+($H7*S7))*$I7 -> 24 | AA7: =(($F7*O7)+($H7*U7))*$I7 -> 0.48599615 | AC7: Mancozeb Plus 80WP
B8: Grapes | C8: Black rot | D8: Myclobutanil | E8: Myclobutanil | F8: 0.045 | I8: 1.5 | J8: =IF(ISBLANK($E8),0,VLOOKUP($E8,'Table of Hazards (AI only)'!$B$6:$P$129,8,)) -> 29 | L8: =IF(ISBLANK($E8),0,VLOOKUP($E8,'Table of Hazards (AI only)'!$B$6:$P$129,9,)) -> 17 | M8: =IF(ISBLANK($E8),0,VLOOKUP($E8,'Table of Hazards (AI only)'!$B$6:$P$129,11,)) -> 24.666667 | O8: =IF(ISBLANK($E8),0,VLOOKUP($E8,'Table of Hazards (AI only)'!$B$6:$P$129,12,)) -> 0.3037476 | P8: =IF(ISBLANK($G8),0,VLOOKUP($G8,'Table of Hazards (AI only)'!$B$6:$P$129,8,)) -> 0 | R8: =IF(ISBLANK($G8),0,VLOOKUP($G8,'Table of Hazards (AI only)'!$B$6:$P$129,9,)) -> 0 | S8: =IF(ISBLANK($G8),0,VLOOKUP($G8,'Table of Hazards (AI only)'!$B$6:$P$129,11,)) -> 0 | U8: =IF(ISBLANK($G8),0,VLOOKUP($G8,'Table of Hazards (AI only)'!$B$6:$P$129,12,)) -> 0 | V8: =(($F8*J8)+($H8*P8))*$I8 -> 1.9575 | X8: =(($F8*L8)+($H8*R8))*$I8 -> 1.1475 | Y8: =(($F8*M8)+($H8*S8))*$I8 -> 1.665 | AA8: =(($F8*O8)+($H8*U8))*$I8 -> 0.020502963 | AC8: Thiocur Forte
B9: Grapes | C9: Black rot | D9: Penconazole | E9: Penconazole | F9: 0.1 | I9: 0.3 | J9: =IF(ISBLANK($E9),0,VLOOKUP($E9,'Table of Hazards (AI only)'!$B$6:$P$129,8,)) -> 43 | L9: =IF(ISBLANK($E9),0,VLOOKUP($E9,'Table of Hazards (AI only)'!$B$6:$P$129,9,)) -> 22 | M9: =IF(ISBLANK($E9),0,VLOOKUP($E9,'Table of Hazards (AI only)'!$B$6:$P$129,11,)) -> 29.333333 | O9: =IF(ISBLANK($E9),0,VLOOKUP($E9,'Table of Hazards (AI only)'!$B$6:$P$129,12,)) -> 0.3037476 | P9: =IF(ISBLANK($G9),0,VLOOKUP($G9,'Table of Hazards (AI only)'!$B$6:$P$129,8,)) -> 0 | R9: =IF(ISBLANK($G9),0,VLOOKUP($G9,'Table of Hazards (AI only)'!$B$6:$P$129,9,)) -> 0 | S9: =IF(ISBLANK($G9),0,VLOOKUP($G9,'Table of Hazards (AI only)'!$B$6:$P$129,11,)) -> 0 | U9: =IF(ISBLANK($G9),0,VLOOKUP($G9,'Table of Hazards (AI only)'!$B$6:$P$129,12,)) -> 0 | V9: =(($F9*J9)+($H9*P9))*$I9 -> 1.29 | X9: =(($F9*L9)+($H9*R9))*$I9 -> 0.66 | Y9: =(($F9*M9)+($H9*S9))*$I9 -> 0.88 | AA9: =(($F9*O9)+($H9*U9))*$I9 -> 0.0091124279 | AC9: Topas 10 EC
B10: Grapes | C10: Black rot | D10: Tetraconazole | E10: Tetraconazole | F10: 0.125 | I10: 0.2 | J10: =IF(ISBLANK($E10),0,VLOOKUP($E10,'Table of Hazards (AI only)'!$B$6:$P$129,8,)) -> 48 | L10: =IF(ISBLANK($E10),0,VLOOKUP($E10,'Table of Hazards (AI only)'!$B$6:$P$129,9,)) -> 30 | M10: =IF(ISBLANK($E10),0,VLOOKUP($E10,'Table of Hazards (AI only)'!$B$6:$P$129,11,)) -> 34 | O10: =IF(ISBLANK($E10),0,VLOOKUP($E10,'Table of Hazards (AI only)'!$B$6:$P$129,12,)) -> 0.3037476 | P10: =IF(ISBLANK($G10),0,VLOOKUP($G10,'Table of Hazards (AI only)'!$B$6:$P$129,8,)) -> 0 | R10: =IF(ISBLANK($G10),0,VLOOKUP($G10,'Table of Hazards (AI only)'!$B$6:$P$129,9,)) -> 0 | S10: =IF(ISBLANK($G10),0,VLOOKUP($G10,'Table of Hazards (AI only)'!$B$6:$P$129,11,)) -> 0 | U10: =IF(ISBLANK($G10),0,VLOOKUP($G10,'Table of Hazards (AI only)'!$B$6:$P$129,12,)) -> 0 | V10: =(($F10*J10)+($H10*P10))*$I10 -> 1.2 | X10: =(($F10*L10)+($H10*R10))*$I10 -> 0.75 | Y10: =(($F10*M10)+($H10*S10))*$I10 -> 0.85 | AA10: =(($F10*O10)+($H10*U10))*$I10 -> 0.0075936899 | AC10: Domark
B11: Grapes | C11: Black rot | D11: Trifloxystrobin | E11: Trifloxystrobin | F11: 0.5 | I11: 0.2 | J11: =IF(ISBLANK($E11),0,VLOOKUP($E11,'Table of Hazards (AI only)'!$B$6:$P$129,8,)) -> 22 | L11: =IF(ISBLANK($E11),0,VLOOKUP($E11,'Table of Hazards (AI only)'!$B$6:$P$129,9,)) -> 4 | M11: =IF(ISBLANK($E11),0,VLOOKUP($E11,'Table of Hazards (AI only)'!$B$6:$P$129,11,)) -> 12 | O11: =IF(ISBLANK($E11),0,VLOOKUP($E11,'Table of Hazards (AI only)'!$B$6:$P$129,12,)) -> 0.3037476 | P11: =IF(ISBLANK($G11),0,VLOOKUP($G11,'Table of Hazards (AI only)'!$B$6:$P$129,8,)) -> 0 | R11: =IF(ISBLANK($G11),0,VLOOKUP($G11,'Table of Hazards (AI only)'!$B$6:$P$129,9,)) -> 0 | S11: =IF(ISBLANK($G11),0,VLOOKUP($G11,'Table of Hazards (AI only)'!$B$6:$P$129,11,)) -> 0 | U11: =IF(ISBLANK($G11),0,VLOOKUP($G11,'Table of Hazards (AI only)'!$B$6:$P$129,12,)) -> 0 | V11: =(($F11*J11)+($H11*P11))*$I11 -> 2.2 | X11: =(($F11*L11)+($H11*R11))*$I11 -> 0.4 | Y11: =(($F11*M11)+($H11*S11))*$I11 -> 1.2 | AA11: =(($F11*O11)+($H11*U11))*$I11 -> 0.03037476 | AC11: Flint
B12: Grapes | C12: Dead-arm | D12: Mancozeb | E12: Mancozeb | F12: 0.8 | I12: 2 | J12: =IF(ISBLANK($E12),0,VLOOKUP($E12,'Table of Hazards (AI only)'!$B$6:$P$129,8,)) -> 29 | L12: =IF(ISBLANK($E12),0,VLOOKUP($E12,'Table of Hazards (AI only)'!$B$6:$P$129,9,)) -> 5 | M12: =IF(ISBLANK($E12),0,VLOOKUP($E12,'Table of Hazards (AI only)'!$B$6:$P$129,11,)) -> 15 | O12: =IF(ISBLANK($E12),0,VLOOKUP($E12,'Table of Hazards (AI only)'!$B$6:$P$129,12,)) -> 0.3037476 | P12: =IF(ISBLANK($G12),0,VLOOKUP($G12,'Table of Hazards (AI only)'!$B$6:$P$129,8,)) -> 0 | R12: =IF(ISBLANK($G12),0,VLOOKUP($G12,'Table of Hazards (AI only)'!$B$6:$P$129,9,)) -> 0 | S12: =IF(ISBLANK($G12),0,VLOOKUP($G12,'Table of Hazards (AI only)'!$B$6:$P$129,11,)) -> 0 | U12: =IF(ISBLANK($G12),0,VLOOKUP($G12,'Table of Hazards (AI only)'!$B$6:$P$129,12,)) -> 0 | V12: =(($F12*J12)+($H12*P12))*$I12 -> 46.4 | X12: =(($F12*L12)+($H12*R12))*$I12 -> 8 | Y12: =(($F12*M12)+($H12*S12))*$I12 -> 24 | AA12: =(($F12*O12)+($H12*U12))*$I12 -> 0.48599615 | AC12: Mancozeb Plus 80WP
B13: Grapes | C13: Dead-arm | D13: Metiram | E13: Metiram | F13: 0.44 | I13: 2.5 | J13: =IF(ISBLANK($E13),0,VLOOKUP($E13,'Table of Hazards (AI only)'!$B$6:$P$129,8,)) -> 18.5 | L13: =IF(ISBLANK($E13),0,VLOOKUP($E13,'Table of Hazards (AI only)'!$B$6:$P$129,9,)) -> 3.5 | M13: =IF(ISBLANK($E13),0,VLOOKUP($E13,'Table of Hazards (AI only)'!$B$6:$P$129,11,)) -> 12.833333 | O13: =IF(ISBLANK($E13),0,VLOOKUP($E13,'Table of Hazards (AI only)'!$B$6:$P$129,12,)) -> 0.3037476 | P13: =IF(ISBLANK($G13),0,VLOOKUP($G13,'Table of Hazards (AI only)'!$B$6:$P$129,8,)) -> 0 | R13: =IF(ISBLANK($G13),0,VLOOKUP($G13,'Table of Hazards (AI only)'!$B$6:$P$129,9,)) -> 0 | S13: =IF(ISBLANK($G13),0,VLOOKUP($G13,'Table of Hazards (AI only)'!$B$6:$P$129,11,)) -> 0 | U13: =IF(ISBLANK($G13),0,VLOOKUP($G13,'Table of Hazards (AI only)'!$B$6:$P$129,12,)) -> 0 | V13: =(($F13*J13)+($H13*P13))*$I13 -> 20.35 | X13: =(($F13*L13)+($H13*R13))*$I13 -> 3.85 | Y13: =(($F13*M13)+($H13*S13))*$I13 -> 14.116667 | AA13: =(($F13*O13)+($H13*U13))*$I13 -> 0.33412236 | AC13: Enervin Top
B14: Grapes | C14: Dead-arm | D14: Propineb | E14: Propineb | F14: 0.7 | I14: 1.75 | J14: =IF(ISBLANK($E14),0,VLOOKUP($E14,'Table of Hazards (AI only)'!$B$6:$P$129,8,)) -> 28 | L14: =IF(ISBLANK($E14),0,VLOOKUP($E14,'Table of Hazards (AI only)'!$B$6:$P$129,9,)) -> 10 | M14: =IF(ISBLANK($E14),0,VLOOKUP($E14,'Table of Hazards (AI only)'!$B$6:$P$129,11,)) -> 24.666667 | O14: =IF(ISBLANK($E14),0,VLOOKUP($E14,'Table of Hazards (AI only)'!$B$6:$P$129,12,)) -> 0.3037476 | P14: =IF(ISBLANK($G14),0,VLOOKUP($G14,'Table of Hazards (AI only)'!$B$6:$P$129,8,)) -> 0 | R14: =IF(ISBLANK($G14),0,VLOOKUP($G14,'Table of Hazards (AI only)'!$B$6:$P$129,9,)) -> 0 | S14: =IF(ISBLANK($G14),0,VLOOKUP($G14,'Table of Hazards (AI only)'!$B$6:$P$129,11,)) -> 0 | U14: =IF(ISBLANK($G14),0,VLOOKUP($G14,'Table of Hazards (AI only)'!$B$6:$P$129,12,)) -> 0 | V14: =(($F14*J14)+($H14*P14))*$I14 -> 34.3 | X14: =(($F14*L14)+($H14*R14))*$I14 -> 12.25 | Y14: =(($F14*M14)+($H14*S14))*$I14 -> 30.216667 | AA14: =(($F14*O14)+($H14*U14))*$I14 -> 0.37209081 | AC14: Antracol 70wg
B15: Grapes | C15: Dead-arm | D15: Sulphur | E15: Sulphur | F15: 0.8 | I15: 1.25 | J15: =IF(ISBLANK($E15),0,VLOOKUP($E15,'Table of Hazards (AI only)'!$B$6:$P$129,8,)) -> 11.5 | L15: =IF(ISBLANK($E15),0,VLOOKUP($E15,'Table of Hazards (AI only)'!$B$6:$P$129,9,)) -> 2.5 | M15: =IF(ISBLANK($E15),0,VLOOKUP($E15,'Table of Hazards (AI only)'!$B$6:$P$129,11,)) -> 9.1666667 | O15: =IF(ISBLANK($E15),0,VLOOKUP($E15,'Table of Hazards (AI only)'!$B$6:$P$129,12,)) -> 0.3037476 | P15: =IF(ISBLANK($G15),0,VLOOKUP($G15,'Table of Hazards (AI only)'!$B$6:$P$129,8,)) -> 0 | R15: =IF(ISBLANK($G15),0,VLOOKUP($G15,'Table of Hazards (AI only)'!$B$6:$P$129,9,)) -> 0 | S15: =IF(ISBLANK($G15),0,VLOOKUP($G15,'Table of Hazards (AI only)'!$B$6:$P$129,11,)) -> 0 | U15: =IF(ISBLANK($G15),0,VLOOKUP($G15,'Table of Hazards (AI only)'!$B$6:$P$129,12,)) -> 0 | V15: =(($F15*J15)+($H15*P15))*$I15 -> 11.5 | X15: =(($F15*L15)+($H15*R15))*$I15 -> 2.5 | Y15: =(($F15*M15)+($H15*S15))*$I15 -> 9.1666667 | AA15: =(($F15*O15)+($H15*U15))*$I15 -> 0.3037476 | AC15: Zolfo 80 wp
B16: Grapes | C16: Downy Mildew | D16: Cyazofamid + Disodium phosphonate | E16: Cyazofamid | F16: 0.025 | G16: Disodium phosphonate | H16: 0.25 | I16: 4 | J16: =IF(ISBLANK($E16),0,VLOOKUP($E16,'Table of Hazards (AI only)'!$B$6:$P$129,8,)) -> 15 | L16: =IF(ISBLANK($E16),0,VLOOKUP($E16,'Table of Hazards (AI only)'!$B$6:$P$129,9,)) -> 3 | M16: =IF(ISBLANK($E16),0,VLOOKUP($E16,'Table of Hazards (AI only)'!$B$6:$P$129,11,)) -> 9.6666667 | O16: =IF(ISBLANK($E16),0,VLOOKUP($E16,'Table of Hazards (AI only)'!$B$6:$P$129,12,)) -> 0.3037476 | P16: =IF(ISBLANK($G16),0,VLOOKUP($G16,'Table of Hazards (AI only)'!$B$6:$P$129,8,)) -> 33 | R16: =IF(ISBLANK($G16),0,VLOOKUP($G16,'Table of Hazards (AI only)'!$B$6:$P$129,9,)) -> 13 | S16: =IF(ISBLANK($G16),0,VLOOKUP($G16,'Table of Hazards (AI only)'!$B$6:$P$129,11,)) -> 40.333333 | U16: =IF(ISBLANK($G16),0,VLOOKUP($G16,'Table of Hazards (AI only)'!$B$6:$P$129,12,)) -> 0.3037476 | V16: =(($F16*J16)+($H16*P16))*$I16 -> 34.5 | X16: =(($F16*L16)+($H16*R16))*$I16 -> 13.3 | Y16: =(($F16*M16)+($H16*S16))*$I16 -> 41.3 | AA16: =(($F16*O16)+($H16*U16))*$I16 -> 0.33412236 | AC16: Mildicut
B17: Grapes | C17: Downy Mildew | D17: Fosetyl-Aluminium | E17: Fosetyl-Aluminium | F17: 0.08 | I17: 2.5 | J17: =IF(ISBLANK($E17),0,VLOOKUP($E17,'Table of Hazards (AI only)'!$B$6:$P$129,8,)) -> 14.5 | L17: =IF(ISBLANK($E17),0,VLOOKUP($E17,'Table of Hazards (AI only)'!$B$6:$P$129,9,)) -> 5.5 | M17: =IF(ISBLANK($E17),0,VLOOKUP($E17,'Table of Hazards (AI only)'!$B$6:$P$129,11,)) -> 10.166667 | O17: =IF(ISBLANK($E17),0,VLOOKUP($E17,'Table of Hazards (AI only)'!$B$6:$P$129,12,)) -> 0.3037476 | P17: =IF(ISBLANK($G17),0,VLOOKUP($G17,'Table of Hazards (AI only)'!$B$6:$P$129,8,)) -> 0 | R17: =IF(ISBLANK($G17),0,VLOOKUP($G17,'Table of Hazards (AI only)'!$B$6:$P$129,9,)) -> 0 | S17: =IF(ISBLANK($G17),0,VLOOKUP($G17,'Table of Hazards (AI only)'!$B$6:$P$129,11,)) -> 0 | U17: =IF(ISBLANK($G17),0,VLOOKUP($G17,'Table of Hazards (AI only)'!$B$6:$P$129,12,)) -> 0 | V17: =(($F17*J17)+($H17*P17))*$I17 -> 2.9 | X17: =(($F17*L17)+($H17*R17))*$I17 -> 1.1 | Y17: =(($F17*M17)+($H17*S17))*$I17 -> 2.0333333 | AA17: =(($F17*O17)+($H17*U17))*$I17 -> 0.060749519 | AC17: Jupiter WG
B18: Grapes | C18: Downy Mildew | D18: Ametoctradin | E18: Ametoctradin | F18: 0.12 | I18: 2.5 | J18: =IF(ISBLANK($E18),0,VLOOKUP($E18,'Table of Hazards (AI only)'!$B$6:$P$129,8,)) -> 15 | L18: =IF(ISBLANK($E18),0,VLOOKUP($E18,'Table of Hazards (AI only)'!$B$6:$P$129,9,)) -> 3 | M18: =IF(ISBLANK($E18),0,VLOOKUP($E18,'Table of Hazards (AI only)'!$B$6:$P$129,11,)) -> 13.666667 | O18: =IF(ISBLANK($E18),0,VLOOKUP($E18,'Table of Hazards (AI only)'!$B$6:$P$129,12,)) -> 0.3037476 | P18: =IF(ISBLANK($G18),0,VLOOKUP($G18,'Table of Hazards (AI only)'!$B$6:$P$129,8,)) -> 0 | R18: =IF(ISBLANK($G18),0,VLOOKUP($G18,'Table of Hazards (AI only)'!$B$6:$P$129,9,)) -> 0 | S18: =IF(ISBLANK($G18),0,VLOOKUP($G18,'Table of Hazards (AI only)'!$B$6:$P$129,11,)) -> 0 | U18: =IF(ISBLANK($G18),0,VLOOKUP($G18,'Table of Hazards (AI only)'!$B$6:$P$129,12,)) -> 0 | V18: =(($F18*J18)+($H18*P18))*$I18 -> 4.5 | X18: =(($F18*L18)+($H18*R18))*$I18 -> 0.9 | Y18: =(($F18*M18)+($H18*S18))*$I18 -> 4.1 | AA18: =(($F18*O18)+($H18*U18))*$I18 -> 0.091124279 | AC18: Enervin Top
B19: Grapes | C19: Downy Mildew | D19: Amisulbrom | E19: Amisulbrom | F19: 0.2 | I19: 0.375 | J19: =IF(ISBLANK($E19),0,VLOOKUP($E19,'Table of Hazards (AI only)'!$B$6:$P$129,8,)) -> 25.5 | L19: =IF(ISBLANK($E19),0,VLOOKUP($E19,'Table of Hazards (AI only)'!$B$6:$P$129,9,)) -> 4.5 | M19: =IF(ISBLANK($E19),0,VLOOKUP($E19,'Table of Hazards (AI only)'!$B$6:$P$129,11,)) -> 13.833333 | O19: =IF(ISBLANK($E19),0,VLOOKUP($E19,'Table of Hazards (AI only)'!$B$6:$P$129,12,)) -> 0.3037476 | P19: =IF(ISBLANK($G19),0,VLOOKUP($G19,'Table of Hazards (AI only)'!$B$6:$P$129,8,)) -> 0 | R19: =IF(ISBLANK($G19),0,VLOOKUP($G19,'Table of Hazards (AI only)'!$B$6:$P$129,9,)) -> 0 | S19: =IF(ISBLANK($G19),0,VLOOKUP($G19,'Table of Hazards (AI only)'!$B$6:$P$129,11,)) -> 0 | U19: =IF(ISBLANK($G19),0,VLOOKUP($G19,'Table of Hazards (AI only)'!$B$6:$P$129,12,)) -> 0 | V19: =(($F19*J19)+($H19*P19))*$I19 -> 1.9125 | X19: =(($F19*L19)+($H19*R19))*$I19 -> 0.3375 | Y19: =(($F19*M19)+($H19*S19))*$I19 -> 1.0375 | AA19: =(($F19*O19)+($H19*U19))*$I19 -> 0.02278107 | AC19: Leimay
B20: Grapes | C20: Downy Mildew | D20: Benalaxyl | E20: Benalaxyl | F20: 0.04 | I20: 2.5 | J20: =IF(ISBLANK($E20),0,VLOOKUP($E20,'Table of Hazards (AI only)'!$B$6:$P$129,8,)) -> 27 | L20: =IF(ISBLANK($E20),0,VLOOKUP($E20,'Table of Hazards (AI only)'!$B$6:$P$129,9,)) -> 15 | M20: =IF(ISBLANK($E20),0,VLOOKUP($E20,'Table of Hazards (AI only)'!$B$6:$P$129,11,)) -> 14.666667 | O20: =IF(ISBLANK($E20),0,VLOOKUP($E20,'Table of Hazards (AI only)'!$B$6:$P$129,12,)) -> 0.3037476 | P20: =IF(ISBLANK($G20),0,VLOOKUP($G20,'Table of Hazards (AI only)'!$B$6:$P$129,8,)) -> 0 | R20: =IF(ISBLANK($G20),0,VLOOKUP($G20,'Table of Hazards (AI only)'!$B$6:$P$129,9,)) -> 0 | S20: =IF(ISBLANK($G20),0,VLOOKUP($G20,'Table of Hazards (AI only)'!$B$6:$P$129,11,)) -> 0 | U20: =IF(ISBLANK($G20),0,VLOOKUP($G20,'Table of Hazards (AI only)'!$B$6:$P$129,12,)) -> 0 | V20: =(($F20*J20)+($H20*P20))*$I20 -> 2.7 | X20: =(($F20*L20)+($H20*R20))*$I20 -> 1.5 | Y20: =(($F20*M20)+($H20*S20))*$I20 -> 1.4666667 | AA20: =(($F20*O20)+($H20*U20))*$I20 -> 0.03037476 | AC20: Fantic
B21: Grapes | C21: Downy Mildew | D21: Benalaxyl-M | E21: Benalaxyl-M | F21: 0.04 | I21: 2.5 | J21: =IF(ISBLANK($E21),0,VLOOKUP($E21,'Table of Hazards (AI only)'!$B$6:$P$129,8,)) -> 43.5 | L21: =IF(ISBLANK($E21),0,VLOOKUP($E21,'Table of Hazards (AI only)'!$B$6:$P$129,9,)) -> 23.5 | M21: =IF(ISBLANK($E21),0,VLOOKUP($E21,'Table of Hazards (AI only)'!$B$6:$P$129,11,)) -> 26.5 | O21: =IF(ISBLANK($E21),0,VLOOKUP($E21,'Table of Hazards (AI only)'!$B$6:$P$129,12,)) -> 0.3037476 | P21: =IF(ISBLANK($G21),0,VLOOKUP($G21,'Table of Hazards (AI only)'!$B$6:$P$129,8,)) -> 0 | R21: =IF(ISBLANK($G21),0,VLOOKUP($G21,'Table of Hazards (AI only)'!$B$6:$P$129,9,)) -> 0 | S21: =IF(ISBLANK($G21),0,VLOOKUP($G21,'Table of Hazards (AI only)'!$B$6:$P$129,11,)) -> 0 | U21: =IF(ISBLANK($G21),0,VLOOKUP($G21,'Table of Hazards (AI only)'!$B$6:$P$129,12,)) -> 0 | V21: =(($F21*J21)+($H21*P21))*$I21 -> 4.35 | X21: =(($F21*L21)+($H21*R21))*$I21 -> 2.35 | Y21: =(($F21*M21)+($H21*S21))*$I21 -> 2.65 | AA21: =(($F21*O21)+($H21*U21))*$I21 -> 0.03037476 | AC21: Galben
B22: Grapes | C22: Downy Mildew | D22: Benthiavalicarb | E22: Benthiavalicarb | F22: 0.0175 | I22: 1.8 | J22: =IF(ISBLANK($E22),0,VLOOKUP($E22,'Table of Hazards (AI only)'!$B$6:$P$129,8,)) -> 50 | L22: =IF(ISBLANK($E22),0,VLOOKUP($E22,'Table of Hazards (AI only)'!$B$6:$P$129,9,)) -> 20 | M22: =IF(ISBLANK($E22),0,VLOOKUP($E22,'Table of Hazards (AI only)'!$B$6:$P$129,11,)) -> 40 | O22: =IF(ISBLANK($E22),0,VLOOKUP($E22,'Table of Hazards (AI only)'!$B$6:$P$129,12,)) -> 0.35170774 | P22: =IF(ISBLANK($G22),0,VLOOKUP($G22,'Table of Hazards (AI only)'!$B$6:$P$129,8,)) -> 0 | R22: =IF(ISBLANK($G22),0,VLOOKUP($G22,'Table of Hazards (AI only)'!$B$6:$P$129,9,)) -> 0 | S22: =IF(ISBLANK($G22),0,VLOOKUP($G22,'Table of Hazards (AI only)'!$B$6:$P$129,11,)) -> 0 | U22: =IF(ISBLANK($G22),0,VLOOKUP($G22,'Table of Hazards (AI only)'!$B$6:$P$129,12,)) -> 0 | V22: =(($F22*J22)+($H22*P22))*$I22 -> 1.575 | X22: =(($F22*L22)+($H22*R22))*$I22 -> 0.63 | Y22: =(($F22*M22)+($H22*S22))*$I22 -> 1.26 | AA22: =(($F22*O22)+($H22*U22))*$I22 -> 0.011078794 | AC22: Vincare
B23: Grapes | C23: Downy Mildew | D23: Cymoxanil | E23: Cymoxanil | F23: 0.02 | I23: 0.65 | J23: =IF(ISBLANK($E23),0,VLOOKUP($E23,'Table of Hazards (AI only)'!$B$6:$P$129,8,)) -> 25.5 | L23: =IF(ISBLANK($E23),0,VLOOKUP($E23,'Table of Hazards (AI only)'!$B$6:$P$129,9,)) -> 4.5 | M23: =IF(ISBLANK($E23),0,VLOOKUP($E23,'Table of Hazards (AI only)'!$B$6:$P$129,11,)) -> 17.166667 | O23: =IF(ISBLANK($E23),0,VLOOKUP($E23,'Table of Hazards (AI only)'!$B$6:$P$129,12,)) -> 0.3037476 | P23: =IF(ISBLANK($G23),0,VLOOKUP($G23,'Table of Hazards (AI only)'!$B$6:$P$129,8,)) -> 0 | R23: =IF(ISBLANK($G23),0,VLOOKUP($G23,'Table of Hazards (AI only)'!$B$6:$P$129,9,)) -> 0 | S23: =IF(ISBLANK($G23),0,VLOOKUP($G23,'Table of Hazards (AI only)'!$B$6:$P$129,11,)) -> 0 | U23: =IF(ISBLANK($G23),0,VLOOKUP($G23,'Table of Hazards (AI only)'!$B$6:$P$129,12,)) -> 0 | V23: =(($F23*J23)+($H23*P23))*$I23 -> 0.3315 | X23: =(($F23*L23)+($H23*R23))*$I23 -> 0.0585 | Y23: =(($F23*M23)+($H23*S23))*$I23 -> 0.22316667 | AA23: =(($F23*O23)+($H23*U23))*$I23 -> 0.0039487188 | AC23: Curzate
B24: Grapes | C24: Downy Mildew | D24: Copper oxychloride | E24: Copper oxychloride | F24: 0.35 | I24: 1.75 | J24: =IF(ISBLANK($E24),0,VLOOKUP($E24,'Table of Hazards (AI only)'!$B$6:$P$129,8,)) -> 37 | L24: =IF(ISBLANK($E24),0,VLOOKUP($E24,'Table of Hazards (AI only)'!$B$6:$P$129,9,)) -> 13 | M24: =IF(ISBLANK($E24),0,VLOOKUP($E24,'Table of Hazards (AI only)'!$B$6:$P$129,11,)) -> 53.333333 | O24: =IF(ISBLANK($E24),0,VLOOKUP($E24,'Table of Hazards (AI only)'!$B$6:$P$129,12,)) -> 0.3037476 | P24: =IF(ISBLANK($G24),0,VLOOKUP($G24,'Table of Hazards (AI only)'!$B$6:$P$129,8,)) -> 0 | R24: =IF(ISBLANK($G24),0,VLOOKUP($G24,'Table of Hazards (AI only)'!$B$6:$P$129,9,)) -> 0 | S24: =IF(ISBLANK($G24),0,VLOOKUP($G24,'Table of Hazards (AI only)'!$B$6:$P$129,11,)) -> 0 | U24: =IF(ISBLANK($G24),0,VLOOKUP($G24,'Table of Hazards (AI only)'!$B$6:$P$129,12,)) -> 0 | V24: =(($F24*J24)+($H24*P24))*$I24 -> 22.6625 | X24: =(($F24*L24)+($H24*R24))*$I24 -> 7.9625 | Y24: =(($F24*M24)+($H24*S24))*$I24 -> 32.666667 | AA24: =(($F24*O24)+($H24*U24))*$I24 -> 0.1860454 | AC24: Ossiclor 35 wg
B25: Grapes | C25: Downy Mildew | D25: Dimethomorph + Mancozeb | E25: Dimethomorph | F25: 0.09 | G25: Mancozeb | H25: 0.6 | I25: 2.1 | J25: =IF(ISBLANK($E25),0,VLOOKUP($E25,'Table of Hazards (AI only)'!$B$6:$P$129,8,)) -> 27 | L25: =IF(ISBLANK($E25),0,VLOOKUP($E25,'Table of Hazards (AI only)'!$B$6:$P$129,9,)) -> 15 | M25: =IF(ISBLANK($E25),0,VLOOKUP($E25,'Table of Hazards (AI only)'!$B$6:$P$129,11,)) -> 16.666667 | O25: =IF(ISBLANK($E25),0,VLOOKUP($E25,'Table of Hazards (AI only)'!$B$6:$P$129,12,)) -> 0.3037476 | P25: =IF(ISBLANK($G25),0,VLOOKUP($G25,'Table of Hazards (AI only)'!$B$6:$P$129,8,)) -> 29 | R25: =IF(ISBLANK($G25),0,VLOOKUP($G25,'Table of Hazards (AI only)'!$B$6:$P$129,9,)) -> 5 | S25: =IF(ISBLANK($G25),0,VLOOKUP($G25,'Table of Hazards (AI only)'!$B$6:$P$129,11,)) -> 15 | U25: =IF(ISBLANK($G25),0,VLOOKUP($G25,'Table of Hazards (AI only)'!$B$6:$P$129,12,)) -> 0.3037476 | V25: =(($F25*J25)+($H25*P25))*$I25 -> 41.643 | X25: =(($F25*L25)+($H25*R25))*$I25 -> 9.135 | Y25: =(($F25*M25)+($H25*S25))*$I25 -> 22.05 | AA25: =(($F25*O25)+($H25*U25))*$I25 -> 0.44013027 | AC25: Forum MZ WG
B26: Grapes | C26: Downy Mildew | D26: Dithianon | E26: Dithianon | F26: 0.7 | I26: 1.1 | J26: =IF(ISBLANK($E26),0,VLOOKUP($E26,'Table of Hazards (AI only)'!$B$6:$P$129,8,)) -> 37 | L26: =IF(ISBLANK($E26),0,VLOOKUP($E26,'Table of Hazards (AI only)'!$B$6:$P$129,9,)) -> 19 | M26: =IF(ISBLANK($E26),0,VLOOKUP($E26,'Table of Hazards (AI only)'!$B$6:$P$129,11,)) -> 22.666667 | O26: =IF(ISBLANK($E26),0,VLOOKUP($E26,'Table of Hazards (AI only)'!$B$6:$P$129,12,)) -> 0.3037476 | P26: =IF(ISBLANK($G26),0,VLOOKUP($G26,'Table of Hazards (AI only)'!$B$6:$P$129,8,)) -> 0 | R26: =IF(ISBLANK($G26),0,VLOOKUP($G26,'Table of Hazards (AI only)'!$B$6:$P$129,9,)) -> 0 | S26: =IF(ISBLANK($G26),0,VLOOKUP($G26,'Table of Hazards (AI only)'!$B$6:$P$129,11,)) -> 0 | U26: =IF(ISBLANK($G26),0,VLOOKUP($G26,'Table of Hazards (AI only)'!$B$6:$P$129,12,)) -> 0 | V26: =(($F26*J26)+($H26*P26))*$I26 -> 28.49 | X26: =(($F26*L26)+($H26*R26))*$I26 -> 14.63 | Y26: =(($F26*M26)+($H26*S26))*$I26 -> 17.453333 | AA26: =(($F26*O26)+($H26*U26))*$I26 -> 0.23388565 | AC26: Delan 70 wg
B27: Grapes | C27: Downy Mildew | D27: Famoxadone + Cymoxanil | E27: Famoxadone | F27: 0.225 | G27: Cymoxanil | H27: 0.3 | I27: 0.4 | J27: =IF(ISBLANK($E27),0,VLOOKUP($E27,'Table of Hazards (AI only)'!$B$6:$P$129,8,)) -> 21 | L27: =IF(ISBLANK($E27),0,VLOOKUP($E27,'Table of Hazards (AI only)'!$B$6:$P$129,9,)) -> 6 | M27: =IF(ISBLANK($E27),0,VLOOKUP($E27,'Table of Hazards (AI only)'!$B$6:$P$129,11,)) -> 15.333333 | O27: =IF(ISBLANK($E27),0,VLOOKUP($E27,'Table of Hazards (AI only)'!$B$6:$P$129,12,)) -> 0.3037476 | P27: =IF(ISBLANK($G27),0,VLOOKUP($G27,'Table of Hazards (AI only)'!$B$6:$P$129,8,)) -> 25.5 | R27: =IF(ISBLANK($G27),0,VLOOKUP($G27,'Table of Hazards (AI only)'!$B$6:$P$129,9,)) -> 4.5 | S27: =IF(ISBLANK($G27),0,VLOOKUP($G27,'Table of Hazards (AI only)'!$B$6:$P$129,11,)) -> 17.166667 | U27: =IF(ISBLANK($G27),0,VLOOKUP($G27,'Table of Hazards (AI only)'!$B$6:$P$129,12,)) -> 0.3037476 | V27: =(($F27*J27)+($H27*P27))*$I27 -> 4.95 | X27: =(($F27*L27)+($H27*R27))*$I27 -> 1.08 | Y27: =(($F27*M27)+($H27*S27))*$I27 -> 3.44 | AA27: =(($F27*O27)+($H27*U27))*$I27 -> 0.063786995 | AC27: Equation Pro
B28: Grapes | C28: Downy Mildew | D28: Fenamidone + Fosetyl-Aluminium | E28: Fenamidone | F28: 0.04 | G28: Fosetyl-Aluminium | H28: 0.667 | I28: 2.75 | J28: =IF(ISBLANK($E28),0,VLOOKUP($E28,'Table of Hazards (AI only)'!$B$6:$P$129,8,)) -> 18.5 | L28: =IF(ISBLANK($E28),0,VLOOKUP($E28,'Table of Hazards (AI only)'!$B$6:$P$129,9,)) -> 3.5 | M28: =IF(ISBLANK($E28),0,VLOOKUP($E28,'Table of Hazards (AI only)'!$B$6:$P$129,11,)) -> 18.166667 | O28: =IF(ISBLANK($E28),0,VLOOKUP($E28,'Table of Hazards (AI only)'!$B$6:$P$129,12,)) -> 0.3037476 | P28: =IF(ISBLANK($G28),0,VLOOKUP($G28,'Table of Hazards (AI only)'!$B$6:$P$129,8,)) -> 14.5 | R28: =IF(ISBLANK($G28),0,VLOOKUP($G28,'Table of Hazards (AI only)'!$B$6:$P$129,9,)) -> 5.5 | S28: =IF(ISBLANK($G28),0,VLOOKUP($G28,'Table of Hazards (AI only)'!$B$6:$P$129,11,)) -> 10.166667 | U28: =IF(ISBLANK($G28),0,VLOOKUP($G28,'Table of Hazards (AI only)'!$B$6:$P$129,12,)) -> 0.3037476 | V28: =(($F28*J28)+($H28*P28))*$I28 -> 28.631625 | X28: =(($F28*L28)+($H28*R28))*$I28 -> 10.473375 | Y28: =(($F28*M28)+($H28*S28))*$I28 -> 20.646542 | AA28: =(($F28*O28)+($H28*U28))*$I28 -> 0.59056126 | AC28: Elicio
B29: Grapes | C29: Downy Mildew | D29: Fluazinam | E29: Fluazinam | F29: 0.5 | I29: 1.5 | J29: =IF(ISBLANK($E29),0,VLOOKUP($E29,'Table of Hazards (AI only)'!$B$6:$P$129,8,)) -> 22 | L29: =IF(ISBLANK($E29),0,VLOOKUP($E29,'Table of Hazards (AI only)'!$B$6:$P$129,9,)) -> 4 | M29: =IF(ISBLANK($E29),0,VLOOKUP($E29,'Table of Hazards (AI only)'!$B$6:$P$129,11,)) -> 14.666667 | O29: =IF(ISBLANK($E29),0,VLOOKUP($E29,'Table of Hazards (AI only)'!$B$6:$P$129,12,)) -> 0.3037476 | P29: =IF(ISBLANK($G29),0,VLOOKUP($G29,'Table of Hazards (AI only)'!$B$6:$P$129,8,)) -> 0 | R29: =IF(ISBLANK($G29),0,VLOOKUP($G29,'Table of Hazards (AI only)'!$B$6:$P$129,9,)) -> 0 | S29: =IF(ISBLANK($G29),0,VLOOKUP($G29,'Table of Hazards (AI only)'!$B$6:$P$129,11,)) -> 0 | U29: =IF(ISBLANK($G29),0,VLOOKUP($G29,'Table of Hazards (AI only)'!$B$6:$P$129,12,)) -> 0 | V29: =(($F29*J29)+($H29*P29))*$I29 -> 16.5 | X29: =(($F29*L29)+($H29*R29))*$I29 -> 3 | Y29: =(($F29*M29)+($H29*S29))*$I29 -> 11 | AA29: =(($F29*O29)+($H29*U29))*$I29 -> 0.2278107 | AC29: Banjo
B30: Grapes | C30: Downy Mildew | D30: Fluopicolide + Fosetyl-Aluminium | E30: Fluopicolide | F30: 0.044 | G30: Fosetyl-Aluminium | H30: 0.667 | I30: 2.63 | J30: =IF(ISBLANK($E30),0,VLOOKUP($E30,'Table of Hazards (AI only)'!$B$6:$P$129,8,)) -> 18.5 | L30: =IF(ISBLANK($E30),0,VLOOKUP($E30,'Table of Hazards (AI only)'!$B$6:$P$129,9,)) -> 9.5 | M30: =IF(ISBLANK($E30),0,VLOOKUP($E30,'Table of Hazards (AI only)'!$B$6:$P$129,11,)) -> 14.833333 | O30: =IF(ISBLANK($E30),0,VLOOKUP($E30,'Table of Hazards (AI only)'!$B$6:$P$129,12,)) -> 0.3037476 | P30: =IF(ISBLANK($G30),0,VLOOKUP($G30,'Table of Hazards (AI only)'!$B$6:$P$129,8,)) -> 14.5 | R30: =IF(ISBLANK($G30),0,VLOOKUP($G30,'Table of Hazards (AI only)'!$B$6:$P$129,9,)) -> 5.5 | S30: =IF(ISBLANK($G30),0,VLOOKUP($G30,'Table of Hazards (AI only)'!$B$6:$P$129,11,)) -> 10.166667 | U30: =IF(ISBLANK($G30),0,VLOOKUP($G30,'Table of Hazards (AI only)'!$B$6:$P$129,12,)) -> 0.3037476 | V30: =(($F30*J30)+($H30*P30))*$I30 -> 27.576865 | X30: =(($F30*L30)+($H30*R30))*$I30 -> 10.747495 | Y30: =(($F30*M30)+($H30*S30))*$I30 -> 19.550982 | AA30: =(($F30*O30)+($H30*U30))*$I30 -> 0.56798674 | AC30: R6
B31: Grapes | C31: Downy Mildew | D31: Folpet | E31: Folpet | F31: 0.8 | I31: 1.38 | J31: =IF(ISBLANK($E31),0,VLOOKUP($E31,'Table of Hazards (AI only)'!$B$6:$P$129,8,)) -> 28 | L31: =IF(ISBLANK($E31),0,VLOOKUP($E31,'Table of Hazards (AI only)'!$B$6:$P$129,9,)) -> 10 | M31: =IF(ISBLANK($E31),0,VLOOKUP($E31,'Table of Hazards (AI only)'!$B$6:$P$129,11,)) -> 16 | O31: =IF(ISBLANK($E31),0,VLOOKUP($E31,'Table of Hazards (AI only)'!$B$6:$P$129,12,)) -> 0.3037476 | P31: =IF(ISBLANK($G31),0,VLOOKUP($G31,'Table of Hazards (AI only)'!$B$6:$P$129,8,)) -> 0 | R31: =IF(ISBLANK($G31),0,VLOOKUP($G31,'Table of Hazards (AI only)'!$B$6:$P$129,9,)) -> 0 | S31: =IF(ISBLANK($G31),0,VLOOKUP($G31,'Table of Hazards (AI only)'!$B$6:$P$129,11,)) -> 0 | U31: =IF(ISBLANK($G31),0,VLOOKUP($G31,'Table of Hazards (AI only)'!$B$6:$P$129,12,)) -> 0 | V31: =(($F31*J31)+($H31*P31))*$I31 -> 30.912 | X31: =(($F31*L31)+($H31*R31))*$I31 -> 11.04 | Y31: =(($F31*M31)+($H31*S31))*$I31 -> 17.664 | AA31: =(($F31*O31)+($H31*U31))*$I31 -> 0.33533735 | AC31: Folpan 80 wg
B32: Grapes | C32: Downy Mildew | D32: Iprovalicarb + Copper oxychloride | E32: Iprovalicarb | F32: 0.084 | G32: Copper oxychloride | H32: 0.406 | I32: 1.75 | J32: =IF(ISBLANK($E32),0,VLOOKUP($E32,'Table of Hazards (AI only)'!$B$6:$P$129,8,)) -> 38 | L32: =IF(ISBLANK($E32),0,VLOOKUP($E32,'Table of Hazards (AI only)'!$B$6:$P$129,9,)) -> 18 | M32: =IF(ISBLANK($E32),0,VLOOKUP($E32,'Table of Hazards (AI only)'!$B$6:$P$129,11,)) -> 25.666667 | O32: =IF(ISBLANK($E32),0,VLOOKUP($E32,'Table of Hazards (AI only)'!$B$6:$P$129,12,)) -> 0.3037476 | P32: =IF(ISBLANK($G32),0,VLOOKUP($G32,'Table of Hazards (AI only)'!$B$6:$P$129,8,)) -> 37 | R32: =IF(ISBLANK($G32),0,VLOOKUP($G32,'Table of Hazards (AI only)'!$B$6:$P$129,9,)) -> 13 | S32: =IF(ISBLANK($G32),0,VLOOKUP($G32,'Table of Hazards (AI only)'!$B$6:$P$129,11,)) -> 53.333333 | U32: =IF(ISBLANK($G32),0,VLOOKUP($G32,'Table of Hazards (AI only)'!$B$6:$P$129,12,)) -> 0.3037476 | V32: =(($F32*J32)+($H32*P32))*$I32 -> 31.8745 | X32: =(($F32*L32)+($H32*R32))*$I32 -> 11.8825 | Y32: =(($F32*M32)+($H32*S32))*$I32 -> 41.666333 | AA32: =(($F32*O32)+($H32*U32))*$I32 -> 0.26046356 | AC32: Melody Compact WG
B33: Grapes | C33: Downy Mildew | D33: Mancozeb | E33: Mancozeb | F33: 0.8 | I33: 2 | J33: =IF(ISBLANK($E33),0,VLOOKUP($E33,'Table of Hazards (AI only)'!$B$6:$P$129,8,)) -> 29 | L33: =IF(ISBLANK($E33),0,VLOOKUP($E33,'Table of Hazards (AI only)'!$B$6:$P$129,9,)) -> 5 | M33: =IF(ISBLANK($E33),0,VLOOKUP($E33,'Table of Hazards (AI only)'!$B$6:$P$129,11,)) -> 15 | O33: =IF(ISBLANK($E33),0,VLOOKUP($E33,'Table of Hazards (AI only)'!$B$6:$P$129,12,)) -> 0.3037476 | P33: =IF(ISBLANK($G33),0,VLOOKUP($G33,'Table of Hazards (AI only)'!$B$6:$P$129,8,)) -> 0 | R33: =IF(ISBLANK($G33),0,VLOOKUP($G33,'Table of Hazards (AI only)'!$B$6:$P$129,9,)) -> 0 | S33: =IF(ISBLANK($G33),0,VLOOKUP($G33,'Table of Hazards (AI only)'!$B$6:$P$129,11,)) -> 0 | U33: =IF(ISBLANK($G33),0,VLOOKUP($G33,'Table of Hazards (AI only)'!$B$6:$P$129,12,)) -> 0 | V33: =(($F33*J33)+($H33*P33))*$I33 -> 46.4 | X33: =(($F33*L33)+($H33*R33))*$I33 -> 8 | Y33: =(($F33*M33)+($H33*S33))*$I33 -> 24 | AA33: =(($F33*O33)+($H33*U33))*$I33 -> 0.48599615 | AC33: Mancozeb plus 80 WP
B34: Grapes | C34: Downy Mildew | D34: Mandipropamid | E34: Mandipropamid | F34: 0.25 | I34: 0.55 | J34: =IF(ISBLANK($E34),0,VLOOKUP($E34,'Table of Hazards (AI only)'!$B$6:$P$129,8,)) -> 10 | L34: =IF(ISBLANK($E34),0,VLOOKUP($E34,'Table of Hazards (AI only)'!$B$6:$P$129,9,)) -> 4 | M34: =IF(ISBLANK($E34),0,VLOOKUP($E34,'Table of Hazards (AI only)'!$B$6:$P$129,11,)) -> 10 | O34: =IF(ISBLANK($E34),0,VLOOKUP($E34,'Table of Hazards (AI only)'!$B$6:$P$129,12,)) -> 0.3037476 | P34: =IF(ISBLANK($G34),0,VLOOKUP($G34,'Table of Hazards (AI only)'!$B$6:$P$129,8,)) -> 0 | R34: =IF(ISBLANK($G34),0,VLOOKUP($G34,'Table of Hazards (AI only)'!$B$6:$P$129,9,)) -> 0 | S34: =IF(ISBLANK($G34),0,VLOOKUP($G34,'Table of Hazards (AI only)'!$B$6:$P$129,11,)) -> 0 | U34: =IF(ISBLANK($G34),0,VLOOKUP($G34,'Table of Hazards (AI only)'!$B$6:$P$129,12,)) -> 0 | V34: =(($F34*J34)+($H34*P34))*$I34 -> 1.375 | X34: =(($F34*L34)+($H34*R34))*$I34 -> 0.55 | Y34: =(($F34*M34)+($H34*S34))*$I34 -> 1.375 | AA34: =(($F34*O34)+($H34*U34))*$I34 -> 0.041765295 | AC34: Pergado SC
B35: Grapes | C35: Downy Mildew | D35: Metalaxyl + Mancozeb | E35: Metalaxyl | F35: 0.039 | G35: Mancozeb | H35: 0.64 | I35: 2.5 | J35: =IF(ISBLANK($E35),0,VLOOKUP($E35,'Table of Hazards (AI only)'!$B$6:$P$129,8,)) -> 20 | L35: =IF(ISBLANK($E35),0,VLOOKUP($E35,'Table of Hazards (AI only)'!$B$6:$P$129,9,)) -> 12 | M35: =IF(ISBLANK($E35),0,VLOOKUP($E35,'Table of Hazards (AI only)'!$B$6:$P$129,11,)) -> 36.666667 | O35: =IF(ISBLANK($E35),0,VLOOKUP($E35,'Table of Hazards (AI only)'!$B$6:$P$129,12,)) -> 0.3037476 | P35: =IF(ISBLANK($G35),0,VLOOKUP($G35,'Table of Hazards (AI only)'!$B$6:$P$129,8,)) -> 29 | R35: =IF(ISBLANK($G35),0,VLOOKUP($G35,'Table of Hazards (AI only)'!$B$6:$P$129,9,)) -> 5 | S35: =IF(ISBLANK($G35),0,VLOOKUP($G35,'Table of Hazards (AI only)'!$B$6:$P$129,11,)) -> 15 | U35: =IF(ISBLANK($G35),0,VLOOKUP($G35,'Table of Hazards (AI only)'!$B$6:$P$129,12,)) -> 0.3037476 | V35: =(($F35*J35)+($H35*P35))*$I35 -> 48.35 | X35: =(($F35*L35)+($H35*R35))*$I35 -> 9.17 | Y35: =(($F35*M35)+($H35*S35))*$I35 -> 27.575 | AA35: =(($F35*O35)+($H35*U35))*$I35 -> 0.51561155 | AC35: Ridomil Gold
B36: Grapes | C36: Downy Mildew | D36: Metalaxyl + Copper II hydroxide | E36: Metalaxyl | F36: 0.035 | G36: Copper II hydroxide | H36: 0.185 | I36: 2 | J36: =IF(ISBLANK($E36),0,VLOOKUP($E36,'Table of Hazards (AI only)'!$B$6:$P$129,8,)) -> 20 | L36: =IF(ISBLANK($E36),0,VLOOKUP($E36,'Table of Hazards (AI only)'!$B$6:$P$129,9,)) -> 12 | M36: =IF(ISBLANK($E36),0,VLOOKUP($E36,'Table of Hazards (AI only)'!$B$6:$P$129,11,)) -> 36.666667 | O36: =IF(ISBLANK($E36),0,VLOOKUP($E36,'Table of Hazards (AI only)'!$B$6:$P$129,12,)) -> 0.3037476 | P36: =IF(ISBLANK($G36),0,VLOOKUP($G36,'Table of Hazards (AI only)'!$B$6:$P$129,8,)) -> 88.5 | R36: =IF(ISBLANK($G36),0,VLOOKUP($G36,'Table of Hazards (AI only)'!$B$6:$P$129,9,)) -> 53.5 | S36: =IF(ISBLANK($G36),0,VLOOKUP($G36,'Table of Hazards (AI only)'!$B$6:$P$129,11,)) -> 86.166667 | U36: =IF(ISBLANK($G36),0,VLOOKUP($G36,'Table of Hazards (AI only)'!$B$6:$P$129,12,)) -> 0.35170774 | V36: =(($F36*J36)+($H36*P36))*$I36 -> 34.145 | X36: =(($F36*L36)+($H36*R36))*$I36 -> 20.635 | Y36: =(($F36*M36)+($H36*S36))*$I36 -> 34.448333 | AA36: =(($F36*O36)+($H36*U36))*$I36 -> 0.1513942 | AC36: Mevaxil Cobre
B37: Grapes | C37: Downy Mildew | D37: Metiram | E37: Metiram | F37: 0.7 | I37: 1.5 | J37: =IF(ISBLANK($E37),0,VLOOKUP($E37,'Table of Hazards (AI only)'!$B$6:$P$129,8,)) -> 18.5 | L37: =IF(ISBLANK($E37),0,VLOOKUP($E37,'Table of Hazards (AI only)'!$B$6:$P$129,9,)) -> 3.5 | M37: =IF(ISBLANK($E37),0,VLOOKUP($E37,'Table of Hazards (AI only)'!$B$6:$P$129,11,)) -> 12.833333 | O37: =IF(ISBLANK($E37),0,VLOOKUP($E37,'Table of Hazards (AI only)'!$B$6:$P$129,12,)) -> 0.3037476 | P37: =IF(ISBLANK($G37),0,VLOOKUP($G37,'Table of Hazards (AI only)'!$B$6:$P$129,8,)) -> 0 | R37: =IF(ISBLANK($G37),0,VLOOKUP($G37,'Table of Hazards (AI only)'!$B$6:$P$129,9,)) -> 0 | S37: =IF(ISBLANK($G37),0,VLOOKUP($G37,'Table of Hazards (AI only)'!$B$6:$P$129,11,)) -> 0 | U37: =IF(ISBLANK($G37),0,VLOOKUP($G37,'Table of Hazards (AI only)'!$B$6:$P$129,12,)) -> 0 | V37: =(($F37*J37)+($H37*P37))*$I37 -> 19.425 | X37: =(($F37*L37)+($H37*R37))*$I37 -> 3.675 | Y37: =(($F37*M37)+($H37*S37))*$I37 -> 13.475 | AA37: =(($F37*O37)+($H37*U37))*$I37 -> 0.31893498 | AC37: Polyram
B38: Grapes | C38: Downy Mildew | D38: Potassium phosphonates | E38: Potassium phosphonates | F38: 0.517 | I38: 2 | J38: =IF(ISBLANK($E38),0,VLOOKUP($E38,'Table of Hazards (AI only)'!$B$6:$P$129,8,)) -> 20 | L38: =IF(ISBLANK($E38),0,VLOOKUP($E38,'Table of Hazards (AI only)'!$B$6:$P$129,9,)) -> 10 | M38: =IF(ISBLANK($E38),0,VLOOKUP($E38,'Table of Hazards (AI only)'!$B$6:$P$129,11,)) -> 26 | O38: =IF(ISBLANK($E38),0,VLOOKUP($E38,'Table of Hazards (AI only)'!$B$6:$P$129,12,)) -> 0.3037476 | P38: =IF(ISBLANK($G38),0,VLOOKUP($G38,'Table of Hazards (AI only)'!$B$6:$P$129,8,)) -> 0 | R38: =IF(ISBLANK($G38),0,VLOOKUP($G38,'Table of Hazards (AI only)'!$B$6:$P$129,9,)) -> 0 | S38: =IF(ISBLANK($G38),0,VLOOKUP($G38,'Table of Hazards (AI only)'!$B$6:$P$129,11,)) -> 0 | U38: =IF(ISBLANK($G38),0,VLOOKUP($G38,'Table of Hazards (AI only)'!$B$6:$P$129,12,)) -> 0 | V38: =(($F38*J38)+($H38*P38))*$I38 -> 20.68 | X38: =(($F38*L38)+($H38*R38))*$I38 -> 10.34 | Y38: =(($F38*M38)+($H38*S38))*$I38 -> 26.884 | AA38: =(($F38*O38)+($H38*U38))*$I38 -> 0.31407502 | AC38: Century SL
B39: Grapes | C39: Downy Mildew | D39: Propineb | E39: Propineb | F39: 0.7 | I39: 1.75 | J39: =IF(ISBLANK($E39),0,VLOOKUP($E39,'Table of Hazards (AI only)'!$B$6:$P$129,8,)) -> 28 | L39: =IF(ISBLANK($E39),0,VLOOKUP($E39,'Table of Hazards (AI only)'!$B$6:$P$129,9,)) -> 10 | M39: =IF(ISBLANK($E39),0,VLOOKUP($E39,'Table of Hazards (AI only)'!$B$6:$P$129,11,)) -> 24.666667 | O39: =IF(ISBLANK($E39),0,VLOOKUP($E39,'Table of Hazards (AI only)'!$B$6:$P$129,12,)) -> 0.3037476 | P39: =IF(ISBLANK($G39),0,VLOOKUP($G39,'Table of Hazards (AI only)'!$B$6:$P$129,8,)) -> 0 | R39: =IF(ISBLANK($G39),0,VLOOKUP($G39,'Table of Hazards (AI only)'!$B$6:$P$129,9,)) -> 0 | S39: =IF(ISBLANK($G39),0,VLOOKUP($G39,'Table of Hazards (AI only)'!$B$6:$P$129,11,)) -> 0 | U39: =IF(ISBLANK($G39),0,VLOOKUP($G39,'Table of Hazards (AI only)'!$B$6:$P$129,12,)) -> 0 | V39: =(($F39*J39)+($H39*P39))*$I39 -> 34.3 | X39: =(($F39*L39)+($H39*R39))*$I39 -> 12.25 | Y39: =(($F39*M39)+($H39*S39))*$I39 -> 30.216667 | AA39: =(($F39*O39)+($H39*U39))*$I39 -> 0.37209081 | AC39: Antracol 70 WG
B40: Grapes | C40: Downy Mildew | D40: Pyraclostrobin + Metiram | E40: Pyraclostrobin | F40: 0.05 | G40: Metiram | H40: 0.55 | I40: 1.5 | J40: =IF(ISBLANK($E40),0,VLOOKUP($E40,'Table of Hazards (AI only)'!$B$6:$P$129,8,)) -> 21 | L40: =IF(ISBLANK($E40),0,VLOOKUP($E40,'Table of Hazards (AI only)'!$B$6:$P$129,9,)) -> 6 | M40: =IF(ISBLANK($E40),0,VLOOKUP($E40,'Table of Hazards (AI only)'!$B$6:$P$129,11,)) -> 13.333333 | O40: =IF(ISBLANK($E40),0,VLOOKUP($E40,'Table of Hazards (AI only)'!$B$6:$P$129,12,)) -> 0.3037476 | P40: =IF(ISBLANK($G40),0,VLOOKUP($G40,'Table of Hazards (AI only)'!$B$6:$P$129,8,)) -> 18.5 | R40: =IF(ISBLANK($G40),0,VLOOKUP($G40,'Table of Hazards (AI only)'!$B$6:$P$129,9,)) -> 3.5 | S40: =IF(ISBLANK($G40),0,VLOOKUP($G40,'Table of Hazards (AI only)'!$B$6:$P$129,11,)) -> 12.833333 | U40: =IF(ISBLANK($G40),0,VLOOKUP($G40,'Table of Hazards (AI only)'!$B$6:$P$129,12,)) -> 0.3037476 | V40: =(($F40*J40)+($H40*P40))*$I40 -> 16.8375 | X40: =(($F40*L40)+($H40*R40))*$I40 -> 3.3375 | Y40: =(($F40*M40)+($H40*S40))*$I40 -> 11.5875 | AA40: =(($F40*O40)+($H40*U40))*$I40 -> 0.27337284 | AC40: Cabrio top
B41: Grapes | C41: Downy Mildew | D41: Valifenalate + Mancozeb | E41: Valifenalate | F41: 0.06 | G41: Mancozeb | H41: 0.66 | I41: 2 | J41: =IF(ISBLANK($E41),0,VLOOKUP($E41,'Table of Hazards (AI only)'!$B$6:$P$129,8,)) -> 32.5 | L41: =IF(ISBLANK($E41),0,VLOOKUP($E41,'Table of Hazards (AI only)'!$B$6:$P$129,9,)) -> 11.5 | M41: =IF(ISBLANK($E41),0,VLOOKUP($E41,'Table of Hazards (AI only)'!$B$6:$P$129,11,)) -> 14.833333 | O41: =IF(ISBLANK($E41),0,VLOOKUP($E41,'Table of Hazards (AI only)'!$B$6:$P$129,12,)) -> 0.3037476 | P41: =IF(ISBLANK($G41),0,VLOOKUP($G41,'Table of Hazards (AI only)'!$B$6:$P$129,8,)) -> 29 | R41: =IF(ISBLANK($G41),0,VLOOKUP($G41,'Table of Hazards (AI only)'!$B$6:$P$129,9,)) -> 5 | S41: =IF(ISBLANK($G41),0,VLOOKUP($G41,'Table of Hazards (AI only)'!$B$6:$P$129,11,)) -> 15 | U41: =IF(ISBLANK($G41),0,VLOOKUP($G41,'Table of Hazards (AI only)'!$B$6:$P$129,12,)) -> 0.3037476 | V41: =(($F41*J41)+($H41*P41))*$I41 -> 42.18 | X41: =(($F41*L41)+($H41*R41))*$I41 -> 7.98 | Y41: =(($F41*M41)+($H41*S41))*$I41 -> 21.58 | AA41: =(($F41*O41)+($H41*U41))*$I41 -> 0.43739654 | AC41: Valis
B42: Grapes | C42: Downy Mildew | D42: Zoxamide | E42: Zoxamide | F42: 0.24 | I42: 0.6875 | J42: =IF(ISBLANK($E42),0,VLOOKUP($E42,'Table of Hazards (AI only)'!$B$6:$P$129,8,)) -> 10 | L42: =IF(ISBLANK($E42),0,VLOOKUP($E42,'Table of Hazards (AI only)'!$B$6:$P$129,9,)) -> 4 | M42: =IF(ISBLANK($E42),0,VLOOKUP($E42,'Table of Hazards (AI only)'!$B$6:$P$129,11,)) -> 8 | O42: =IF(ISBLANK($E42),0,VLOOKUP($E42,'Table of Hazards (AI only)'!$B$6:$P$129,12,)) -> 0.3037476 | P42: =IF(ISBLANK($G42),0,VLOOKUP($G42,'Table of Hazards (AI only)'!$B$6:$P$129,8,)) -> 0 | R42: =IF(ISBLANK($G42),0,VLOOKUP($G42,'Table of Hazards (AI only)'!$B$6:$P$129,9,)) -> 0 | S42: =IF(ISBLANK($G42),0,VLOOKUP($G42,'Table of Hazards (AI only)'!$B$6:$P$129,11,)) -> 0 | U42: =IF(ISBLANK($G42),0,VLOOKUP($G42,'Table of Hazards (AI only)'!$B$6:$P$129,12,)) -> 0 | V42: =(($F42*J42)+($H42*P42))*$I42 -> 1.65 | X42: =(($F42*L42)+($H42*R42))*$I42 -> 0.66 | Y42: =(($F42*M42)+($H42*S42))*$I42 -> 1.32 | AA42: =(($F42*O42)+($H42*U42))*$I42 -> 0.050118353 | AC42: Zoxium
B43: Grapes | C43: Downy Mildew | D43: Dimethomorph + Copper oxychloride | E43: Dimethomorph | F43: 0.06 | G43: Copper oxychloride | H43: 0.24 | I43: 3.5 | J43: =IF(ISBLANK($E43),0,VLOOKUP($E43,'Table of Hazards (AI only)'!$B$6:$P$129,8,)) -> 27 | L43: =IF(ISBLANK($E43),0,VLOOKUP($E43,'Table of Hazards (AI only)'!$B$6:$P$129,9,)) -> 15 | M43: =IF(ISBLANK($E43),0,VLOOKUP($E43,'Table of Hazards (AI only)'!$B$6:$P$129,11,)) -> 16.666667 | O43: =IF(ISBLANK($E43),0,VLOOKUP($E43,'Table of Hazards (AI only)'!$B$6:$P$129,12,)) -> 0.3037476 | P43: =IF(ISBLANK($G43),0,VLOOKUP($G43,'Table of Hazards (AI only)'!$B$6:$P$129,8,)) -> 37 | R43: =IF(ISBLANK($G43),0,VLOOKUP($G43,'Table of Hazards (AI only)'!$B$6:$P$129,9,)) -> 13 | S43: =IF(ISBLANK($G43),0,VLOOKUP($G43,'Table of Hazards (AI only)'!$B$6:$P$129,11,)) -> 53.333333 | U43: =IF(ISBLANK($G43),0,VLOOKUP($G43,'Table of Hazards (AI only)'!$B$6:$P$129,12,)) -> 0.3037476 | V43: =(($F43*J43)+($H43*P43))*$I43 -> 36.75 | X43: =(($F43*L43)+($H43*R43))*$I43 -> 14.07 | Y43: =(($F43*M43)+($H43*S43))*$I43 -> 48.3 | AA43: =(($F43*O43)+($H43*U43))*$I43 -> 0.31893498 | AC43: Forum R 3B
B44: Grapes | C44: Grey Mould | D44: Boscalid | E44: Boscalid | F44: 0.5 | I44: 1.1 | J44: =IF(ISBLANK($E44),0,VLOOKUP($E44,'Table of Hazards (AI only)'!$B$6:$P$129,8,)) -> 48 | L44: =IF(ISBLANK($E44),0,VLOOKUP($E44,'Table of Hazards (AI only)'!$B$6:$P$129,9,)) -> 30 | M44: =IF(ISBLANK($E44),0,VLOOKUP($E44,'Table of Hazards (AI only)'!$B$6:$P$129,11,)) -> 22.666667 | O44: =IF(ISBLANK($E44),0,VLOOKUP($E44,'Table of Hazards (AI only)'!$B$6:$P$129,12,)) -> 0.3037476 | P44: =IF(ISBLANK($G44),0,VLOOKUP($G44,'Table of Hazards (AI only)'!$B$6:$P$129,8,)) -> 0 | R44: =IF(ISBLANK($G44),0,VLOOKUP($G44,'Table of Hazards (AI only)'!$B$6:$P$129,9,)) -> 0 | S44: =IF(ISBLANK($G44),0,VLOOKUP($G44,'Table of Hazards (AI only)'!$B$6:$P$129,11,)) -> 0 | U44: =IF(ISBLANK($G44),0,VLOOKUP($G44,'Table of Hazards (AI only)'!$B$6:$P$129,12,)) -> 0 | V44: =(($F44*J44)+($H44*P44))*$I44 -> 26.4 | X44: =(($F44*L44)+($H44*R44))*$I44 -> 16.5 | Y44: =(($F44*M44)+($H44*S44))*$I44 -> 12.466667 | AA44: =(($F44*O44)+($H44*U44))*$I44 -> 0.16706118 | AC44: Cantus
B45: Grapes | C45: Grey Mould | D45: Cyprodinil + Fludioxonil | E45: Cyprodinil | F45: 0.375 | G45: Fludioxonil | H45: 0.25 | I45: 0.8 | J45: =IF(ISBLANK($E45),0,VLOOKUP($E45,'Table of Hazards (AI only)'!$B$6:$P$129,8,)) -> 25 | L45: =IF(ISBLANK($E45),0,VLOOKUP($E45,'Table of Hazards (AI only)'!$B$6:$P$129,9,)) -> 13 | M45: =IF(ISBLANK($E45),0,VLOOKUP($E45,'Table of Hazards (AI only)'!$B$6:$P$129,11,)) -> 18 | O45: =IF(ISBLANK($E45),0,VLOOKUP($E45,'Table of Hazards (AI only)'!$B$6:$P$129,12,)) -> 0.3037476 | P45: =IF(ISBLANK($G45),0,VLOOKUP($G45,'Table of Hazards (AI only)'!$B$6:$P$129,8,)) -> 22 | R45: =IF(ISBLANK($G45),0,VLOOKUP($G45,'Table of Hazards (AI only)'!$B$6:$P$129,9,)) -> 4 | S45: =IF(ISBLANK($G45),0,VLOOKUP($G45,'Table of Hazards (AI only)'!$B$6:$P$129,11,)) -> 12 | U45: =IF(ISBLANK($G45),0,VLOOKUP($G45,'Table of Hazards (AI only)'!$B$6:$P$129,12,)) -> 0.3037476 | V45: =(($F45*J45)+($H45*P45))*$I45 -> 11.9 | X45: =(($F45*L45)+($H45*R45))*$I45 -> 4.7 | Y45: =(($F45*M45)+($H45*S45))*$I45 -> 7.8 | AA45: =(($F45*O45)+($H45*U45))*$I45 -> 0.1518738 | AC45: Switch
B46: Grapes | C46: Grey Mould | D46: Fenhexamid | E46: Fenhexamid | F46: 0.5 | I46: 1.25 | J46: =IF(ISBLANK($E46),0,VLOOKUP($E46,'Table of Hazards (AI only)'!$B$6:$P$129,8,)) -> 18.5 | L46: =IF(ISBLANK($E46),0,VLOOKUP($E46,'Table of Hazards (AI only)'!$B$6:$P$129,9,)) -> 3.5 | M46: =IF(ISBLANK($E46),0,VLOOKUP($E46,'Table of Hazards (AI only)'!$B$6:$P$129,11,)) -> 12.833333 | O46: =IF(ISBLANK($E46),0,VLOOKUP($E46,'Table of Hazards (AI only)'!$B$6:$P$129,12,)) -> 0.3037476 | P46: =IF(ISBLANK($G46),0,VLOOKUP($G46,'Table of Hazards (AI only)'!$B$6:$P$129,8,)) -> 0 | R46: =IF(ISBLANK($G46),0,VLOOKUP($G46,'Table of Hazards (AI only)'!$B$6:$P$129,9,)) -> 0 | S46: =IF(ISBLANK($G46),0,VLOOKUP($G46,'Table of Hazards (AI only)'!$B$6:$P$129,11,)) -> 0 | U46: =IF(ISBLANK($G46),0,VLOOKUP($G46,'Table of Hazards (AI only)'!$B$6:$P$129,12,)) -> 0 | V46: =(($F46*J46)+($H46*P46))*$I46 -> 11.5625 | X46: =(($F46*L46)+($H46*R46))*$I46 -> 2.1875 | Y46: =(($F46*M46)+($H46*S46))*$I46 -> 8.0208333 | AA46: =(($F46*O46)+($H46*U46))*$I46 -> 0.18984225 | AC46: Teldor Plus
B47: Grapes | C47: Grey Mould | D47: Fenpyrazamine | E47: Fenpyrazamine | F47: 0.5 | I47: 1 | J47: =IF(ISBLANK($E47),0,VLOOKUP($E47,'Table of Hazards (AI only)'!$B$6:$P$129,8,)) -> 19 | L47: =IF(ISBLANK($E47),0,VLOOKUP($E47,'Table of Hazards (AI only)'!$B$6:$P$129,9,)) -> 7 | M47: =IF(ISBLANK($E47),0,VLOOKUP($E47,'Table of Hazards (AI only)'!$B$6:$P$129,11,)) -> 13 | O47: =IF(ISBLANK($E47),0,VLOOKUP($E47,'Table of Hazards (AI only)'!$B$6:$P$129,12,)) -> 0.3037476 | P47: =IF(ISBLANK($G47),0,VLOOKUP($G47,'Table of Hazards (AI only)'!$B$6:$P$129,8,)) -> 0 | R47: =IF(ISBLANK($G47),0,VLOOKUP($G47,'Table of Hazards (AI only)'!$B$6:$P$129,9,)) -> 0 | S47: =IF(ISBLANK($G47),0,VLOOKUP($G47,'Table of Hazards (AI only)'!$B$6:$P$129,11,)) -> 0 | U47: =IF(ISBLANK($G47),0,VLOOKUP($G47,'Table of Hazards (AI only)'!$B$6:$P$129,12,)) -> 0 | V47: =(($F47*J47)+($H47*P47))*$I47 -> 9.5 | X47: =(($F47*L47)+($H47*R47))*$I47 -> 3.5 | Y47: =(($F47*M47)+($H47*S47))*$I47 -> 6.5 | AA47: =(($F47*O47)+($H47*U47))*$I47 -> 0.1518738 | AC47: Prolectus
B48: Grapes | C48: Grey Mould | D48: Fluazinam | E48: Fluazinam | F48: 0.5 | I48: 1.5 | J48: =IF(ISBLANK($E48),0,VLOOKUP($E48,'Table of Hazards (AI only)'!$B$6:$P$129,8,)) -> 22 | L48: =IF(ISBLANK($E48),0,VLOOKUP($E48,'Table of Hazards (AI only)'!$B$6:$P$129,9,)) -> 4 | M48: =IF(ISBLANK($E48),0,VLOOKUP($E48,'Table of Hazards (AI only)'!$B$6:$P$129,11,)) -> 14.666667 | O48: =IF(ISBLANK($E48),0,VLOOKUP($E48,'Table of Hazards (AI only)'!$B$6:$P$129,12,)) -> 0.3037476 | P48: =IF(ISBLANK($G48),0,VLOOKUP($G48,'Table of Hazards (AI only)'!$B$6:$P$129,8,)) -> 0 | R48: =IF(ISBLANK($G48),0,VLOOKUP($G48,'Table of Hazards (AI only)'!$B$6:$P$129,9,)) -> 0 | S48: =IF(ISBLANK($G48),0,VLOOKUP($G48,'Table of Hazards (AI only)'!$B$6:$P$129,11,)) -> 0 | U48: =IF(ISBLANK($G48),0,VLOOKUP($G48,'Table of Hazards (AI only)'!$B$6:$P$129,12,)) -> 0 | V48: =(($F48*J48)+($H48*P48))*$I48 -> 16.5 | X48: =(($F48*L48)+($H48*R48))*$I48 -> 3 | Y48: =(($F48*M48)+($H48*S48))*$I48 -> 11 | AA48: =(($F48*O48)+($H48*U48))*$I48 -> 0.2278107 | AC48: Banjo
B49: Grapes | C49: Grey Mould | D49: Fludioxonil + Cyprodinil | E49: Fludioxonil | F49: 0.25 | G49: Cyprodinil | H49: 0.375 | I49: 0.8 | J49: =IF(ISBLANK($E49),0,VLOOKUP($E49,'Table of Hazards (AI only)'!$B$6:$P$129,8,)) -> 22 | L49: =IF(ISBLANK($E49),0,VLOOKUP($E49,'Table of Hazards (AI only)'!$B$6:$P$129,9,)) -> 4 | M49: =IF(ISBLANK($E49),0,VLOOKUP($E49,'Table of Hazards (AI only)'!$B$6:$P$129,11,)) -> 12 | O49: =IF(ISBLANK($E49),0,VLOOKUP($E49,'Table of Hazards (AI only)'!$B$6:$P$129,12,)) -> 0.3037476 | P49: =IF(ISBLANK($G49),0,VLOOKUP($G49,'Table of Hazards (AI only)'!$B$6:$P$129,8,)) -> 25 | R49: =IF(ISBLANK($G49),0,VLOOKUP($G49,'Table of Hazards (AI only)'!$B$6:$P$129,9,)) -> 13 | S49: =IF(ISBLANK($G49),0,VLOOKUP($G49,'Table of Hazards (AI only)'!$B$6:$P$129,11,)) -> 18 | U49: =IF(ISBLANK($G49),0,VLOOKUP($G49,'Table of Hazards (AI only)'!$B$6:$P$129,12,)) -> 0.3037476 | V49: =(($F49*J49)+($H49*P49))*$I49 -> 11.9 | X49: =(($F49*L49)+($H49*R49))*$I49 -> 4.7 | Y49: =(($F49*M49)+($H49*S49))*$I49 -> 7.8 | AA49: =(($F49*O49)+($H49*U49))*$I49 -> 0.1518738 | AC49: Switch
B50: Grapes | C50: Grey Mould | D50: Pyrimethanil | E50: Pyrimethanil | F50: 0.4 | I50: 2.5 | J50: =IF(ISBLANK($E50),0,VLOOKUP($E50,'Table of Hazards (AI only)'!$B$6:$P$129,8,)) -> 19 | L50: =IF(ISBLANK($E50),0,VLOOKUP($E50,'Table of Hazards (AI only)'!$B$6:$P$129,9,)) -> 7 | M50: =IF(ISBLANK($E50),0,VLOOKUP($E50,'Table of Hazards (AI only)'!$B$6:$P$129,11,)) -> 14 | O50: =IF(ISBLANK($E50),0,VLOOKUP($E50,'Table of Hazards (AI only)'!$B$6:$P$129,12,)) -> 0.3037476 | P50: =IF(ISBLANK($G50),0,VLOOKUP($G50,'Table of Hazards (AI only)'!$B$6:$P$129,8,)) -> 0 | R50: =IF(ISBLANK($G50),0,VLOOKUP($G50,'Table of Hazards (AI only)'!$B$6:$P$129,9,)) -> 0 | S50: =IF(ISBLANK($G50),0,VLOOKUP($G50,'Table of Hazards (AI only)'!$B$6:$P$129,11,)) -> 0 | U50: =IF(ISBLANK($G50),0,VLOOKUP($G50,'Table of Hazards (AI only)'!$B$6:$P$129,12,)) -> 0 | V50: =(($F50*J50)+($H50*P50))*$I50 -> 19 | X50: =(($F50*L50)+($H50*R50))*$I50 -> 7 | Y50: =(($F50*M50)+($H50*S50))*$I50 -> 14 | AA50: =(($F50*O50)+($H50*U50))*$I50 -> 0.3037476 | AC50: Scala
B51: Grapes | C51: Grey Mould | D51: Potassium bicarbonate | E51: Potassium bicarbonate | F51: 0.85 | I51: 5 | J51: =IF(ISBLANK($E51),0,VLOOKUP($E51,'Table of Hazards (AI only)'!$B$6:$P$129,8,)) -> 8 | L51: =IF(ISBLANK($E51),0,VLOOKUP($E51,'Table of Hazards (AI only)'!$B$6:$P$129,9,)) -> 2 | M51: =IF(ISBLANK($E51),0,VLOOKUP($E51,'Table of Hazards (AI only)'!$B$6:$P$129,11,)) -> 8.6666667 | O51: =IF(ISBLANK($E51),0,VLOOKUP($E51,'Table of Hazards (AI only)'!$B$6:$P$129,12,)) -> 0.3037476 | P51: =IF(ISBLANK($G51),0,VLOOKUP($G51,'Table of Hazards (AI only)'!$B$6:$P$129,8,)) -> 0 | R51: =IF(ISBLANK($G51),0,VLOOKUP($G51,'Table of Hazards (AI only)'!$B$6:$P$129,9,)) -> 0 | S51: =IF(ISBLANK($G51),0,VLOOKUP($G51,'Table of Hazards (AI only)'!$B$6:$P$129,11,)) -> 0 | U51: =IF(ISBLANK($G51),0,VLOOKUP($G51,'Table of Hazards (AI only)'!$B$6:$P$129,12,)) -> 0 | V51: =(($F51*J51)+($H51*P51))*$I51 -> 34 | X51: =(($F51*L51)+($H51*R51))*$I51 -> 8.5 | Y51: =(($F51*M51)+($H51*S51))*$I51 -> 36.833333 | AA51: =(($F51*O51)+($H51*U51))*$I51 -> 1.2909273 | AC51: Karma
B52: Grapes | C52: Powdery Mildew | D52: Azoxystrobin | E52: Azoxystrobin | F52: 0.25 | I52: 1 | J52: =IF(ISBLANK($E52),0,VLOOKUP($E52,'Table of Hazards (AI only)'!$B$6:$P$129,8,)) -> 40.5 | L52: =IF(ISBLANK($E52),0,VLOOKUP($E52,'Table of Hazards (AI only)'!$B$6:$P$129,9,)) -> 25.5 | M52: =IF(ISBLANK($E52),0,VLOOKUP($E52,'Table of Hazards (AI only)'!$B$6:$P$129,11,)) -> 22.166667 | O52: =IF(ISBLANK($E52),0,VLOOKUP($E52,'Table of Hazards (AI only)'!$B$6:$P$129,12,)) -> 0.3037476 | P52: =IF(ISBLANK($G52),0,VLOOKUP($G52,'Table of Hazards (AI only)'!$B$6:$P$129,8,)) -> 0 | R52: =IF(ISBLANK($G52),0,VLOOKUP($G52,'Table of Hazards (AI only)'!$B$6:$P$129,9,)) -> 0 | S52: =IF(ISBLANK($G52),0,VLOOKUP($G52,'Table of Hazards (AI only)'!$B$6:$P$129,11,)) -> 0 | U52: =IF(ISBLANK($G52),0,VLOOKUP($G52,'Table of Hazards (AI only)'!$B$6:$P$129,12,)) -> 0 | V52: =(($F52*J52)+($H52*P52))*$I52 -> 10.125 | X52: =(($F52*L52)+($H52*R52))*$I52 -> 6.375 | Y52: =(($F52*M52)+($H52*S52))*$I52 -> 5.5416667 | AA52: =(($F52*O52)+($H52*U52))*$I52 -> 0.075936899 | AC52: Quadris
B53: Grapes | C53: Powdery Mildew | D53: Boscalid | E53: Boscalid | F53: 0.5 | I53: 1.1 | J53: =IF(ISBLANK($E53),0,VLOOKUP($E53,'Table of Hazards (AI only)'!$B$6:$P$129,8,)) -> 48 | L53: =IF(ISBLANK($E53),0,VLOOKUP($E53,'Table of Hazards (AI only)'!$B$6:$P$129,9,)) -> 30 | M53: =IF(ISBLANK($E53),0,VLOOKUP($E53,'Table of Hazards (AI only)'!$B$6:$P$129,11,)) -> 22.666667 | O53: =IF(ISBLANK($E53),0,VLOOKUP($E53,'Table of Hazards (AI only)'!$B$6:$P$129,12,)) -> 0.3037476 | P53: =IF(ISBLANK($G53),0,VLOOKUP($G53,'Table of Hazards (AI only)'!$B$6:$P$129,8,)) -> 0 | R53: =IF(ISBLANK($G53),0,VLOOKUP($G53,'Table of Hazards (AI only)'!$B$6:$P$129,9,)) -> 0 | S53: =IF(ISBLANK($G53),0,VLOOKUP($G53,'Table of Hazards (AI only)'!$B$6:$P$129,11,)) -> 0 | U53: =IF(ISBLANK($G53),0,VLOOKUP($G53,'Table of Hazards (AI only)'!$B$6:$P$129,12,)) -> 0 | V53: =(($F53*J53)+($H53*P53))*$I53 -> 26.4 | X53: =(($F53*L53)+($H53*R53))*$I53 -> 16.5 | Y53: =(($F53*M53)+($H53*S53))*$I53 -> 12.466667 | AA53: =(($F53*O53)+($H53*U53))*$I53 -> 0.16706118 | AC53: Cantus
B54: Grapes | C54: Powdery Mildew | D54: Bupirimate | E54: Bupirimate | F54: 0.25 | I54: 1.15 | J54: =IF(ISBLANK($E54),0,VLOOKUP($E54,'Table of Hazards (AI only)'!$B$6:$P$129,8,)) -> 31 | L54: =IF(ISBLANK($E54),0,VLOOKUP($E54,'Table of Hazards (AI only)'!$B$6:$P$129,9,)) -> 16 | M54: =IF(ISBLANK($E54),0,VLOOKUP($E54,'Table of Hazards (AI only)'!$B$6:$P$129,11,)) -> 18 | O54: =IF(ISBLANK($E54),0,VLOOKUP($E54,'Table of Hazards (AI only)'!$B$6:$P$129,12,)) -> 0.3037476 | P54: =IF(ISBLANK($G54),0,VLOOKUP($G54,'Table of Hazards (AI only)'!$B$6:$P$129,8,)) -> 0 | R54: =IF(ISBLANK($G54),0,VLOOKUP($G54,'Table of Hazards (AI only)'!$B$6:$P$129,9,)) -> 0 | S54: =IF(ISBLANK($G54),0,VLOOKUP($G54,'Table of Hazards (AI only)'!$B$6:$P$129,11,)) -> 0 | U54: =IF(ISBLANK($G54),0,VLOOKUP($G54,'Table of Hazards (AI only)'!$B$6:$P$129,12,)) -> 0 | V54: =(($F54*J54)+($H54*P54))*$I54 -> 8.9125 | X54: =(($F54*L54)+($H54*R54))*$I54 -> 4.6 | Y54: =(($F54*M54)+($H54*S54))*$I54 -> 5.175 | AA54: =(($F54*O54)+($H54*U54))*$I54 -> 0.087327434 | AC54: Nimrod 250 ew
B55: Grapes | C55: Powdery Mildew | D55: Cyproconazole | E55: Cyproconazole | F55: 0.04 | I55: 0.275 | J55: =IF(ISBLANK($E55),0,VLOOKUP($E55,'Table of Hazards (AI only)'!$B$6:$P$129,8,)) -> 32 | L55: =IF(ISBLANK($E55),0,VLOOKUP($E55,'Table of Hazards (AI only)'!$B$6:$P$129,9,)) -> 14 | M55: =IF(ISBLANK($E55),0,VLOOKUP($E55,'Table of Hazards (AI only)'!$B$6:$P$129,11,)) -> 31.333333 | O55: =IF(ISBLANK($E55),0,VLOOKUP($E55,'Table of Hazards (AI only)'!$B$6:$P$129,12,)) -> 0.3037476 | P55: =IF(ISBLANK($G55),0,VLOOKUP($G55,'Table of Hazards (AI only)'!$B$6:$P$129,8,)) -> 0 | R55: =IF(ISBLANK($G55),0,VLOOKUP($G55,'Table of Hazards (AI only)'!$B$6:$P$129,9,)) -> 0 | S55: =IF(ISBLANK($G55),0,VLOOKUP($G55,'Table of Hazards (AI only)'!$B$6:$P$129,11,)) -> 0 | U55: =IF(ISBLANK($G55),0,VLOOKUP($G55,'Table of Hazards (AI only)'!$B$6:$P$129,12,)) -> 0 | V55: =(($F55*J55)+($H55*P55))*$I55 -> 0.352 | X55: =(($F55*L55)+($H55*R55))*$I55 -> 0.154 | Y55: =(($F55*M55)+($H55*S55))*$I55 -> 0.34466667 | AA55: =(($F55*O55)+($H55*U55))*$I55 -> 0.0033412236 | AC55: Galeo
B56: Grapes | C56: Powdery Mildew | D56: Cyflufenamid | E56: Cyflufenamid | F56: 0.0513 | I56: 0.5 | J56: =IF(ISBLANK($E56),0,VLOOKUP($E56,'Table of Hazards (AI only)'!$B$6:$P$129,8,)) -> 17 | L56: =IF(ISBLANK($E56),0,VLOOKUP($E56,'Table of Hazards (AI only)'!$B$6:$P$129,9,)) -> 5 | M56: =IF(ISBLANK($E56),0,VLOOKUP($E56,'Table of Hazards (AI only)'!$B$6:$P$129,11,)) -> 10.333333 | O56: =IF(ISBLANK($E56),0,VLOOKUP($E56,'Table of Hazards (AI only)'!$B$6:$P$129,12,)) -> 0.3037476 | P56: =IF(ISBLANK($G56),0,VLOOKUP($G56,'Table of Hazards (AI only)'!$B$6:$P$129,8,)) -> 0 | R56: =IF(ISBLANK($G56),0,VLOOKUP($G56,'Table of Hazards (AI only)'!$B$6:$P$129,9,)) -> 0 | S56: =IF(ISBLANK($G56),0,VLOOKUP($G56,'Table of Hazards (AI only)'!$B$6:$P$129,11,)) -> 0 | U56: =IF(ISBLANK($G56),0,VLOOKUP($G56,'Table of Hazards (AI only)'!$B$6:$P$129,12,)) -> 0 | V56: =(($F56*J56)+($H56*P56))*$I56 -> 0.43605 | X56: =(($F56*L56)+($H56*R56))*$I56 -> 0.12825 | Y56: =(($F56*M56)+($H56*S56))*$I56 -> 0.26505 | AA56: =(($F56*O56)+($H56*U56))*$I56 -> 0.0077911259 | AC56: Cidely
B57: Grapes | C57: Powdery Mildew | D57: Difenoconazole | E57: Difenoconazole | F57: 0.25 | I57: 0.2 | J57: =IF(ISBLANK($E57),0,VLOOKUP($E57,'Table of Hazards (AI only)'!$B$6:$P$129,8,)) -> 37 | L57: =IF(ISBLANK($E57),0,VLOOKUP($E57,'Table of Hazards (AI only)'!$B$6:$P$129,9,)) -> 19 | M57: =IF(ISBLANK($E57),0,VLOOKUP($E57,'Table of Hazards (AI only)'!$B$6:$P$129,11,)) -> 18 | O57: =IF(ISBLANK($E57),0,VLOOKUP($E57,'Table of Hazards (AI only)'!$B$6:$P$129,12,)) -> 0.3037476 | P57: =IF(ISBLANK($G57),0,VLOOKUP($G57,'Table of Hazards (AI only)'!$B$6:$P$129,8,)) -> 0 | R57: =IF(ISBLANK($G57),0,VLOOKUP($G57,'Table of Hazards (AI only)'!$B$6:$P$129,9,)) -> 0 | S57: =IF(ISBLANK($G57),0,VLOOKUP($G57,'Table of Hazards (AI only)'!$B$6:$P$129,11,)) -> 0 | U57: =IF(ISBLANK($G57),0,VLOOKUP($G57,'Table of Hazards (AI only)'!$B$6:$P$129,12,)) -> 0 | V57: =(($F57*J57)+($H57*P57))*$I57 -> 1.85 | X57: =(($F57*L57)+($H57*R57))*$I57 -> 0.95 | Y57: =(($F57*M57)+($H57*S57))*$I57 -> 0.9 | AA57: =(($F57*O57)+($H57*U57))*$I57 -> 0.01518738 | AC57: SCORE 25 EC
B58: Grapes | C58: Powdery Mildew | D58: Fenbuconazole | E58: Fenbuconazole | F58: 0.05 | I58: 0.6 | J58: =IF(ISBLANK($E58),0,VLOOKUP($E58,'Table of Hazards (AI only)'!$B$6:$P$129,8,)) -> 37 | L58: =IF(ISBLANK($E58),0,VLOOKUP($E58,'Table of Hazards (AI only)'!$B$6:$P$129,9,)) -> 19 | M58: =IF(ISBLANK($E58),0,VLOOKUP($E58,'Table of Hazards (AI only)'!$B$6:$P$129,11,)) -> 20 | O58: =IF(ISBLANK($E58),0,VLOOKUP($E58,'Table of Hazards (AI only)'!$B$6:$P$129,12,)) -> 0.3037476 | P58: =IF(ISBLANK($G58),0,VLOOKUP($G58,'Table of Hazards (AI only)'!$B$6:$P$129,8,)) -> 0 | R58: =IF(ISBLANK($G58),0,VLOOKUP($G58,'Table of Hazards (AI only)'!$B$6:$P$129,9,)) -> 0 | S58: =IF(ISBLANK($G58),0,VLOOKUP($G58,'Table of Hazards (AI only)'!$B$6:$P$129,11,)) -> 0 | U58: =IF(ISBLANK($G58),0,VLOOKUP($G58,'Table of Hazards (AI only)'!$B$6:$P$129,12,)) -> 0 | V58: =(($F58*J58)+($H58*P58))*$I58 -> 1.11 | X58: =(($F58*L58)+($H58*R58))*$I58 -> 0.57 | Y58: =(($F58*M58)+($H58*S58))*$I58 -> 0.6 | AA58: =(($F58*O58)+($H58*U58))*$I58 -> 0.0091124279 | AC58: Simitar 5 ew
B59: Grapes | C59: Powdery Mildew | D59: Meptyldinocap | E59: Meptyldinocap | F59: 0.35 | I59: 0.6 | J59: =IF(ISBLANK($E59),0,VLOOKUP($E59,'Table of Hazards (AI only)'!$B$6:$P$129,8,)) -> 11.5 | L59: =IF(ISBLANK($E59),0,VLOOKUP($E59,'Table of Hazards (AI only)'!$B$6:$P$129,9,)) -> 2.5 | M59: =IF(ISBLANK($E59),0,VLOOKUP($E59,'Table of Hazards (AI only)'!$B$6:$P$129,11,)) -> 14.5 | O59: =IF(ISBLANK($E59),0,VLOOKUP($E59,'Table of Hazards (AI only)'!$B$6:$P$129,12,)) -> 0.3037476 | P59: =IF(ISBLANK($G59),0,VLOOKUP($G59,'Table of Hazards (AI only)'!$B$6:$P$129,8,)) -> 0 | R59: =IF(ISBLANK($G59),0,VLOOKUP($G59,'Table of Hazards (AI only)'!$B$6:$P$129,9,)) -> 0 | S59: =IF(ISBLANK($G59),0,VLOOKUP($G59,'Table of Hazards (AI only)'!$B$6:$P$129,11,)) -> 0 | U59: =IF(ISBLANK($G59),0,VLOOKUP($G59,'Table of Hazards (AI only)'!$B$6:$P$129,12,)) -> 0 | V59: =(($F59*J59)+($H59*P59))*$I59 -> 2.415 | X59: =(($F59*L59)+($H59*R59))*$I59 -> 0.525 | Y59: =(($F59*M59)+($H59*S59))*$I59 -> 3.045 | AA59: =(($F59*O59)+($H59*U59))*$I59 -> 0.063786995 | AC59: Karathane Star
B60: Grapes | C60: Powdery Mildew | D60: Metrafenone | E60: Metrafenone | F60: 0.5 | I60: 2.25 | J60: =IF(ISBLANK($E60),0,VLOOKUP($E60,'Table of Hazards (AI only)'!$B$6:$P$129,8,)) -> 31 | L60: =IF(ISBLANK($E60),0,VLOOKUP($E60,'Table of Hazards (AI only)'!$B$6:$P$129,9,)) -> 11 | M60: =IF(ISBLANK($E60),0,VLOOKUP($E60,'Table of Hazards (AI only)'!$B$6:$P$129,11,)) -> 46.333333 | O60: =IF(ISBLANK($E60),0,VLOOKUP($E60,'Table of Hazards (AI only)'!$B$6:$P$129,12,)) -> 0.3037476 | P60: =IF(ISBLANK($G60),0,VLOOKUP($G60,'Table of Hazards (AI only)'!$B$6:$P$129,8,)) -> 0 | R60: =IF(ISBLANK($G60),0,VLOOKUP($G60,'Table of Hazards (AI only)'!$B$6:$P$129,9,)) -> 0 | S60: =IF(ISBLANK($G60),0,VLOOKUP($G60,'Table of Hazards (AI only)'!$B$6:$P$129,11,)) -> 0 | U60: =IF(ISBLANK($G60),0,VLOOKUP($G60,'Table of Hazards (AI only)'!$B$6:$P$129,12,)) -> 0 | V60: =(($F60*J60)+($H60*P60))*$I60 -> 34.875 | X60: =(($F60*L60)+($H60*R60))*$I60 -> 12.375 | Y60: =(($F60*M60)+($H60*S60))*$I60 -> 52.125 | AA60: =(($F60*O60)+($H60*U60))*$I60 -> 0.34171605 | AC60: Vivando
B61: Grapes | C61: Powdery Mildew | D61: Myclobutanil | E61: Myclobutanil | F61: 0.045 | I61: 1.5 | J61: =IF(ISBLANK($E61),0,VLOOKUP($E61,'Table of Hazards (AI only)'!$B$6:$P$129,8,)) -> 29 | L61: =IF(ISBLANK($E61),0,VLOOKUP($E61,'Table of Hazards (AI only)'!$B$6:$P$129,9,)) -> 17 | M61: =IF(ISBLANK($E61),0,VLOOKUP($E61,'Table of Hazards (AI only)'!$B$6:$P$129,11,)) -> 24.666667 | O61: =IF(ISBLANK($E61),0,VLOOKUP($E61,'Table of Hazards (AI only)'!$B$6:$P$129,12,)) -> 0.3037476 | P61: =IF(ISBLANK($G61),0,VLOOKUP($G61,'Table of Hazards (AI only)'!$B$6:$P$129,8,)) -> 0 | R61: =IF(ISBLANK($G61),0,VLOOKUP($G61,'Table of Hazards (AI only)'!$B$6:$P$129,9,)) -> 0 | S61: =IF(ISBLANK($G61),0,VLOOKUP($G61,'Table of Hazards (AI only)'!$B$6:$P$129,11,)) -> 0 | U61: =IF(ISBLANK($G61),0,VLOOKUP($G61,'Table of Hazards (AI only)'!$B$6:$P$129,12,)) -> 0 | V61: =(($F61*J61)+($H61*P61))*$I61 -> 1.9575 | X61: =(($F61*L61)+($H61*R61))*$I61 -> 1.1475 | Y61: =(($F61*M61)+($H61*S61))*$I61 -> 1.665 | AA61: =(($F61*O61)+($H61*U61))*$I61 -> 0.020502963 | AC61: Thiocur Forte
... B64: Grapes | C64: Powdery Mildew | D64: Propiconazole | E64: Propiconazole | F64: 0.25 | I64: 1.15 | J64: =IF(ISBLANK($E64),0,VLOOKUP($E64,'Table of Hazards (AI only)'!$B$6:$P$129,8,)) -> 33 | L64: =IF(ISBLANK($E64),0,VLOOKUP($E64,'Table of Hazards (AI only)'!$B$6:$P$129,9,)) -> 18 | M64: =IF(ISBLANK($E64),0,VLOOKUP($E64,'Table of Hazards (AI only)'!$B$6:$P$129,11,)) -> 16.666667 | O64: =IF(ISBLANK($E64),0,VLOOKUP($E64,'Table of Hazards (AI only)'!$B$6:$P$129,12,)) -> 0.3037476 | P64: =IF(ISBLANK($G64),0,VLOOKUP($G64,'Table of Hazards (AI only)'!$B$6:$P$129,8,)) -> 0 | R64: =IF(ISBLANK($G64),0,VLOOKUP($G64,'Table of Hazards (AI only)'!$B$6:$P$129,9,)) -> 0 | S64: =IF(ISBLANK($G64),0,VLOOKUP($G64,'Table of Hazards (AI only)'!$B$6:$P$129,11,)) -> 0 | U64: =IF(ISBLANK($G64),0,VLOOKUP($G64,'Table of Hazards (AI only)'!$B$6:$P$129,12,)) -> 0 | V64: =(($F64*J64)+($H64*P64))*$I64 -> 9.4875 | X64: =(($F64*L64)+($H64*R64))*$I64 -> 5.175 | Y64: =(($F64*M64)+($H64*S64))*$I64 -> 4.7916667 | AA64: =(($F64*O64)+($H64*U64))*$I64 -> 0.087327434 | AC64: Protil EC
B65: Grapes | C65: Powdery Mildew | D65: Pyraclostrobin + Metiram | E65: Pyraclostrobin | F65: 0.05 | G65: Metiram | H65: 0.55 | I65: 1.5 | J65: =IF(ISBLANK($E65),0,VLOOKUP($E65,'Table of Hazards (AI only)'!$B$6:$P$129,8,)) -> 21 | L65: =IF(ISBLANK($E65),0,VLOOKUP($E65,'Table of Hazards (AI only)'!$B$6:$P$129,9,)) -> 6 | M65: =IF(ISBLANK($E65),0,VLOOKUP($E65,'Table of Hazards (AI only)'!$B$6:$P$129,11,)) -> 13.333333 | O65: =IF(ISBLANK($E65),0,VLOOKUP($E65,'Table of Hazards (AI only)'!$B$6:$P$129,12,)) -> 0.3037476 | P65: =IF(ISBLANK($G65),0,VLOOKUP($G65,'Table of Hazards (AI only)'!$B$6:$P$129,8,)) -> 18.5 | R65: =IF(ISBLANK($G65),0,VLOOKUP($G65,'Table of Hazards (AI only)'!$B$6:$P$129,9,)) -> 3.5 | S65: =IF(ISBLANK($G65),0,VLOOKUP($G65,'Table of Hazards (AI only)'!$B$6:$P$129,11,)) -> 12.833333 | U65: =IF(ISBLANK($G65),0,VLOOKUP($G65,'Table of Hazards (AI only)'!$B$6:$P$129,12,)) -> 0.3037476 | V65: =(($F65*J65)+($H65*P65))*$I65 -> 16.8375 | X65: =(($F65*L65)+($H65*R65))*$I65 -> 3.3375 | Y65: =(($F65*M65)+($H65*S65))*$I65 -> 11.5875 | AA65: =(($F65*O65)+($H65*U65))*$I65 -> 0.27337284 | AC65: Cabrio Top
B66: Grapes | C66: Powdery Mildew | D66: Quinoxyfen | E66: Quinoxyfen | F66: 0.25 | I66: 0.275 | J66: =IF(ISBLANK($E66),0,VLOOKUP($E66,'Table of Hazards (AI only)'!$B$6:$P$129,8,)) -> 13 | L66: =IF(ISBLANK($E66),0,VLOOKUP($E66,'Table of Hazards (AI only)'!$B$6:$P$129,9,)) -> 4 | M66: =IF(ISBLANK($E66),0,VLOOKUP($E66,'Table of Hazards (AI only)'!$B$6:$P$129,11,)) -> 10 | O66: =IF(ISBLANK($E66),0,VLOOKUP($E66,'Table of Hazards (AI only)'!$B$6:$P$129,12,)) -> 0.3037476 | P66: =IF(ISBLANK($G66),0,VLOOKUP($G66,'Table of Hazards (AI only)'!$B$6:$P$129,8,)) -> 0 | R66: =IF(ISBLANK($G66),0,VLOOKUP($G66,'Table of Hazards (AI only)'!$B$6:$P$129,9,)) -> 0 | S66: =IF(ISBLANK($G66),0,VLOOKUP($G66,'Table of Hazards (AI only)'!$B$6:$P$129,11,)) -> 0 | U66: =IF(ISBLANK($G66),0,VLOOKUP($G66,'Table of Hazards (AI only)'!$B$6:$P$129,12,)) -> 0 | V66: =(($F66*J66)+($H66*P66))*$I66 -> 0.89375 | X66: =(($F66*L66)+($H66*R66))*$I66 -> 0.275 | Y66: =(($F66*M66)+($H66*S66))*$I66 -> 0.6875 | AA66: =(($F66*O66)+($H66*U66))*$I66 -> 0.020882647 | AC66: Arius
B67: Grapes | C67: Powdery Mildew | D67: Spiroxamine | E67: Spiroxamine | F67: 0.3 | I67: 1.15 | J67: =IF(ISBLANK($E67),0,VLOOKUP($E67,'Table of Hazards (AI only)'!$B$6:$P$129,8,)) -> 32.5 | L67: =IF(ISBLANK($E67),0,VLOOKUP($E67,'Table of Hazards (AI only)'!$B$6:$P$129,9,)) -> 5.5 | M67: =IF(ISBLANK($E67),0,VLOOKUP($E67,'Table of Hazards (AI only)'!$B$6:$P$129,11,)) -> 22.833333 | O67: =IF(ISBLANK($E67),0,VLOOKUP($E67,'Table of Hazards (AI only)'!$B$6:$P$129,12,)) -> 0.3037476 | P67: =IF(ISBLANK($G67),0,VLOOKUP($G67,'Table of Hazards (AI only)'!$B$6:$P$129,8,)) -> 0 | R67: =IF(ISBLANK($G67),0,VLOOKUP($G67,'Table of Hazards (AI only)'!$B$6:$P$129,9,)) -> 0 | S67: =IF(ISBLANK($G67),0,VLOOKUP($G67,'Table of Hazards (AI only)'!$B$6:$P$129,11,)) -> 0 | U67: =IF(ISBLANK($G67),0,VLOOKUP($G67,'Table of Hazards (AI only)'!$B$6:$P$129,12,)) -> 0 | V67: =(($F67*J67)+($H67*P67))*$I67 -> 11.2125 | X67: =(($F67*L67)+($H67*R67))*$I67 -> 1.8975 | Y67: =(($F67*M67)+($H67*S67))*$I67 -> 7.8775 | AA67: =(($F67*O67)+($H67*U67))*$I67 -> 0.10479292 | AC67: Prosper 300 CS
B68: Grapes | C68: Powdery Mildew | D68: Sulphur | E68: Sulphur | F68: 0.8 | I68: 1.15 | J68: =IF(ISBLANK($E68),0,VLOOKUP($E68,'Table of Hazards (AI only)'!$B$6:$P$129,8,)) -> 11.5 | L68: =IF(ISBLANK($E68),0,VLOOKUP($E68,'Table of Hazards (AI only)'!$B$6:$P$129,9,)) -> 2.5 | M68: =IF(ISBLANK($E68),0,VLOOKUP($E68,'Table of Hazards (AI only)'!$B$6:$P$129,11,)) -> 9.1666667 | O68: =IF(ISBLANK($E68),0,VLOOKUP($E68,'Table of Hazards (AI only)'!$B$6:$P$129,12,)) -> 0.3037476 | P68: =IF(ISBLANK($G68),0,VLOOKUP($G68,'Table of Hazards (AI only)'!$B$6:$P$129,8,)) -> 0 | R68: =IF(ISBLANK($G68),0,VLOOKUP($G68,'Table of Hazards (AI only)'!$B$6:$P$129,9,)) -> 0 | S68: =IF(ISBLANK($G68),0,VLOOKUP($G68,'Table of Hazards (AI only)'!$B$6:$P$129,11,)) -> 0 | U68: =IF(ISBLANK($G68),0,VLOOKUP($G68,'Table of Hazards (AI only)'!$B$6:$P$129,12,)) -> 0 | V68: =(($F68*J68)+($H68*P68))*$I68 -> 10.58 | X68: =(($F68*L68)+($H68*R68))*$I68 -> 2.3 | Y68: =(($F68*M68)+($H68*S68))*$I68 -> 8.4333333 | AA68: =(($F68*O68)+($H68*U68))*$I68 -> 0.27944779 | AC68: Zolfo 80 WP
B69: Grapes | C69: Powdery Mildew | D69: Tebuconazole | E69: Tebuconazole | F69: 0.25 | I69: 0.4 | J69: =IF(ISBLANK($E69),0,VLOOKUP($E69,'Table of Hazards (AI only)'!$B$6:$P$129,8,)) -> 53 | L69: =IF(ISBLANK($E69),0,VLOOKUP($E69,'Table of Hazards (AI only)'!$B$6:$P$129,9,)) -> 29 | M69: =IF(ISBLANK($E69),0,VLOOKUP($E69,'Table of Hazards (AI only)'!$B$6:$P$129,11,)) -> 27.333333 | O69: =IF(ISBLANK($E69),0,VLOOKUP($E69,'Table of Hazards (AI only)'!$B$6:$P$129,12,)) -> 0.3037476 | P69: =IF(ISBLANK($G69),0,VLOOKUP($G69,'Table of Hazards (AI only)'!$B$6:$P$129,8,)) -> 0 | R69: =IF(ISBLANK($G69),0,VLOOKUP($G69,'Table of Hazards (AI only)'!$B$6:$P$129,9,)) -> 0 | S69: =IF(ISBLANK($G69),0,VLOOKUP($G69,'Table of Hazards (AI only)'!$B$6:$P$129,11,)) -> 0 | U69: =IF(ISBLANK($G69),0,VLOOKUP($G69,'Table of Hazards (AI only)'!$B$6:$P$129,12,)) -> 0 | V69: =(($F69*J69)+($H69*P69))*$I69 -> 5.3 | X69: =(($F69*L69)+($H69*R69))*$I69 -> 2.9 | Y69: =(($F69*M69)+($H69*S69))*$I69 -> 2.7333333 | AA69: =(($F69*O69)+($H69*U69))*$I69 -> 0.03037476 | AC69: Folicur WG
B70: Grapes | C70: Powdery Mildew | D70: Tetraconazole | E70: Tetraconazole | F70: 0.125 | I70: 0.2 | J70: =IF(ISBLANK($E70),0,VLOOKUP($E70,'Table of Hazards (AI only)'!$B$6:$P$129,8,)) -> 48 | L70: =IF(ISBLANK($E70),0,VLOOKUP($E70,'Table of Hazards (AI only)'!$B$6:$P$129,9,)) -> 30 | M70: =IF(ISBLANK($E70),0,VLOOKUP($E70,'Table of Hazards (AI only)'!$B$6:$P$129,11,)) -> 34 | O70: =IF(ISBLANK($E70),0,VLOOKUP($E70,'Table of Hazards (AI only)'!$B$6:$P$129,12,)) -> 0.3037476 | P70: =IF(ISBLANK($G70),0,VLOOKUP($G70,'Table of Hazards (AI only)'!$B$6:$P$129,8,)) -> 0 | R70: =IF(ISBLANK($G70),0,VLOOKUP($G70,'Table of Hazards (AI only)'!$B$6:$P$129,9,)) -> 0 | S70: =IF(ISBLANK($G70),0,VLOOKUP($G70,'Table of Hazards (AI only)'!$B$6:$P$129,11,)) -> 0 | U70: =IF(ISBLANK($G70),0,VLOOKUP($G70,'Table of Hazards (AI only)'!$B$6:$P$129,12,)) -> 0 | V70: =(($F70*J70)+($H70*P70))*$I70 -> 1.2 | X70: =(($F70*L70)+($H70*R70))*$I70 -> 0.75 | Y70: =(($F70*M70)+($H70*S70))*$I70 -> 0.85 | AA70: =(($F70*O70)+($H70*U70))*$I70 -> 0.0075936899 | AC70: Domark
B71: Grapes | C71: Powdery Mildew | D71: Trifloxystrobin | E71: Trifloxystrobin | F71: 0.5 | I71: 0.1375 | J71: =IF(ISBLANK($E71),0,VLOOKUP($E71,'Table of Hazards (AI only)'!$B$6:$P$129,8,)) -> 22 | L71: =IF(ISBLANK($E71),0,VLOOKUP($E71,'Table of Hazards (AI only)'!$B$6:$P$129,9,)) -> 4 | M71: =IF(ISBLANK($E71),0,VLOOKUP($E71,'Table of Hazards (AI only)'!$B$6:$P$129,11,)) -> 12 | O71: =IF(ISBLANK($E71),0,VLOOKUP($E71,'Table of Hazards (AI only)'!$B$6:$P$129,12,)) -> 0.3037476 | P71: =IF(ISBLANK($G71),0,VLOOKUP($G71,'Table of Hazards (AI only)'!$B$6:$P$129,8,)) -> 0 | R71: =IF(ISBLANK($G71),0,VLOOKUP($G71,'Table of Hazards (AI only)'!$B$6:$P$129,9,)) -> 0 | S71: =IF(ISBLANK($G71),0,VLOOKUP($G71,'Table of Hazards (AI only)'!$B$6:$P$129,11,)) -> 0 | U71: =IF(ISBLANK($G71),0,VLOOKUP($G71,'Table of Hazards (AI only)'!$B$6:$P$129,12,)) -> 0 | V71: =(($F71*J71)+($H71*P71))*$I71 -> 1.5125 | X71: =(($F71*L71)+($H71*R71))*$I71 -> 0.275 | Y71: =(($F71*M71)+($H71*S71))*$I71 -> 0.825 | AA71: =(($F71*O71)+($H71*U71))*$I71 -> 0.020882647 | AC71: Flint
B72: Grapes | C72: European grapevine moth, Eulia | D72: Bacillus thuringiensis Berliner subsp. Kurstaki | E72: Bacillus thuringiensis Berliner subsp. Kurstaki | F72: 0.54 | I72: 0.75 | J72: =IF(ISBLANK($E72),0,VLOOKUP($E72,'Table of Hazards (AI only)'!$B$6:$P$129,8,)) -> 8 | L72: =IF(ISBLANK($E72),0,VLOOKUP($E72,'Table of Hazards (AI only)'!$B$6:$P$129,9,)) -> 2 | M72: =IF(ISBLANK($E72),0,VLOOKUP($E72,'Table of Hazards (AI only)'!$B$6:$P$129,11,)) -> 6.6666667 | O72: =IF(ISBLANK($E72),0,VLOOKUP($E72,'Table of Hazards (AI only)'!$B$6:$P$129,12,)) -> 0.3037476 | P72: =IF(ISBLANK($G72),0,VLOOKUP($G72,'Table of Hazards (AI only)'!$B$6:$P$129,8,)) -> 0 | R72: =IF(ISBLANK($G72),0,VLOOKUP($G72,'Table of Hazards (AI only)'!$B$6:$P$129,9,)) -> 0 | S72: =IF(ISBLANK($G72),0,VLOOKUP($G72,'Table of Hazards (AI only)'!$B$6:$P$129,11,)) -> 0 | U72: =IF(ISBLANK($G72),0,VLOOKUP($G72,'Table of Hazards (AI only)'!$B$6:$P$129,12,)) -> 0 | V72: =(($F72*J72)+($H72*P72))*$I72 -> 3.24 | X72: =(($F72*L72)+($H72*R72))*$I72 -> 0.81 | Y72: =(($F72*M72)+($H72*S72))*$I72 -> 2.7 | AA72: =(($F72*O72)+($H72*U72))*$I72 -> 0.12301778 | AC72: BTK 32 WG
B73: Grapes | C73: European grapevine moth, Eulia | D73: Indoxacarb | E73: Indoxacarb | F73: 0.3 | I73: 0.15 | J73: =IF(ISBLANK($E73),0,VLOOKUP($E73,'Table of Hazards (AI only)'!$B$6:$P$129,8,)) -> 18.5 | L73: =IF(ISBLANK($E73),0,VLOOKUP($E73,'Table of Hazards (AI only)'!$B$6:$P$129,9,)) -> 3.5 | M73: =IF(ISBLANK($E73),0,VLOOKUP($E73,'Table of Hazards (AI only)'!$B$6:$P$129,11,)) -> 22.166667 | O73: =IF(ISBLANK($E73),0,VLOOKUP($E73,'Table of Hazards (AI only)'!$B$6:$P$129,12,)) -> 0.3037476 | P73: =IF(ISBLANK($G73),0,VLOOKUP($G73,'Table of Hazards (AI only)'!$B$6:$P$129,8,)) -> 0 | R73: =IF(ISBLANK($G73),0,VLOOKUP($G73,'Table of Hazards (AI only)'!$B$6:$P$129,9,)) -> 0 | S73: =IF(ISBLANK($G73),0,VLOOKUP($G73,'Table of Hazards (AI only)'!$B$6:$P$129,11,)) -> 0 | U73: =IF(ISBLANK($G73),0,VLOOKUP($G73,'Table of Hazards (AI only)'!$B$6:$P$129,12,)) -> 0 | V73: =(($F73*J73)+($H73*P73))*$I73 -> 0.8325 | X73: =(($F73*L73)+($H73*R73))*$I73 -> 0.1575 | Y73: =(($F73*M73)+($H73*S73))*$I73 -> 0.9975 | AA73: =(($F73*O73)+($H73*U73))*$I73 -> 0.013668642 | AC73: Steward
B74: Grapes | C74: European grapevine moth, Eulia | D74: Spinosad | E74: Spinosad | F74: 0.48 | I74: 0.15 | J74: =IF(ISBLANK($E74),0,VLOOKUP($E74,'Table of Hazards (AI only)'!$B$6:$P$129,8,)) -> 17 | L74: =IF(ISBLANK($E74),0,VLOOKUP($E74,'Table of Hazards (AI only)'!$B$6:$P$129,9,)) -> 5 | M74: =IF(ISBLANK($E74),0,VLOOKUP($E74,'Table of Hazards (AI only)'!$B$6:$P$129,11,)) -> 17.666667 | O74: =IF(ISBLANK($E74),0,VLOOKUP($E74,'Table of Hazards (AI only)'!$B$6:$P$129,12,)) -> 0.3037476 | P74: =IF(ISBLANK($G74),0,VLOOKUP($G74,'Table of Hazards (AI only)'!$B$6:$P$129,8,)) -> 0 | R74: =IF(ISBLANK($G74),0,VLOOKUP($G74,'Table of Hazards (AI only)'!$B$6:$P$129,9,)) -> 0 | S74: =IF(ISBLANK($G74),0,VLOOKUP($G74,'Table of Hazards (AI only)'!$B$6:$P$129,11,)) -> 0 | U74: =IF(ISBLANK($G74),0,VLOOKUP($G74,'Table of Hazards (AI only)'!$B$6:$P$129,12,)) -> 0 | V74: =(($F74*J74)+($H74*P74))*$I74 -> 1.224 | X74: =(($F74*L74)+($H74*R74))*$I74 -> 0.36 | Y74: =(($F74*M74)+($H74*S74))*$I74 -> 1.272 | AA74: =(($F74*O74)+($H74*U74))*$I74 -> 0.021869827 | AC74: Laser
B75: Grapes | C75: European grapevine moth, Eulia | D75: Chlorantraniliprole | E75: Chlorantraniliprole | F75: 0.2 | I75: 0.21 | J75: =IF(ISBLANK($E75),0,VLOOKUP($E75,'Table of Hazards (AI only)'!$B$6:$P$129,8,)) -> 23 | L75: =IF(ISBLANK($E75),0,VLOOKUP($E75,'Table of Hazards (AI only)'!$B$6:$P$129,9,)) -> 11 | M75: =IF(ISBLANK($E75),0,VLOOKUP($E75,'Table of Hazards (AI only)'!$B$6:$P$129,11,)) -> 21.666667 | O75: =IF(ISBLANK($E75),0,VLOOKUP($E75,'Table of Hazards (AI only)'!$B$6:$P$129,12,)) -> 0.3037476 | P75: =IF(ISBLANK($G75),0,VLOOKUP($G75,'Table of Hazards (AI only)'!$B$6:$P$129,8,)) -> 0 | R75: =IF(ISBLANK($G75),0,VLOOKUP($G75,'Table of Hazards (AI only)'!$B$6:$P$129,9,)) -> 0 | S75: =IF(ISBLANK($G75),0,VLOOKUP($G75,'Table of Hazards (AI only)'!$B$6:$P$129,11,)) -> 0 | U75: =IF(ISBLANK($G75),0,VLOOKUP($G75,'Table of Hazards (AI only)'!$B$6:$P$129,12,)) -> 0 | V75: =(($F75*J75)+($H75*P75))*$I75 -> 0.966 | X75: =(($F75*L75)+($H75*R75))*$I75 -> 0.462 | Y75: =(($F75*M75)+($H75*S75))*$I75 -> 0.91 | AA75: =(($F75*O75)+($H75*U75))*$I75 -> 0.012757399 | AC75: Coragen
B76: Grapes | C76: European grapevine moth, Eulia | D76: Methoxyfenozide (MAC) | E76: Methoxyfenozide (MAC) | F76: 0.24 | I76: 0.4 | J76: =IF(ISBLANK($E76),0,VLOOKUP($E76,'Table of Hazards (AI only)'!$B$6:$P$129,8,)) -> 20 | L76: =IF(ISBLANK($E76),0,VLOOKUP($E76,'Table of Hazards (AI only)'!$B$6:$P$129,9,)) -> 14 | M76: =IF(ISBLANK($E76),0,VLOOKUP($E76,'Table of Hazards (AI only)'!$B$6:$P$129,11,)) -> 15.333333 | O76: =IF(ISBLANK($E76),0,VLOOKUP($E76,'Table of Hazards (AI only)'!$B$6:$P$129,12,)) -> 0.3037476 | P76: =IF(ISBLANK($G76),0,VLOOKUP($G76,'Table of Hazards (AI only)'!$B$6:$P$129,8,)) -> 0 | R76: =IF(ISBLANK($G76),0,VLOOKUP($G76,'Table of Hazards (AI only)'!$B$6:$P$129,9,)) -> 0 | S76: =IF(ISBLANK($G76),0,VLOOKUP($G76,'Table of Hazards (AI only)'!$B$6:$P$129,11,)) -> 0 | U76: =IF(ISBLANK($G76),0,VLOOKUP($G76,'Table of Hazards (AI only)'!$B$6:$P$129,12,)) -> 0 | V76: =(($F76*J76)+($H76*P76))*$I76 -> 1.92 | X76: =(($F76*L76)+($H76*R76))*$I76 -> 1.344 | Y76: =(($F76*M76)+($H76*S76))*$I76 -> 1.472 | AA76: =(($F76*O76)+($H76*U76))*$I76 -> 0.029159769 | AC76: Intrepid
B77: Grapes | C77: European grapevine moth, Eulia | D77: Tebufenozide (MAC) | E77: Tebufenozide (MAC) | F77: 0.24 | I77: 0.6 | J77: =IF(ISBLANK($E77),0,VLOOKUP($E77,'Table of Hazards (AI only)'!$B$6:$P$129,8,)) -> 23.5 | L77: =IF(ISBLANK($E77),0,VLOOKUP($E77,'Table of Hazards (AI only)'!$B$6:$P$129,9,)) -> 8.5 | M77: =IF(ISBLANK($E77),0,VLOOKUP($E77,'Table of Hazards (AI only)'!$B$6:$P$129,11,)) -> 27.166667 | O77: =IF(ISBLANK($E77),0,VLOOKUP($E77,'Table of Hazards (AI only)'!$B$6:$P$129,12,)) -> 0.3037476 | P77: =IF(ISBLANK($G77),0,VLOOKUP($G77,'Table of Hazards (AI only)'!$B$6:$P$129,8,)) -> 0 | R77: =IF(ISBLANK($G77),0,VLOOKUP($G77,'Table of Hazards (AI only)'!$B$6:$P$129,9,)) -> 0 | S77: =IF(ISBLANK($G77),0,VLOOKUP($G77,'Table of Hazards (AI only)'!$B$6:$P$129,11,)) -> 0 | U77: =IF(ISBLANK($G77),0,VLOOKUP($G77,'Table of Hazards (AI only)'!$B$6:$P$129,12,)) -> 0 | V77: =(($F77*J77)+($H77*P77))*$I77 -> 3.384 | X77: =(($F77*L77)+($H77*R77))*$I77 -> 1.224 | Y77: =(($F77*M77)+($H77*S77))*$I77 -> 3.912 | AA77: =(($F77*O77)+($H77*U77))*$I77 -> 0.043739654 | AC77: Mimic
... B108: Lettuce | C108: Damping-off | D108: Fosetyl-Aluminium | E108: Fosetyl-Aluminium | F108: 0.8 | I108: 2.5 | J108: =IF(ISBLANK($E108),0,VLOOKUP($E108,'Table of Hazards (AI only)'!$B$6:$P$129,8,)) -> 14.5 | L108: =IF(ISBLANK($E108),0,VLOOKUP($E108,'Table of Hazards (AI only)'!$B$6:$P$129,9,)) -> 5.5 | M108: =IF(ISBLANK($E108),0,VLOOKUP($E108,'Table of Hazards (AI only)'!$B$6:$P$129,11,)) -> 10.166667 | O108: =IF(ISBLANK($E108),0,VLOOKUP($E108,'Table of Hazards (AI only)'!$B$6:$P$129,12,)) -> 0.3037476 | P108: =IF(ISBLANK($G108),0,VLOOKUP($G108,'Table of Hazards (AI only)'!$B$6:$P$129,8,)) -> 0 | R108: =IF(ISBLANK($G108),0,VLOOKUP($G108,'Table of Hazards (AI only)'!$B$6:$P$129,9,)) -> 0 | S108: =IF(ISBLANK($G108),0,VLOOKUP($G108,'Table of Hazards (AI only)'!$B$6:$P$129,11,)) -> 0 | U108: =IF(ISBLANK($G108),0,VLOOKUP($G108,'Table of Hazards (AI only)'!$B$6:$P$129,12,)) -> 0 | V108: =(($F108*J108)+($H108*P108))*$I108 -> 29 | X108: =(($F108*L108)+($H108*R108))*$I108 -> 11 | Y108: =(($F108*M108)+($H108*S108))*$I108 -> 20.333333 | AA108: =(($F108*O108)+($H108*U108))*$I108 -> 0.60749519 | AC108: Aliette
B109: Lettuce | C109: Downy mildew | D109: Ametoctradin + Dimethomorph | E109: Ametoctradin | F109: 0.3 | G109: Dimethomorph | H109: 0.225 | I109: 0.8 | J109: =IF(ISBLANK($E109),0,VLOOKUP($E109,'Table of Hazards (AI only)'!$B$6:$P$129,8,)) -> 15 | L109: =IF(ISBLANK($E109),0,VLOOKUP($E109,'Table of Hazards (AI only)'!$B$6:$P$129,9,)) -> 3 | M109: =IF(ISBLANK($E109),0,VLOOKUP($E109,'Table of Hazards (AI only)'!$B$6:$P$129,11,)) -> 13.666667 | O109: =IF(ISBLANK($E109),0,VLOOKUP($E109,'Table of Hazards (AI only)'!$B$6:$P$129,12,)) -> 0.3037476 | P109: =IF(ISBLANK($G109),0,VLOOKUP($G109,'Table of Hazards (AI only)'!$B$6:$P$129,8,)) -> 27 | R109: =IF(ISBLANK($G109),0,VLOOKUP($G109,'Table of Hazards (AI only)'!$B$6:$P$129,9,)) -> 15 | S109: =IF(ISBLANK($G109),0,VLOOKUP($G109,'Table of Hazards (AI only)'!$B$6:$P$129,11,)) -> 16.666667 | U109: =IF(ISBLANK($G109),0,VLOOKUP($G109,'Table of Hazards (AI only)'!$B$6:$P$129,12,)) -> 0.3037476 | V109: =(($F109*J109)+($H109*P109))*$I109 -> 8.46 | X109: =(($F109*L109)+($H109*R109))*$I109 -> 3.42 | Y109: =(($F109*M109)+($H109*S109))*$I109 -> 6.28 | AA109: =(($F109*O109)+($H109*U109))*$I109 -> 0.12757399 | AC109: Enervin Duo
B110: Lettuce | C110: Downy mildew | D110: Ametoctradin + Metiram | E110: Ametoctradin | F110: 0.12 | G110: Metiram | H110: 0.44 | I110: 2 | J110: =IF(ISBLANK($E110),0,VLOOKUP($E110,'Table of Hazards (AI only)'!$B$6:$P$129,8,)) -> 15 | L110: =IF(ISBLANK($E110),0,VLOOKUP($E110,'Table of Hazards (AI only)'!$B$6:$P$129,9,)) -> 3 | M110: =IF(ISBLANK($E110),0,VLOOKUP($E110,'Table of Hazards (AI only)'!$B$6:$P$129,11,)) -> 13.666667 | O110: =IF(ISBLANK($E110),0,VLOOKUP($E110,'Table of Hazards (AI only)'!$B$6:$P$129,12,)) -> 0.3037476 | P110: =IF(ISBLANK($G110),0,VLOOKUP($G110,'Table of Hazards (AI only)'!$B$6:$P$129,8,)) -> 18.5 | R110: =IF(ISBLANK($G110),0,VLOOKUP($G110,'Table of Hazards (AI only)'!$B$6:$P$129,9,)) -> 3.5 | S110: =IF(ISBLANK($G110),0,VLOOKUP($G110,'Table of Hazards (AI only)'!$B$6:$P$129,11,)) -> 12.833333 | U110: =IF(ISBLANK($G110),0,VLOOKUP($G110,'Table of Hazards (AI only)'!$B$6:$P$129,12,)) -> 0.3037476 | V110: =(($F110*J110)+($H110*P110))*$I110 -> 19.88 | X110: =(($F110*L110)+($H110*R110))*$I110 -> 3.8 | Y110: =(($F110*M110)+($H110*S110))*$I110 -> 14.573333 | AA110: =(($F110*O110)+($H110*U110))*$I110 -> 0.34019731 | AC110: Prevint Top
B111: Lettuce | C111: Downy mildew | D111: Azoxystrobin + Difenoconazole | E111: Azoxystrobin | F111: 0.2 | G111: Difenoconazole | H111: 0.125 | I111: 1 | J111: =IF(ISBLANK($E111),0,VLOOKUP($E111,'Table of Hazards (AI only)'!$B$6:$P$129,8,)) -> 40.5 | L111: =IF(ISBLANK($E111),0,VLOOKUP($E111,'Table of Hazards (AI only)'!$B$6:$P$129,9,)) -> 25.5 | M111: =IF(ISBLANK($E111),0,VLOOKUP($E111,'Table of Hazards (AI only)'!$B$6:$P$129,11,)) -> 22.166667 | O111: =IF(ISBLANK($E111),0,VLOOKUP($E111,'Table of Hazards (AI only)'!$B$6:$P$129,12,)) -> 0.3037476 | P111: =IF(ISBLANK($G111),0,VLOOKUP($G111,'Table of Hazards (AI only)'!$B$6:$P$129,8,)) -> 37 | R111: =IF(ISBLANK($G111),0,VLOOKUP($G111,'Table of Hazards (AI only)'!$B$6:$P$129,9,)) -> 19 | S111: =IF(ISBLANK($G111),0,VLOOKUP($G111,'Table of Hazards (AI only)'!$B$6:$P$129,11,)) -> 18 | U111: =IF(ISBLANK($G111),0,VLOOKUP($G111,'Table of Hazards (AI only)'!$B$6:$P$129,12,)) -> 0.3037476 | V111: =(($F111*J111)+($H111*P111))*$I111 -> 12.725 | X111: =(($F111*L111)+($H111*R111))*$I111 -> 7.475 | Y111: =(($F111*M111)+($H111*S111))*$I111 -> 6.6833333 | AA111: =(($F111*O111)+($H111*U111))*$I111 -> 0.098717969 | AC111: Ortiva Top SC
B112: Lettuce | C112: Downy mildew | D112: Fenamidone + Fosetyl-Aluminium | E112: Fenamidone | F112: 0.044 | G112: Fosetyl-Aluminium | H112: 0.667 | I112: 2.25 | J112: =IF(ISBLANK($E112),0,VLOOKUP($E112,'Table of Hazards (AI only)'!$B$6:$P$129,8,)) -> 18.5 | L112: =IF(ISBLANK($E112),0,VLOOKUP($E112,'Table of Hazards (AI only)'!$B$6:$P$129,9,)) -> 3.5 | M112: =IF(ISBLANK($E112),0,VLOOKUP($E112,'Table of Hazards (AI only)'!$B$6:$P$129,11,)) -> 18.166667 | O112: =IF(ISBLANK($E112),0,VLOOKUP($E112,'Table of Hazards (AI only)'!$B$6:$P$129,12,)) -> 0.3037476 | P112: =IF(ISBLANK($G112),0,VLOOKUP($G112,'Table of Hazards (AI only)'!$B$6:$P$129,8,)) -> 14.5 | R112: =IF(ISBLANK($G112),0,VLOOKUP($G112,'Table of Hazards (AI only)'!$B$6:$P$129,9,)) -> 5.5 | S112: =IF(ISBLANK($G112),0,VLOOKUP($G112,'Table of Hazards (AI only)'!$B$6:$P$129,11,)) -> 10.166667 | U112: =IF(ISBLANK($G112),0,VLOOKUP($G112,'Table of Hazards (AI only)'!$B$6:$P$129,12,)) -> 0.3037476 | V112: =(($F112*J112)+($H112*P112))*$I112 -> 23.592375 | X112: =(($F112*L112)+($H112*R112))*$I112 -> 8.600625 | Y112: =(($F112*M112)+($H112*S112))*$I112 -> 17.056125 | AA112: =(($F112*O112)+($H112*U112))*$I112 -> 0.48592022 | AC112: Elicio
B113: Lettuce | C113: Downy mildew | D113: Fluopicolide + Propamocarb | E113: Fluopicolide | F113: 0.0625 | G113: Propamocarb | H113: 0.625 | I113: 1.5 | J113: =IF(ISBLANK($E113),0,VLOOKUP($E113,'Table of Hazards (AI only)'!$B$6:$P$129,8,)) -> 18.5 | L113: =IF(ISBLANK($E113),0,VLOOKUP($E113,'Table of Hazards (AI only)'!$B$6:$P$129,9,)) -> 9.5 | M113: =IF(ISBLANK($E113),0,VLOOKUP($E113,'Table of Hazards (AI only)'!$B$6:$P$129,11,)) -> 14.833333 | O113: =IF(ISBLANK($E113),0,VLOOKUP($E113,'Table of Hazards (AI only)'!$B$6:$P$129,12,)) -> 0.3037476 | P113: =IF(ISBLANK($G113),0,VLOOKUP($G113,'Table of Hazards (AI only)'!$B$6:$P$129,8,)) -> 25.5 | R113: =IF(ISBLANK($G113),0,VLOOKUP($G113,'Table of Hazards (AI only)'!$B$6:$P$129,9,)) -> 10.5 | S113: =IF(ISBLANK($G113),0,VLOOKUP($G113,'Table of Hazards (AI only)'!$B$6:$P$129,11,)) -> 15.166667 | U113: =IF(ISBLANK($G113),0,VLOOKUP($G113,'Table of Hazards (AI only)'!$B$6:$P$129,12,)) -> 0.3037476 | V113: =(($F113*J113)+($H113*P113))*$I113 -> 25.640625 | X113: =(($F113*L113)+($H113*R113))*$I113 -> 10.734375 | Y113: =(($F113*M113)+($H113*S113))*$I113 -> 15.609375 | AA113: =(($F113*O113)+($H113*U113))*$I113 -> 0.31323971 | AC113: Volare (or Infinito)
B114: Lettuce | C114: Downy mildew | D114: Propamocarb + Fosetyl | E114: Propamocarb | F114: 0.53 | G114: Fosetyl | H114: 0.31 | I114: 2.25 | J114: =IF(ISBLANK($E114),0,VLOOKUP($E114,'Table of Hazards (AI only)'!$B$6:$P$129,8,)) -> 25.5 | L114: =IF(ISBLANK($E114),0,VLOOKUP($E114,'Table of Hazards (AI only)'!$B$6:$P$129,9,)) -> 10.5 | M114: =IF(ISBLANK($E114),0,VLOOKUP($E114,'Table of Hazards (AI only)'!$B$6:$P$129,11,)) -> 15.166667 | O114: =IF(ISBLANK($E114),0,VLOOKUP($E114,'Table of Hazards (AI only)'!$B$6:$P$129,12,)) -> 0.3037476 | P114: =IF(ISBLANK($G114),0,VLOOKUP($G114,'Table of Hazards (AI only)'!$B$6:$P$129,8,)) -> 23 | R114: =IF(ISBLANK($G114),0,VLOOKUP($G114,'Table of Hazards (AI only)'!$B$6:$P$129,9,)) -> 11 | S114: =IF(ISBLANK($G114),0,VLOOKUP($G114,'Table of Hazards (AI only)'!$B$6:$P$129,11,)) -> 13 | U114: =IF(ISBLANK($G114),0,VLOOKUP($G114,'Table of Hazards (AI only)'!$B$6:$P$129,12,)) -> 0.3037476 | V114: =(($F114*J114)+($H114*P114))*$I114 -> 46.45125 | X114: =(($F114*L114)+($H114*R114))*$I114 -> 20.19375 | Y114: =(($F114*M114)+($H114*S114))*$I114 -> 27.15375 | AA114: =(($F114*O114)+($H114*U114))*$I114 -> 0.57408296 | AC114: Previcur Energy
B115: Lettuce | C115: Downy mildew | D115: Pyraclostrobin + Dimethomorph | E115: Pyraclostrobin | F115: 0.04 | G115: Dimethomorph | H115: 0.072 | I115: 2 | J115: =IF(ISBLANK($E115),0,VLOOKUP($E115,'Table of Hazards (AI only)'!$B$6:$P$129,8,)) -> 21 | L115: =IF(ISBLANK($E115),0,VLOOKUP($E115,'Table of Hazards (AI only)'!$B$6:$P$129,9,)) -> 6 | M115: =IF(ISBLANK($E115),0,VLOOKUP($E115,'Table of Hazards (AI only)'!$B$6:$P$129,11,)) -> 13.333333 | O115: =IF(ISBLANK($E115),0,VLOOKUP($E115,'Table of Hazards (AI only)'!$B$6:$P$129,12,)) -> 0.3037476 | P115: =IF(ISBLANK($G115),0,VLOOKUP($G115,'Table of Hazards (AI only)'!$B$6:$P$129,8,)) -> 27 | R115: =IF(ISBLANK($G115),0,VLOOKUP($G115,'Table of Hazards (AI only)'!$B$6:$P$129,9,)) -> 15 | S115: =IF(ISBLANK($G115),0,VLOOKUP($G115,'Table of Hazards (AI only)'!$B$6:$P$129,11,)) -> 16.666667 | U115: =IF(ISBLANK($G115),0,VLOOKUP($G115,'Table of Hazards (AI only)'!$B$6:$P$129,12,)) -> 0.3037476 | V115: =(($F115*J115)+($H115*P115))*$I115 -> 5.568 | X115: =(($F115*L115)+($H115*R115))*$I115 -> 2.64 | Y115: =(($F115*M115)+($H115*S115))*$I115 -> 3.4666667 | AA115: =(($F115*O115)+($H115*U115))*$I115 -> 0.068039462 | AC115: Cabrio Duo
B116: Lettuce | C116: Downy mildew | D116: Amisulbrom | E116: Amisulbrom | F116: 0.2 | I116: 0.6 | J116: =IF(ISBLANK($E116),0,VLOOKUP($E116,'Table of Hazards (AI only)'!$B$6:$P$129,8,)) -> 25.5 | L116: =IF(ISBLANK($E116),0,VLOOKUP($E116,'Table of Hazards (AI only)'!$B$6:$P$129,9,)) -> 4.5 | M116: =IF(ISBLANK($E116),0,VLOOKUP($E116,'Table of Hazards (AI only)'!$B$6:$P$129,11,)) -> 13.833333 | O116: =IF(ISBLANK($E116),0,VLOOKUP($E116,'Table of Hazards (AI only)'!$B$6:$P$129,12,)) -> 0.3037476 | P116: =IF(ISBLANK($G116),0,VLOOKUP($G116,'Table of Hazards (AI only)'!$B$6:$P$129,8,)) -> 0 | R116: =IF(ISBLANK($G116),0,VLOOKUP($G116,'Table of Hazards (AI only)'!$B$6:$P$129,9,)) -> 0 | S116: =IF(ISBLANK($G116),0,VLOOKUP($G116,'Table of Hazards (AI only)'!$B$6:$P$129,11,)) -> 0 | U116: =IF(ISBLANK($G116),0,VLOOKUP($G116,'Table of Hazards (AI only)'!$B$6:$P$129,12,)) -> 0 | V116: =(($F116*J116)+($H116*P116))*$I116 -> 3.06 | X116: =(($F116*L116)+($H116*R116))*$I116 -> 0.54 | Y116: =(($F116*M116)+($H116*S116))*$I116 -> 1.66 | AA116: =(($F116*O116)+($H116*U116))*$I116 -> 0.036449712 | AC116: Leimay
B117: Lettuce | C117: Downy mildew | D117: Azoxystrobin | E117: Azoxystrobin | F117: 0.25 | I117: 0.9 | J117: =IF(ISBLANK($E117),0,VLOOKUP($E117,'Table of Hazards (AI only)'!$B$6:$P$129,8,)) -> 40.5 | L117: =IF(ISBLANK($E117),0,VLOOKUP($E117,'Table of Hazards (AI only)'!$B$6:$P$129,9,)) -> 25.5 | M117: =IF(ISBLANK($E117),0,VLOOKUP($E117,'Table of Hazards (AI only)'!$B$6:$P$129,11,)) -> 22.166667 | O117: =IF(ISBLANK($E117),0,VLOOKUP($E117,'Table of Hazards (AI only)'!$B$6:$P$129,12,)) -> 0.3037476 | P117: =IF(ISBLANK($G117),0,VLOOKUP($G117,'Table of Hazards (AI only)'!$B$6:$P$129,8,)) -> 0 | R117: =IF(ISBLANK($G117),0,VLOOKUP($G117,'Table of Hazards (AI only)'!$B$6:$P$129,9,)) -> 0 | S117: =IF(ISBLANK($G117),0,VLOOKUP($G117,'Table of Hazards (AI only)'!$B$6:$P$129,11,)) -> 0 | U117: =IF(ISBLANK($G117),0,VLOOKUP($G117,'Table of Hazards (AI only)'!$B$6:$P$129,12,)) -> 0 | V117: =(($F117*J117)+($H117*P117))*$I117 -> 9.1125 | X117: =(($F117*L117)+($H117*R117))*$I117 -> 5.7375 | Y117: =(($F117*M117)+($H117*S117))*$I117 -> 4.9875 | AA117: =(($F117*O117)+($H117*U117))*$I117 -> 0.068343209 | AC117: Ortiva
B118: Lettuce | C118: Downy mildew | D118: Cymoxanil | E118: Cymoxanil | F118: 0.45 | I118: 0.45 | J118: =IF(ISBLANK($E118),0,VLOOKUP($E118,'Table of Hazards (AI only)'!$B$6:$P$129,8,)) -> 25.5 | L118: =IF(ISBLANK($E118),0,VLOOKUP($E118,'Table of Hazards (AI only)'!$B$6:$P$129,9,)) -> 4.5 | M118: =IF(ISBLANK($E118),0,VLOOKUP($E118,'Table of Hazards (AI only)'!$B$6:$P$129,11,)) -> 17.166667 | O118: =IF(ISBLANK($E118),0,VLOOKUP($E118,'Table of Hazards (AI only)'!$B$6:$P$129,12,)) -> 0.3037476 | P118: =IF(ISBLANK($G118),0,VLOOKUP($G118,'Table of Hazards (AI only)'!$B$6:$P$129,8,)) -> 0 | R118: =IF(ISBLANK($G118),0,VLOOKUP($G118,'Table of Hazards (AI only)'!$B$6:$P$129,9,)) -> 0 | S118: =IF(ISBLANK($G118),0,VLOOKUP($G118,'Table of Hazards (AI only)'!$B$6:$P$129,11,)) -> 0 | U118: =IF(ISBLANK($G118),0,VLOOKUP($G118,'Table of Hazards (AI only)'!$B$6:$P$129,12,)) -> 0 | V118: =(($F118*J118)+($H118*P118))*$I118 -> 5.16375 | X118: =(($F118*L118)+($H118*R118))*$I118 -> 0.91125 | Y118: =(($F118*M118)+($H118*S118))*$I118 -> 3.47625 | AA118: =(($F118*O118)+($H118*U118))*$I118 -> 0.061508888 | AC118: Cymbal
B119: Lettuce | C119: Downy mildew | D119: Copper oxychloride | E119: Copper oxychloride | F119: 0.25 | I119: 1.55 | J119: =IF(ISBLANK($E119),0,VLOOKUP($E119,'Table of Hazards (AI only)'!$B$6:$P$129,8,)) -> 37 | L119: =IF(ISBLANK($E119),0,VLOOKUP($E119,'Table of Hazards (AI only)'!$B$6:$P$129,9,)) -> 13 | M119: =IF(ISBLANK($E119),0,VLOOKUP($E119,'Table of Hazards (AI only)'!$B$6:$P$129,11,)) -> 53.333333 | O119: =IF(ISBLANK($E119),0,VLOOKUP($E119,'Table of Hazards (AI only)'!$B$6:$P$129,12,)) -> 0.3037476 | P119: =IF(ISBLANK($G119),0,VLOOKUP($G119,'Table of Hazards (AI only)'!$B$6:$P$129,8,)) -> 0 | R119: =IF(ISBLANK($G119),0,VLOOKUP($G119,'Table of Hazards (AI only)'!$B$6:$P$129,9,)) -> 0 | S119: =IF(ISBLANK($G119),0,VLOOKUP($G119,'Table of Hazards (AI only)'!$B$6:$P$129,11,)) -> 0 | U119: =IF(ISBLANK($G119),0,VLOOKUP($G119,'Table of Hazards (AI only)'!$B$6:$P$129,12,)) -> 0 | V119: =(($F119*J119)+($H119*P119))*$I119 -> 14.3375 | X119: =(($F119*L119)+($H119*R119))*$I119 -> 5.0375 | Y119: =(($F119*M119)+($H119*S119))*$I119 -> 20.666667 | AA119: =(($F119*O119)+($H119*U119))*$I119 -> 0.11770219 | AC119: Cyprus 25 DF
B120: Lettuce | C120: Downy mildew | D120: Fosetyl-Aluminium | E120: Fosetyl-Aluminium | F120: 0.8 | I120: 2.5 | J120: =IF(ISBLANK($E120),0,VLOOKUP($E120,'Table of Hazards (AI only)'!$B$6:$P$129,8,)) -> 14.5 | L120: =IF(ISBLANK($E120),0,VLOOKUP($E120,'Table of Hazards (AI only)'!$B$6:$P$129,9,)) -> 5.5 | M120: =IF(ISBLANK($E120),0,VLOOKUP($E120,'Table of Hazards (AI only)'!$B$6:$P$129,11,)) -> 10.166667 | O120: =IF(ISBLANK($E120),0,VLOOKUP($E120,'Table of Hazards (AI only)'!$B$6:$P$129,12,)) -> 0.3037476 | P120: =IF(ISBLANK($G120),0,VLOOKUP($G120,'Table of Hazards (AI only)'!$B$6:$P$129,8,)) -> 0 | R120: =IF(ISBLANK($G120),0,VLOOKUP($G120,'Table of Hazards (AI only)'!$B$6:$P$129,9,)) -> 0 | S120: =IF(ISBLANK($G120),0,VLOOKUP($G120,'Table of Hazards (AI only)'!$B$6:$P$129,11,)) -> 0 | U120: =IF(ISBLANK($G120),0,VLOOKUP($G120,'Table of Hazards (AI only)'!$B$6:$P$129,12,)) -> 0 | V120: =(($F120*J120)+($H120*P120))*$I120 -> 29 | X120: =(($F120*L120)+($H120*R120))*$I120 -> 11 | Y120: =(($F120*M120)+($H120*S120))*$I120 -> 20.333333 | AA120: =(($F120*O120)+($H120*U120))*$I120 -> 0.60749519 | AC120: Aliette
B121: Lettuce | C121: Downy mildew | D121: Iprovalicarb + Copper oxychloride | E121: Iprovalicarb | F121: 0.042 | G121: Copper oxychloride | H121: 0.406 | I121: 1.85 | J121: =IF(ISBLANK($E121),0,VLOOKUP($E121,'Table of Hazards (AI only)'!$B$6:$P$129,8,)) -> 38 | L121: =IF(ISBLANK($E121),0,VLOOKUP($E121,'Table of Hazards (AI only)'!$B$6:$P$129,9,)) -> 18 | M121: =IF(ISBLANK($E121),0,VLOOKUP($E121,'Table of Hazards (AI only)'!$B$6:$P$129,11,)) -> 25.666667 | O121: =IF(ISBLANK($E121),0,VLOOKUP($E121,'Table of Hazards (AI only)'!$B$6:$P$129,12,)) -> 0.3037476 | P121: =IF(ISBLANK($G121),0,VLOOKUP($G121,'Table of Hazards (AI only)'!$B$6:$P$129,8,)) -> 37 | R121: =IF(ISBLANK($G121),0,VLOOKUP($G121,'Table of Hazards (AI only)'!$B$6:$P$129,9,)) -> 13 | S121: =IF(ISBLANK($G121),0,VLOOKUP($G121,'Table of Hazards (AI only)'!$B$6:$P$129,11,)) -> 53.333333 | U121: =IF(ISBLANK($G121),0,VLOOKUP($G121,'Table of Hazards (AI only)'!$B$6:$P$129,12,)) -> 0.3037476 | V121: =(($F121*J121)+($H121*P121))*$I121 -> 30.7433 | X121: =(($F121*L121)+($H121*R121))*$I121 -> 11.1629 | Y121: =(($F121*M121)+($H121*S121))*$I121 -> 42.052967 | AA121: =(($F121*O121)+($H121*U121))*$I121 -> 0.25174601 | AC121: Melody Compact WG
B122: Lettuce | C122: Downy mildew | D122: Laminarin | E122: Laminarin | F122: 0.045 | I122: 2 | J122: =IF(ISBLANK($E122),0,VLOOKUP($E122,'Table of Hazards (AI only)'!$B$6:$P$129,8,)) -> 50 | L122: =IF(ISBLANK($E122),0,VLOOKUP($E122,'Table of Hazards (AI only)'!$B$6:$P$129,9,)) -> 20 | M122: =IF(ISBLANK($E122),0,VLOOKUP($E122,'Table of Hazards (AI only)'!$B$6:$P$129,11,)) -> 79.333333 | O122: =IF(ISBLANK($E122),0,VLOOKUP($E122,'Table of Hazards (AI only)'!$B$6:$P$129,12,)) -> 0.35170774 | P122: =IF(ISBLANK($G122),0,VLOOKUP($G122,'Table of Hazards (AI only)'!$B$6:$P$129,8,)) -> 0 | R122: =IF(ISBLANK($G122),0,VLOOKUP($G122,'Table of Hazards (AI only)'!$B$6:$P$129,9,)) -> 0 | S122: =IF(ISBLANK($G122),0,VLOOKUP($G122,'Table of Hazards (AI only)'!$B$6:$P$129,11,)) -> 0 | U122: =IF(ISBLANK($G122),0,VLOOKUP($G122,'Table of Hazards (AI only)'!$B$6:$P$129,12,)) -> 0 | V122: =(($F122*J122)+($H122*P122))*$I122 -> 4.5 | X122: =(($F122*L122)+($H122*R122))*$I122 -> 1.8 | Y122: =(($F122*M122)+($H122*S122))*$I122 -> 7.14 | AA122: =(($F122*O122)+($H122*U122))*$I122 -> 0.031653697 | AC122: Vacciplant
B123: Lettuce | C123: Downy mildew | D123: Mandipropamid | E123: Mandipropamid | F123: 0.25 | I123: 0.5 | J123: =IF(ISBLANK($E123),0,VLOOKUP($E123,'Table of Hazards (AI only)'!$B$6:$P$129,8,)) -> 10 | L123: =IF(ISBLANK($E123),0,VLOOKUP($E123,'Table of Hazards (AI only)'!$B$6:$P$129,9,)) -> 4 | M123: =IF(ISBLANK($E123),0,VLOOKUP($E123,'Table of Hazards (AI only)'!$B$6:$P$129,11,)) -> 10 | O123: =IF(ISBLANK($E123),0,VLOOKUP($E123,'Table of Hazards (AI only)'!$B$6:$P$129,12,)) -> 0.3037476 | P123: =IF(ISBLANK($G123),0,VLOOKUP($G123,'Table of Hazards (AI only)'!$B$6:$P$129,8,)) -> 0 | R123: =IF(ISBLANK($G123),0,VLOOKUP($G123,'Table of Hazards (AI only)'!$B$6:$P$129,9,)) -> 0 | S123: =IF(ISBLANK($G123),0,VLOOKUP($G123,'Table of Hazards (AI only)'!$B$6:$P$129,11,)) -> 0 | U123: =IF(ISBLANK($G123),0,VLOOKUP($G123,'Table of Hazards (AI only)'!$B$6:$P$129,12,)) -> 0 | V123: =(($F123*J123)+($H123*P123))*$I123 -> 1.25 | X123: =(($F123*L123)+($H123*R123))*$I123 -> 0.5 | Y123: =(($F123*M123)+($H123*S123))*$I123 -> 1.25 | AA123: =(($F123*O123)+($H123*U123))*$I123 -> 0.03796845 | AC123: Pergado SC
B124: Lettuce | C124: Downy mildew | D124: Metalaxyl + Copper oxychloride | E124: Metalaxyl | F124: 0.049 | G124: Copper oxychloride | H124: 0.259 | I124: 0.4 | J124: =IF(ISBLANK($E124),0,VLOOKUP($E124,'Table of Hazards (AI only)'!$B$6:$P$129,8,)) -> 20 | L124: =IF(ISBLANK($E124),0,VLOOKUP($E124,'Table of Hazards (AI only)'!$B$6:$P$129,9,)) -> 12 | M124: =IF(ISBLANK($E124),0,VLOOKUP($E124,'Table of Hazards (AI only)'!$B$6:$P$129,11,)) -> 36.666667 | O124: =IF(ISBLANK($E124),0,VLOOKUP($E124,'Table of Hazards (AI only)'!$B$6:$P$129,12,)) -> 0.3037476 | P124: =IF(ISBLANK($G124),0,VLOOKUP($G124,'Table of Hazards (AI only)'!$B$6:$P$129,8,)) -> 37 | R124: =IF(ISBLANK($G124),0,VLOOKUP($G124,'Table of Hazards (AI only)'!$B$6:$P$129,9,)) -> 13 | S124: =IF(ISBLANK($G124),0,VLOOKUP($G124,'Table of Hazards (AI only)'!$B$6:$P$129,11,)) -> 53.333333 | U124: =IF(ISBLANK($G124),0,VLOOKUP($G124,'Table of Hazards (AI only)'!$B$6:$P$129,12,)) -> 0.3037476 | V124: =(($F124*J124)+($H124*P124))*$I124 -> 4.2252 | X124: =(($F124*L124)+($H124*R124))*$I124 -> 1.582 | Y124: =(($F124*M124)+($H124*S124))*$I124 -> 6.244 | AA124: =(($F124*O124)+($H124*U124))*$I124 -> 0.037421704 | AC124: Kasko R
B125: Lettuce | C125: Downy mildew | D125: Metalaxyl | E125: Metalaxyl | F125: 0.049 | I125: 0.4 | J125: =IF(ISBLANK($E125),0,VLOOKUP($E125,'Table of Hazards (AI only)'!$B$6:$P$129,8,)) -> 20 | L125: =IF(ISBLANK($E125),0,VLOOKUP($E125,'Table of Hazards (AI only)'!$B$6:$P$129,9,)) -> 12 | M125: =IF(ISBLANK($E125),0,VLOOKUP($E125,'Table of Hazards (AI only)'!$B$6:$P$129,11,)) -> 36.666667 | O125: =IF(ISBLANK($E125),0,VLOOKUP($E125,'Table of Hazards (AI only)'!$B$6:$P$129,12,)) -> 0.3037476 | P125: =IF(ISBLANK($G125),0,VLOOKUP($G125,'Table of Hazards (AI only)'!$B$6:$P$129,8,)) -> 0 | R125: =IF(ISBLANK($G125),0,VLOOKUP($G125,'Table of Hazards (AI only)'!$B$6:$P$129,9,)) -> 0 | S125: =IF(ISBLANK($G125),0,VLOOKUP($G125,'Table of Hazards (AI only)'!$B$6:$P$129,11,)) -> 0 | U125: =IF(ISBLANK($G125),0,VLOOKUP($G125,'Table of Hazards (AI only)'!$B$6:$P$129,12,)) -> 0 | V125: =(($F125*J125)+($H125*P125))*$I125 -> 0.392 | X125: =(($F125*L125)+($H125*R125))*$I125 -> 0.2352 | Y125: =(($F125*M125)+($H125*S125))*$I125 -> 0.71866667 | AA125: =(($F125*O125)+($H125*U125))*$I125 -> 0.0059534529
B126: Lettuce | C126: Downy mildew | D126: Metalaxyl-M | E126: Metalaxyl-M | F126: 0.465 | I126: 1.5 | J126: =IF(ISBLANK($E126),0,VLOOKUP($E126,'Table of Hazards (AI only)'!$B$6:$P$129,8,)) -> 10 | L126: =IF(ISBLANK($E126),0,VLOOKUP($E126,'Table of Hazards (AI only)'!$B$6:$P$129,9,)) -> 4 | M126: =IF(ISBLANK($E126),0,VLOOKUP($E126,'Table of Hazards (AI only)'!$B$6:$P$129,11,)) -> 10 | O126: =IF(ISBLANK($E126),0,VLOOKUP($E126,'Table of Hazards (AI only)'!$B$6:$P$129,12,)) -> 0.3037476 | P126: =IF(ISBLANK($G126),0,VLOOKUP($G126,'Table of Hazards (AI only)'!$B$6:$P$129,8,)) -> 0 | R126: =IF(ISBLANK($G126),0,VLOOKUP($G126,'Table of Hazards (AI only)'!$B$6:$P$129,9,)) -> 0 | S126: =IF(ISBLANK($G126),0,VLOOKUP($G126,'Table of Hazards (AI only)'!$B$6:$P$129,11,)) -> 0 | U126: =IF(ISBLANK($G126),0,VLOOKUP($G126,'Table of Hazards (AI only)'!$B$6:$P$129,12,)) -> 0 | V126: =(($F126*J126)+($H126*P126))*$I126 -> 6.975 | X126: =(($F126*L126)+($H126*R126))*$I126 -> 2.79 | Y126: =(($F126*M126)+($H126*S126))*$I126 -> 6.975 | AA126: =(($F126*O126)+($H126*U126))*$I126 -> 0.21186395 | AC126: Flare Gold [or Ridomil Gold SL (0.049. 0.259)
B127: Lettuce | C127: Downy Mildew | D127: Potassium phosphonates | E127: Potassium phosphonates | F127: 0.517 | I127: 2 | J127: =IF(ISBLANK($E127),0,VLOOKUP($E127,'Table of Hazards (AI only)'!$B$6:$P$129,8,)) -> 20 | L127: =IF(ISBLANK($E127),0,VLOOKUP($E127,'Table of Hazards (AI only)'!$B$6:$P$129,9,)) -> 10 | M127: =IF(ISBLANK($E127),0,VLOOKUP($E127,'Table of Hazards (AI only)'!$B$6:$P$129,11,)) -> 26 | O127: =IF(ISBLANK($E127),0,VLOOKUP($E127,'Table of Hazards (AI only)'!$B$6:$P$129,12,)) -> 0.3037476 | P127: =IF(ISBLANK($G127),0,VLOOKUP($G127,'Table of Hazards (AI only)'!$B$6:$P$129,8,)) -> 0 | R127: =IF(ISBLANK($G127),0,VLOOKUP($G127,'Table of Hazards (AI only)'!$B$6:$P$129,9,)) -> 0 | S127: =IF(ISBLANK($G127),0,VLOOKUP($G127,'Table of Hazards (AI only)'!$B$6:$P$129,11,)) -> 0 | U127: =IF(ISBLANK($G127),0,VLOOKUP($G127,'Table of Hazards (AI only)'!$B$6:$P$129,12,)) -> 0 | V127: =(($F127*J127)+($H127*P127))*$I127 -> 20.68 | X127: =(($F127*L127)+($H127*R127))*$I127 -> 10.34 | Y127: =(($F127*M127)+($H127*S127))*$I127 -> 26.884 | AA127: =(($F127*O127)+($H127*U127))*$I127 -> 0.31407502 | AC127: Century SL
B128: Lettuce | C128: Downy mildew | D128: Propamocarb | E128: Propamocarb | F128: 0.667 | I128: 1.5 | J128: =IF(ISBLANK($E128),0,VLOOKUP($E128,'Table of Hazards (AI only)'!$B$6:$P$129,8,)) -> 25.5 | L128: =IF(ISBLANK($E128),0,VLOOKUP($E128,'Table of Hazards (AI only)'!$B$6:$P$129,9,)) -> 10.5 | M128: =IF(ISBLANK($E128),0,VLOOKUP($E128,'Table of Hazards (AI only)'!$B$6:$P$129,11,)) -> 15.166667 | O128: =IF(ISBLANK($E128),0,VLOOKUP($E128,'Table of Hazards (AI only)'!$B$6:$P$129,12,)) -> 0.3037476 | P128: =IF(ISBLANK($G128),0,VLOOKUP($G128,'Table of Hazards (AI only)'!$B$6:$P$129,8,)) -> 0 | R128: =IF(ISBLANK($G128),0,VLOOKUP($G128,'Table of Hazards (AI only)'!$B$6:$P$129,9,)) -> 0 | S128: =IF(ISBLANK($G128),0,VLOOKUP($G128,'Table of Hazards (AI only)'!$B$6:$P$129,11,)) -> 0 | U128: =IF(ISBLANK($G128),0,VLOOKUP($G128,'Table of Hazards (AI only)'!$B$6:$P$129,12,)) -> 0 | V128: =(($F128*J128)+($H128*P128))*$I128 -> 25.51275 | X128: =(($F128*L128)+($H128*R128))*$I128 -> 10.50525 | Y128: =(($F128*M128)+($H128*S128))*$I128 -> 15.17425 | AA128: =(($F128*O128)+($H128*U128))*$I128 -> 0.30389947 | AC128: Previter
